Workbook

Sheet README
A1: Valuation Workpaper — Cover & User Guide
A2: Auto-generated by the Orionmano valuation pipeline. Read this sheet first. Every figure on every downstream tab is driven by a named range on the Inputs sheet.
B4: Engagement metadata
B5: Company | C5: =company_name -> Sample TechCo Holdings Limited
B6: Country of incorporation | C6: =company_country -> SG
B7: Industry (US) | C7: =company_industry_us -> Software (Internet)
B8: Industry (Global) | C8: =company_industry_global -> Software (Internet)
B9: Report purpose | C9: =report_purpose -> IPO pricing
B10: Accounting standard | C10: =accounting_standard -> IFRS
B11: Client (engaging party) | C11: =client_name -> Sample TechCo Holdings Limited
B12: Engagement partner | C12: =engagement_team_partner -> A. Lee
B13: Engagement manager | C13: =engagement_team_manager -> T. Wong
B14: Department | C14: =engagement_department -> Valuation Advisory
B17: Currency & units
B18: Reporting currency | C18: =currency -> USD
B19: Unit | C19: =unit -> '000
B20: Secondary currency | C20: =currency_alt -> 0
B21: FX rate to alt | C21: =fx_rate_alt -> 0
B22: Note | C22: All monetary values throughout this workbook are denominated in [currency] [unit] unless explicitly stated otherwise.
B24: Valuation methodologies & weights
B25: Methodology | C25: Weight | D25: Sheet | E25: Notes
B26: Discounted Cash Flow (DCF) | C26: =weight_dcf -> 0.5 | D26: DCF / DCF (Independent) | E26: Two-scenario WACC; Gordon-growth or exit-multiple terminal.
B27: Comparable Companies (CoCo) | C27: =weight_comps -> 0.3 | D27: Comps / CoCo Multiples | E27: Q1/Median/Q3 NTM trading multiples × target metrics.
B28: Precedent Transactions | C28: =weight_precedent -> 0.2 | D28: Precedent | E28: Mean EV/EBITDA × Y1 EBITDA from observed M&A deals.
B29: Net Asset Value (NAV) | C29: =weight_nav -> 0 | D29: — | E29: Asset-based; typically 0% for going-concern targets.
B30: Total weight | C30: =weight_dcf+weight_comps+weight_precedent+weight_nav -> 1 | D30: Must equal 100%
B33: Sheet index
B34: # | C34: Sheet | D34: Purpose
B35: 1 | C35: README | D35: Instructions, version, manual-input checklist
B36: 2 | C36: Dashboard | D36: High-level outputs: EV, Net debt, Surplus, Equity, WACC, terminal g + benchmark charts
B37: 3 | C37: Inputs | D37: Single source of truth — all driver parameters
B38: 4 | C38: Historical FS | D38: 3-5 yr audited income statement + balance sheet (PBC raw)
B39: 5 | C39: Projections | D39: Year-by-year forecast lines driven by Inputs
B40: 6 | C40: DCF | D40: FCFF schedule, partial-year discount, PV, terminal value
B41: 7 | C41: DCF (Independent) | D41: Parallel scenario with independent WACC range
B42: 8 | C42: Comps | D42: Apply CoCo multiples to target metrics; implied EV/Sales, EV/EBITDA, P/E
B43: 9 | C43: Football Field | D43: Valuation range chart per methodology + weighted selected range
B44: 10 | C44: WACC | D44: Full Ke + Kd build with Per-Mgmt and Independent scenarios
B45: 11 | C45: CoCo Selection | D45: Comparable company selection with tier flags + market cap
... B54: 20 | C54: Valuation Summary | D54: Final EV -> Equity -> Per share with all weighting and adjustments
B57: Items requiring post-export manual input
B58: # | C58: Item | D58: Sheet | E58: Cell / range | F58: Notes
B59: 1 | C59: Selected football-field band (analyst override) | D59: Inputs / Football Field | E59: selected_low / selected_mid / selected_high | F59: Producer auto-fills initial estimate (±15% around weighted mid). Adjust to your judgment band before finalizing.
B60: 2 | C60: shares_outstanding_diluted | D60: Inputs | E60: shares_outstanding_diluted | F60: Required for diluted per-share output. Pull from prospectus / cap table if not auto-filled.
B61: 3 | C61: Coco/Precedent metric values flagged as null | D61: CoCo Multiples / Margins / Ratios / Precedent | E61: Cells with INPUT_FILL background | F61: Producer leaves a metric null when source data is unavailable. Fill from Capital IQ / Bloomberg if you obtain it.
B62: 4 | C62: Engagement team names | D62: Inputs | E62: engagement_team_partner / engagement_team_manager | F62: Defaults to 'TBD' if engagement letter not provided. Replace with actual partner / manager names.
B64: Reference data — refresh schedule
B65: Dataset | C65: Cadence | D65: Source | E65: URL / vendor
B66: Country ERP | C66: Annual | D66: Damodaran NYU Stern country risk premium | E66: pages.stern.nyu.edu/~adamodar/
B67: Industry Averages | C67: Annual | D67: Damodaran US industry betas / margins / multiples | E67: pages.stern.nyu.edu/~adamodar/
B68: Risk-free rate | C68: Per engagement | D68: 10y UST yield as at valuation date | E68: Bloomberg / Capital IQ
B69: ERP | C69: Per engagement | D69: Implied / historical ERP for mature markets | E69: Damodaran implied ERP
B71: Disclaimer & use restriction
B72: This workpaper has been prepared for the express purpose stated above and for the exclusive use of the engaging party. It must not be reproduced, distributed, or relied upon by any other party without prior written consent. The valuation reflects conditions and information available as at the valuation date; subsequent events are not incorporated. All inputs derive from sources cited in the audit-trail columns of the Inputs sheet — refer to those entries for source documents and assumptions. This is not a fairness opinion, audit, or attestation engagement under PCAOB / AICPA standards unless explicitly designated.

Sheet Dashboard
A1: Valuation Dashboard
A2: =company_name & " · " & report_purpose -> Sample TechCo Holdings Limited · IPO pricing
B4: Headline values (Per-Management scenario)
C5: Enterprise Value | D5: Equity (after DLOM/DLOC) | E5: Per share (basic) | F5: WACC | G5: Terminal growth
C6: ='Valuation Summary'!C7 -> 327299.06 | D6: ='Valuation Summary'!C10 -> 239563.36 | E6: ='Valuation Summary'!C16 -> 0.95825345 | F6: =wacc_per_mgmt -> 0.13905529 | G6: =terminal_growth_rate -> 0.03
B8: Independent scenario | C8: ='Valuation Summary'!D7 -> 273676.53 | D8: ='Valuation Summary'!D10 -> 203100.04 | E8: ='Valuation Summary'!D16 -> 0.81240016 | F8: =wacc_indep -> 0.1558895 | G8: =terminal_growth_rate -> 0.03
B11: Methodology range — enterprise value
B12: Methodology | C12: Low | D12: Mid | E12: High | F12: Weight | G12: Weighted mid | H12: Notes
B13: DCF (across scenarios) | C13: ='Football Field'!B7 -> 273676.53 | D13: ='Football Field'!C7 -> 300487.8 | E13: ='Football Field'!D7 -> 327299.06 | F13: =weight_dcf -> 0.5 | G13: ='Football Field'!F7 -> 150243.9 | H13: Per-Mgmt vs Independent WACC.
B14: Comparable Companies | C14: ='Football Field'!B11 -> 50820.5 | D14: ='Football Field'!C11 -> 227069.33 | E14: ='Football Field'!D11 -> 485750 | F14: =weight_comps -> 0.3 | G14: ='Football Field'!F11 -> 68120.8 | H14: Cross-check vs DCF (±10% band).
B15: Precedent Transactions | C15: ='Football Field'!B12 -> 0 | D15: ='Football Field'!C12 -> 243600 | E15: ='Football Field'!D12 -> 0 | F15: =weight_precedent -> 0.2 | G15: ='Football Field'!F12 -> 48720 | H15: Cross-check vs DCF (±10% band).
B17: Concluded EV (DCF primary) | G17: ='Football Field'!F16 -> 267084.7
B18: Selected band (low / mid / high) | C18: =selected_low -> 0 | D18: =selected_mid -> 0 | E18: =selected_high -> 0
B20: CoCo trading multiples — benchmark stats
B21: Multiple | C21: Min | D21: Q1 | E21: Median | F21: Q3 | G21: Max | H21: Mean
B22: EV / Sales NTM | C22: ='CoCo Multiples'!F42 -> 2.7 | D22: ='CoCo Multiples'!F41 -> 3.075 | E22: ='CoCo Multiples'!F39 -> 3.35 | F22: ='CoCo Multiples'!F38 -> 3.775 | G22: ='CoCo Multiples'!F37 -> 4.6 | H22: ='CoCo Multiples'!F40 -> 3.5
B23: EV / EBITDA NTM | C23: ='CoCo Multiples'!H42 -> 12 | D23: ='CoCo Multiples'!H41 -> 13.125 | E23: ='CoCo Multiples'!H39 -> 14.25 | F23: ='CoCo Multiples'!H38 -> 15.75 | G23: ='CoCo Multiples'!H37 -> 18 | H23: ='CoCo Multiples'!H40 -> 14.625
B24: P / E NTM | C24: ='CoCo Multiples'!J42 -> 18 | D24: ='CoCo Multiples'!J41 -> 19.5 | E24: ='CoCo Multiples'!J39 -> 21 | F24: ='CoCo Multiples'!J38 -> 23 | G24: ='CoCo Multiples'!J37 -> 26 | H24: ='CoCo Multiples'!J40 -> 21.5
B25: EV / Sales LTM | C25: ='CoCo Multiples'!E42 -> 3.1 | D25: ='CoCo Multiples'!E41 -> 3.625 | E25: ='CoCo Multiples'!E39 -> 4 | F25: ='CoCo Multiples'!E38 -> 4.525 | G25: ='CoCo Multiples'!E37 -> 5.5 | H25: ='CoCo Multiples'!E40 -> 4.15
B26: EV / EBITDA LTM | C26: ='CoCo Multiples'!G42 -> 14 | D26: ='CoCo Multiples'!G41 -> 15.875 | E26: ='CoCo Multiples'!G39 -> 17.25 | F26: ='CoCo Multiples'!G38 -> 19 | G26: ='CoCo Multiples'!G37 -> 22 | H26: ='CoCo Multiples'!G40 -> 17.625
B27: P / E LTM | C27: ='CoCo Multiples'!I42 -> 21 | D27: ='CoCo Multiples'!I41 -> 23.25 | E27: ='CoCo Multiples'!I39 -> 25 | F27: ='CoCo Multiples'!I38 -> 27.5 | G27: ='CoCo Multiples'!I37 -> 32 | H27: ='CoCo Multiples'!I40 -> 25.75
B30: Sensitivity — EV (WACC × terminal growth, Per-Mgmt)
B31: Full grid is on the Sensitivity tab. This panel shows EV at the base case (centre cell) plus ±1 step in each direction.
B32: WACC ↓ / g → | C32: g − 1 step | D32: Base g | E32: g + 1 step
B33: WACC − 1 step | C33: =INDEX(Sensitivity!C7:M17,sens_wacc_count,sens_terminal_g_count) -> 321729.72 | D33: =INDEX(Sensitivity!C7:M17,sens_wacc_count,sens_terminal_g_count+1) -> 334962.23 | E33: =INDEX(Sensitivity!C7:M17,sens_wacc_count,sens_terminal_g_count+2) -> 349530.61
B34: Base WACC | C34: =INDEX(Sensitivity!C7:M17,sens_wacc_count+1,sens_terminal_g_count) -> 304415.7 | D34: =INDEX(Sensitivity!C7:M17,sens_wacc_count+1,sens_terminal_g_count+1) -> 316279.27 | E34: =INDEX(Sensitivity!C7:M17,sens_wacc_count+1,sens_terminal_g_count+2) -> 329282.96
B35: WACC + 1 step | C35: =INDEX(Sensitivity!C7:M17,sens_wacc_count+2,sens_terminal_g_count) -> 288605.39 | D35: =INDEX(Sensitivity!C7:M17,sens_wacc_count+2,sens_terminal_g_count+1) -> 299285.38 | E35: =INDEX(Sensitivity!C7:M17,sens_wacc_count+2,sens_terminal_g_count+2) -> 310944.68
B38: Backtesting — historical revenue vs Y0 base
B39: Sanity check: Y0 base revenue (cascading into Projections) should equal the most-recent FY-1 audited revenue.
C40: FY-3 | D40: FY-2 | E40: FY-1 | F40: Y0 (Projections) | G40: Δ Y0 vs FY-1
B41: Revenue | C41: ='Historical FS'!E7 -> 86000 | D41: ='Historical FS'!F7 -> 95000 | E41: ='Historical FS'!G7 -> 100000 | F41: =revenue_y0 -> 100000 | G41: =IFERROR(revenue_y0/'Historical FS'!G7-1,"n/a") -> 0
B42: EBITDA | C42: ='Historical FS'!E13 -> 8600 | D42: ='Historical FS'!F13 -> 9500 | E42: ='Historical FS'!G13 -> 10000 | F42: — | G42: —
B45: Open the web dashboard (Orionmano · Companies · this entity · Valuation tab) for interactive Football Field, Sensitivity heatmap, FCFF projection, and CoCo multiple charts.

Sheet Inputs
A1: Inputs — single source of truth for all valuation parameters
A2: Every parameter below is a named range. Downstream sheets reference these by name, not by cell coordinate. The Source / Source detail / Notes columns record the audit trail.
A4: id | B4: Parameter | C4: Type | D4: Value (Per Mgmt) | E4: Value (Independent) | F4: Source | G4: Source detail | H4: Notes
A6: Section A — Engagement metadata (Core)
A7: company_name | B7: Company name | C7: text | D7: Sample TechCo Holdings Limited | F7: Engagement Letter | G7: EL dated 2026-03-15
A8: company_country | B8: Country of incorporation | C8: enum | D8: SG
A9: company_industry_us | B9: Industry (US classification) | C9: enum | D9: Software (Internet)
A10: company_industry_global | B10: Industry (Global classification) | C10: enum | D10: Software (Internet)
A11: report_purpose | B11: Report purpose | C11: enum | D11: IPO pricing
A12: accounting_standard | B12: Accounting standard | C12: enum | D12: IFRS
A13: engagement_team_partner | B13: Engagement partner | C13: text | D13: A. Lee
A14: engagement_team_manager | B14: Engagement manager | C14: text | D14: T. Wong
A15: engagement_department | B15: Department | C15: text | D15: Valuation Advisory
A16: client_name | B16: Client (engaging party) | C16: text | D16: Sample TechCo Holdings Limited
A18: Section B — Currency & units (Core)
A19: currency | B19: Reporting currency | C19: enum | D19: USD
A20: unit | B20: Unit of presentation | C20: enum | D20: '000
A21: currency_alt | B21: Secondary display currency (optional) | C21: enum
A22: fx_rate_alt | B22: FX rate to alternate currency | C22: number
A24: Section C — Tax rule (Core)
A25: tax_jurisdiction | B25: Tax jurisdiction | C25: enum | D25: SG
A26: tax_type | B26: Tax structure | C26: enum | D26: flat | H26: flat | two_tier | progressive
A27: tax_rate_low | B27: Low-tier rate | C27: percentage | D27: 0.17
A28: tax_rate_high | B28: High-tier rate (or flat rate) | C28: percentage | D28: 0.17 | F28: Manual | G28: Singapore corporate tax rate 17% flat
A29: tax_threshold | B29: Threshold between tiers | C29: currency
A30: tax_effective_rate | B30: Effective rate (override) | C30: percentage
A32: Section D — Projection drivers (Core)
A33: projection_years | B33: Explicit forecast years | C33: number | D33: 5
A34: revenue_growth_method | B34: Revenue growth method | C34: enum | D34: per_year | H34: flat | declining | staged | per_year
A35: revenue_y0 | B35: Revenue base (Y0 / LTM) | C35: currency | D35: 100000 | F35: Audited FS | G35: FY2025 Audited FS, Consolidated P&L, p.34 | H35: Last full reported year
A36: nwc_y0 | B36: Net working capital (Y0) | C36: currency | D36: 8000 | F36: Audited FS | G36: FY2025 Audited FS, Balance Sheet, p.36 (current assets ex-cash − current liabilities ex-debt)
A37: gross_profit_y0 | B37: Gross profit (Y0) | C37: currency | H37: Audited Y0 gross profit; populates the Projections Y0 gross-profit cell
A38: opex_y0 | B38: Operating expenses (Y0) | C38: currency | H38: Audited Y0 opex (negative); populates the Projections Y0 opex cell
A39: ebitda_y0 | B39: EBITDA (Y0) | C39: currency | H39: Audited Y0 EBITDA; populates the Projections Y0 EBITDA cell
A40: ebit_y0 | B40: EBIT (Y0) | C40: currency | H40: Audited Y0 EBIT; populates the Projections Y0 EBIT cell
A41: tax_y0 | B41: Tax (Y0) | C41: currency | H41: Audited Y0 tax expense (negative); populates the Projections Y0 tax cell
A42: net_income_y0 | B42: Net income (Y0) | C42: currency | H42: Audited Y0 net income; populates the Projections Y0 net-income cell
A43: revenue_growth_y1 | B43: Revenue growth (total) (Y1) | C43: percentage | D43: 0.45
A44: revenue_growth_y2 | B44: Revenue growth (total) (Y2) | C44: percentage | D44: 0.3
A45: revenue_growth_y3 | B45: Revenue growth (total) (Y3) | C45: percentage | D45: 0.22
A46: revenue_growth_y4 | B46: Revenue growth (total) (Y4) | C46: percentage | D46: 0.16
A47: revenue_growth_y5 | B47: Revenue growth (total) (Y5) | C47: percentage | D47: 0.1
A48: revenue_growth_primary_y1 | B48: Revenue growth (primary, conservative) (Y1) | C48: percentage
A49: revenue_growth_primary_y2 | B49: Revenue growth (primary, conservative) (Y2) | C49: percentage
A50: revenue_growth_primary_y3 | B50: Revenue growth (primary, conservative) (Y3) | C50: percentage
A51: revenue_growth_primary_y4 | B51: Revenue growth (primary, conservative) (Y4) | C51: percentage
A52: revenue_growth_primary_y5 | B52: Revenue growth (primary, conservative) (Y5) | C52: percentage
A53: gross_margin_y1 | B53: Gross margin (Y1) | C53: percentage | D53: 0.62
A54: gross_margin_y2 | B54: Gross margin (Y2) | C54: percentage | D54: 0.64
A55: gross_margin_y3 | B55: Gross margin (Y3) | C55: percentage | D55: 0.65
A56: gross_margin_y4 | B56: Gross margin (Y4) | C56: percentage | D56: 0.65
A57: gross_margin_y5 | B57: Gross margin (Y5) | C57: percentage | D57: 0.66
A58: opex_pct_revenue_y1 | B58: Opex % of revenue (Y1) | C58: percentage | D58: 0.55
A59: opex_pct_revenue_y2 | B59: Opex % of revenue (Y2) | C59: percentage | D59: 0.5
A60: opex_pct_revenue_y3 | B60: Opex % of revenue (Y3) | C60: percentage | D60: 0.45
A61: opex_pct_revenue_y4 | B61: Opex % of revenue (Y4) | C61: percentage | D61: 0.42
A62: opex_pct_revenue_y5 | B62: Opex % of revenue (Y5) | C62: percentage | D62: 0.4
A63: capex_pct_revenue_y1 | B63: Capex % of revenue (Y1) | C63: percentage | D63: 0.06
A64: capex_pct_revenue_y2 | B64: Capex % of revenue (Y2) | C64: percentage | D64: 0.05
... A77: nwc_pct_sales_y5 | B77: Working capital % of sales (Y5) | C77: percentage | D77: 0.08
A79: Section E — Terminal value (Core)
A80: terminal_method | B80: Terminal value method | C80: enum | D80: gordon_growth | H80: gordon_growth | exit_multiple
A81: terminal_growth_rate | B81: Terminal growth rate | C81: percentage | D81: 0.03 | F81: Manual | G81: Long-run global GDP growth proxy for software industry maturity
A82: terminal_exit_multiple_type | B82: Exit multiple metric | C82: enum
A83: terminal_exit_multiple_value | B83: Exit multiple value | C83: number
A84: terminal_nominal_gdp_growth | B84: Nominal GDP growth (reference ceiling) | C84: percentage | H84: Long-run nominal GDP of the operating jurisdiction; terminal g at/above GDP − 50bps is flagged
A86: Section F — WACC inputs (Core)
A87: risk_free_rate | B87: Risk-free rate | C87: percentage | D87: 0.045 | F87: Manual | G87: 10y UST yield 2026-04-29 close
A88: risk_free_rate_source | B88: Risk-free rate source descriptor | C88: text | D88: 10y UST as at 2026-04-29
A89: equity_risk_premium | B89: Equity risk premium (ERP) | C89: percentage | D89: 0.055 | F89: Damodaran | G89: Damodaran ERP 2024 implied
A90: country_risk_premium | B90: Country risk premium | C90: percentage | D90: 0.005 | F90: Damodaran | G90: Damodaran Country ERP 2024, SG
A91: unlevered_beta | B91: Unlevered beta | C91: number | D91: 1.05 | E91: 1.15 | F91: Calculated | G91: Median unlevered beta of comparable companies marked selected_for_wacc, re-levered to target capital structure
A92: target_debt_to_equity | B92: Target D/E ratio | C92: percentage | D92: 0.2 | E92: 0.25
A93: levered_beta | B93: Levered beta (calculated) | C93: number | D93: =WACC!E10 -> 1.2243 | E93: =WACC!F10 -> 1.388625
A94: size_premium | B94: Size premium | C94: percentage | D94: 0.02 | E94: 0.025
A95: specific_risk_premium | B95: Specific risk premium | C95: percentage | D95: 0.02 | E95: 0.03
A96: cost_of_equity | B96: Cost of equity (calculated) | C96: percentage | D96: =WACC!E16 -> 0.1573365 | E96: =WACC!F16 -> 0.18137438
A97: pretax_cost_of_debt | B97: Pre-tax cost of debt | C97: percentage | D97: 0.06 | E97: 0.065
A98: aftertax_cost_of_debt | B98: After-tax cost of debt (calculated) | C98: percentage | D98: =WACC!E20 -> 0.0498 | E98: =WACC!F20 -> 0.05395
A99: target_debt_weight | B99: D/V (debt weight) | C99: percentage | D99: 0.17 | E99: 0.2
A100: target_equity_weight | B100: E/V (equity weight) | C100: percentage | D100: 0.83 | E100: 0.8
A101: wacc | B101: WACC (calculated) | C101: percentage | D101: =WACC!E25 -> 0.13905529 | E101: =WACC!F25 -> 0.1558895
A103: Section I — EV -> Equity bridge (Core)
A104: surplus_assets | B104: Surplus / non-operating assets | C104: currency | D104: 25000
A105: net_debt_override | B105: Net debt (override) | C105: currency
A106: minority_interests | B106: Minority interests | C106: currency | D106: 0
A107: non_operating_assets | B107: Non-operating assets | C107: currency | D107: 0
A108: dlom_pct | B108: DLOM rate | C108: percentage | D108: 0.2 | F108: Manual | G108: Restricted stock studies median, 2024 | H108: Pre-IPO
A109: dloc_pct | B109: DLOC rate | C109: percentage | D109: 0.15 | F109: Manual | G109: Mergerstat control premium inverse
A110: equity_interest_pct | B110: Client's % equity interest | C110: percentage | D110: 1
A111: shares_outstanding | B111: Shares outstanding (basic) | C111: number | D111: 250000000 | F111: Prospectus | G111: Draft prospectus, share capital section | H111: Basic — diluted figure tracked separately
A112: shares_outstanding_diluted | B112: Shares outstanding (diluted) | C112: number | D112: 285000000
A113: pre_money_pct | B113: Pre-money equity % | C113: percentage | D113: 0.85
A115: Section J — Adjustment toggles (Extended)
A116: capitalize_rd | B116: Capitalize R&D? | C116: boolean | D116: =TRUE() -> TRUE
A117: rd_amortization_years | B117: R&D amortization period (years) | C117: number | D117: 5
A118: convert_operating_leases | B118: Convert operating leases to debt? | C118: boolean | D118: =FALSE() -> FALSE
A119: lease_discount_rate | B119: Lease discount rate | C119: percentage
A121: Section K — Football field weights (Extended)
A122: weight_dcf | B122: DCF weight | C122: percentage | D122: 0.5
...

Sheet Historical FS
A1: Historical Financial Statements
A2: 3-5 years audited income statement + balance sheet. Manual entry from client PBC. Y0 base values for the Projections sheet (revenue, NWC) should be populated from this sheet.
A4: Line item | B4: Unit | C4: FY-5 | D4: FY-4 | E4: FY-3 | F4: FY-2 | G4: FY-1
A6: Income Statement
A7: Revenue | B7: (currency × unit) | C7: 70000 | D7: 78000 | E7: 86000 | F7: 95000 | G7: 100000
A8: Cost of revenue | B8: (currency × unit) | C8: -42000 | D8: -46800 | E8: -51600 | F8: -57000 | G8: -60000
A9: Gross profit | B9: (currency × unit) | C9: 28000 | D9: 31200 | E9: 34400 | F9: 38000 | G9: 40000
A10: Operating expenses | B10: (currency × unit) | C10: -21000 | D10: -23400 | E10: -25800 | F10: -28500 | G10: -30000
A11: Selling, general & admin | B11: (currency × unit) | C11: -15000 | D11: -16800 | E11: -18500 | F11: -20400 | G11: -21500
A12: Research & development | B12: (currency × unit) | C12: -6000 | D12: -6600 | E12: -7300 | F12: -8100 | G12: -8500
A13: EBITDA | B13: (currency × unit) | C13: 7000 | D13: 7800 | E13: 8600 | F13: 9500 | G13: 10000
A14: Depreciation & amortization | B14: (currency × unit) | C14: -2100 | D14: -2340 | E14: -2580 | F14: -2850 | G14: -3000
A15: EBIT (Operating income) | B15: (currency × unit) | C15: 4900 | D15: 5460 | E15: 6020 | F15: 6650 | G15: 7000
A16: Interest expense | B16: (currency × unit) | C16: -800 | D16: -800 | E16: -750 | F16: -700 | G16: -700
A17: Other income / (expense) | B17: (currency × unit) | C17: 0 | D17: 0 | E17: 0 | F17: 0 | G17: 0
A18: Profit before tax | B18: (currency × unit) | C18: 4100 | D18: 4660 | E18: 5270 | F18: 5950 | G18: 6300
... A20: Net income | B20: (currency × unit) | C20: 3116 | D20: 3542 | E20: 4005 | F20: 4522 | G20: 4788
A22: Balance Sheet
A23: Current assets | B23: (currency × unit)
A24: Cash and equivalents | B24: (currency × unit) | C24: 3000 | D24: 3500 | E24: 4500 | F24: 5500 | G24: 6500
A25: Accounts receivable | B25: (currency × unit) | C25: 10000 | D25: 11000 | E25: 12000 | F25: 13000 | G25: 14000
A26: Inventory | B26: (currency × unit) | C26: 4500 | D26: 5000 | E26: 5500 | F26: 6000 | G26: 6500
A27: Prepaid expenses | B27: (currency × unit) | C27: 800 | D27: 900 | E27: 1000 | F27: 1100 | G27: 1200
A28: Total current assets | B28: (currency × unit) | C28: 18300 | D28: 20400 | E28: 23000 | F28: 25600 | G28: 28200
A29: Non-current assets | B29: (currency × unit)
A30: Property, plant & equipment | B30: (currency × unit) | C30: 22000 | D30: 26000 | E30: 30000 | F30: 34000 | G30: 38000
A31: Intangible assets | B31: (currency × unit) | C31: 3500 | D31: 3500 | E31: 3500 | F31: 3500 | G31: 3500
A32: Other long-term assets | B32: (currency × unit) | C32: 1500 | D32: 1500 | E32: 1500 | F32: 1500 | G32: 1500
A33: Total assets | B33: (currency × unit) | C33: 45300 | D33: 51400 | E33: 58000 | F33: 64600 | G33: 71200
A35: Current liabilities | B35: (currency × unit)
A36: Accounts payable | B36: (currency × unit) | C36: -7000 | D36: -7700 | E36: -8500 | F36: -9300 | G36: -10000
A37: Short-term debt | B37: (currency × unit) | C37: -3000 | D37: -2500 | E37: -2000 | F37: -2000 | G37: -2000
A38: Other current liabilities | B38: (currency × unit) | C38: -2000 | D38: -2200 | E38: -2400 | F38: -2700 | G38: -3000
A39: Total current liabilities | B39: (currency × unit) | C39: -12000 | D39: -12400 | E39: -12900 | F39: -14000 | G39: -15000
A40: Non-current liabilities | B40: (currency × unit)
A41: Long-term debt | B41: (currency × unit) | C41: -12000 | D41: -11000 | E41: -9500 | F41: -9000 | G41: -8500
A42: Other long-term liabilities | B42: (currency × unit) | C42: -1000 | D42: -1000 | E42: -1000 | F42: -1000 | G42: -1000
A43: Total liabilities | B43: (currency × unit) | C43: -25000 | D43: -24400 | E43: -23400 | F43: -24000 | G43: -24500
A44: Total equity | B44: (currency × unit) | C44: 20300 | D44: 27000 | E44: 34600 | F44: 40600 | G44: 46700
A46: Derived metrics (calculated)
A47: Net working capital (= current assets − current liabilities) | B47: (currency × unit) | C47: =C28-C39 -> 30300 | D47: =D28-D39 -> 32800 | E47: =E28-E39 -> 35900 | F47: =F28-F39 -> 39600 | G47: =G28-G39 -> 43200
A48: Net debt (= short-term debt + long-term debt − cash) | B48: (currency × unit) | C48: =C37+C41-C24 -> -18000 | D48: =D37+D41-D24 -> -17000 | E48: =E37+E41-E24 -> -16000 | F48: =F37+F41-F24 -> -16500 | G48: =G37+G41-G24 -> -17000

Sheet Projections
A1: Projections — driven by Inputs
A2: Year-by-year forecast lines. Every assumption flows from Inputs named ranges. Edit a value on Inputs and this sheet recalculates.
A4: Line item | B4: Unit | C4: Y0 (base) | D4: Y1 | E4: Y2 | F4: Y3 | G4: Y4 | H4: Y5
A6: Revenue & growth
A8: Revenue - Primary | B8: (from Inputs) | C8: =revenue_y0 -> 100000 | D8: =C8*(1+IF(ISNUMBER(revenue_growth_primary_y1),revenue_growth_primary_y1,revenue_growth_y1)) -> 145000 | E8: =D8*(1+IF(ISNUMBER(revenue_growth_primary_y2),revenue_growth_primary_y2,revenue_growth_y2)) -> 188500 | F8: =E8*(1+IF(ISNUMBER(revenue_growth_primary_y3),revenue_growth_primary_y3,revenue_growth_y3)) -> 229970 | G8: =F8*(1+IF(ISNUMBER(revenue_growth_primary_y4),revenue_growth_primary_y4,revenue_growth_y4)) -> 266765.2 | H8: =G8*(1+IF(ISNUMBER(revenue_growth_primary_y5),revenue_growth_primary_y5,revenue_growth_y5)) -> 293441.72
A9: Core business baseline carryover | D9: =C8 -> 100000 | E9: =D8 -> 145000 | F9: =E8 -> 188500 | G9: =F8 -> 229970 | H9: =G8 -> 266765.2
A10: Capped baseline growth | D10: =C8*D11 -> 45000 | E10: =D8*E11 -> 43500 | F10: =E8*F11 -> 41470 | G10: =F8*G11 -> 36795.2 | H10: =G8*H11 -> 26676.52
A11: Revenue growth (primary) | B11: % | D11: =IF(ISNUMBER(revenue_growth_primary_y1),revenue_growth_primary_y1,revenue_growth_y1) -> 0.45 | E11: =IF(ISNUMBER(revenue_growth_primary_y2),revenue_growth_primary_y2,revenue_growth_y2) -> 0.3 | F11: =IF(ISNUMBER(revenue_growth_primary_y3),revenue_growth_primary_y3,revenue_growth_y3) -> 0.22 | G11: =IF(ISNUMBER(revenue_growth_primary_y4),revenue_growth_primary_y4,revenue_growth_y4) -> 0.16 | H11: =IF(ISNUMBER(revenue_growth_primary_y5),revenue_growth_primary_y5,revenue_growth_y5) -> 0.1
A12: Revenue - Others | B12: (currency × unit) | C12: 0 | D12: =D25-D8 -> 0 | E12: =E25-E8 -> 0 | F12: =F25-F8 -> 0 | G12: =G25-G8 -> 0 | H12: =H25-H8 -> 0
A13: Core business excess upside | D13: =IF(AND(NOT(INDEX(segments_table,1,1)=""),EXACT(INDEX(segments_table,1,19),"core")),D75,0)+IF(AND(NOT(INDEX(segments_table,2,1)=""),EXACT(INDEX(segments_table,2,19),"core")),D79,0)+IF(AND(NOT(INDEX(segments_table,3,1)=""),EXACT(INDEX(segments_table,3,19),"core")),D83,0)+IF(AND(NOT(INDEX(segments_table,4,1)=""),EXACT(INDEX(segments_table,4,19),"core")),D87,0)+IF(AND(NOT(INDEX(segments_table,5,1)=""),EXACT(INDEX(segments_table,5,19),"core")),D91,0)+IF(AND(NOT(INDEX(segments_table,6,1)=""),EXACT(INDEX(segments_table,6,19),"core")),D95,0)+IF(AND(NOT(INDEX(segments_table,7,1)=""),EXACT(INDEX(segments_table,7,19),"core")),D99,0)+IF(AND(NOT(INDEX(segments_table,8,1)=""),EXACT(INDEX(segments_table,8,19),"core")),D103,0)-D8 -> -145000 | E13: =IF(AND(NOT(INDEX(segments_table,1,1)=""),EXACT(INDEX(segments_table,1,19),"core")),E75,0)+IF(AND(NOT(INDEX(segments_table,2,1)=""),EXACT(INDEX(segments_table,2,19),"core")),E79,0)+IF(AND(NOT(INDEX(segments_table,3,1)=""),EXACT(INDEX(segments_table,3,19),"core")),E83,0)+IF(AND(NOT(INDEX(segments_table,4,1)=""),EXACT(INDEX(segments_table,4,19),"core")),E87,0)+IF(AND(NOT(INDEX(segments_table,5,1)=""),EXACT(INDEX(segments_table,5,19),"core")),E91,0)+IF(AND(NOT(INDEX(segments_table,6,1)=""),EXACT(INDEX(segments_table,6,19),"core")),E95,0)+IF(AND(NOT(INDEX(segments_table,7,1)=""),EXACT(INDEX(segments_table,7,19),"core")),E99,0)+IF(AND(NOT(INDEX(segments_table,8,1)=""),EXACT(INDEX(segments_table,8,19),"core")),E103,0)-E8 -> -188500 | F13: =IF(AND(NOT(INDEX(segments_table,1,1)=""),EXACT(INDEX(segments_table,1,19),"core")),F75,0)+IF(AND(NOT(INDEX(segments_table,2,1)=""),EXACT(INDEX(segments_table,2,19),"core")),F79,0)+IF(AND(NOT(INDEX(segments_table,3,1)=""),EXACT(INDEX(segments_table,3,19),"core")),F83,0)+IF(AND(NOT(INDEX(segments_table,4,1)=""),EXACT(INDEX(segments_table,4,19),"core")),F87,0)+IF(AND(NOT(INDEX(segments_table,5,1)=""),EXACT(INDEX(segments_table,5,19),"core")),F91,0)+IF(AND(NOT(INDEX(segments_table,6,1)=""),EXACT(INDEX(segments_table,6,19),"core")),F95,0)+IF(AND(NOT(INDEX(segments_table,7,1)=""),EXACT(INDEX(segments_table,7,19),"core")),F99,0)+IF(AND(NOT(INDEX(segments_table,8,1)=""),EXACT(INDEX(segments_table,8,19),"core")),F103,0)-F8 -> -229970 | G13: =IF(AND(NOT(INDEX(segments_table,1,1)=""),EXACT(INDEX(segments_table,1,19),"core")),G75,0)+IF(AND(NOT(INDEX(segments_table,2,1)=""),EXACT(INDEX(segments_table,2,19),"core")),G79,0)+IF(AND(NOT(INDEX(segments_table,3,1)=""),EXACT(INDEX(segments_table,3,19),"core")),G83,0)+IF(AND(NOT(INDEX(segments_table,4,1)=""),EXACT(INDEX(segments_table,4,19),"core")),G87,0)+IF(AND(NOT(INDEX(segments_table,5,1)=""),EXACT(INDEX(segments_table,5,19),"core")),G91,0)+IF(AND(NOT(INDEX(segments_table,6,1)=""),EXACT(INDEX(segments_table,6,19),"core")),G95,0)+IF(AND(NOT(INDEX(segments_table,7,1)=""),EXACT(INDEX(segments_table,7,19),"core")),G99,0)+IF(AND(NOT(INDEX(segments_table,8,1)=""),EXACT(INDEX(segments_table,8,19),"core")),G103,0)-G8 -> -266765.2 | H13: =IF(AND(NOT(INDEX(segments_table,1,1)=""),EXACT(INDEX(segments_table,1,19),"core")),H75,0)+IF(AND(NOT(INDEX(segments_table,2,1)=""),EXACT(INDEX(segments_table,2,19),"core")),H79,0)+IF(AND(NOT(INDEX(segments_table,3,1)=""),EXACT(INDEX(segments_table,3,19),"core")),H83,0)+IF(AND(NOT(INDEX(segments_table,4,1)=""),EXACT(INDEX(segments_table,4,19),"core")),H87,0)+IF(AND(NOT(INDEX(segments_table,5,1)=""),EXACT(INDEX(segments_table,5,19),"core")),H91,0)+IF(AND(NOT(INDEX(segments_table,6,1)=""),EXACT(INDEX(segments_table,6,19),"core")),H95,0)+IF(AND(NOT(INDEX(segments_table,7,1)=""),EXACT(INDEX(segments_table,7,19),"core")),H99,0)+IF(AND(NOT(INDEX(segments_table,8,1)=""),EXACT(INDEX(segments_table,8,19),"core")),H103,0)-H8 -> -293441.72
A14: =IF(OR(INDEX(segments_table,1,1)="",EXACT(INDEX(segments_table,1,19),"core")),""," "&INDEX(segments_table,1,1)) | D14: =IF(OR(INDEX(segments_table,1,1)="",EXACT(INDEX(segments_table,1,19),"core")),0,D75) -> 0 | E14: =IF(OR(INDEX(segments_table,1,1)="",EXACT(INDEX(segments_table,1,19),"core")),0,E75) -> 0 | F14: =IF(OR(INDEX(segments_table,1,1)="",EXACT(INDEX(segments_table,1,19),"core")),0,F75) -> 0 | G14: =IF(OR(INDEX(segments_table,1,1)="",EXACT(INDEX(segments_table,1,19),"core")),0,G75) -> 0 | H14: =IF(OR(INDEX(segments_table,1,1)="",EXACT(INDEX(segments_table,1,19),"core")),0,H75) -> 0
A15: =IF(OR(INDEX(segments_table,2,1)="",EXACT(INDEX(segments_table,2,19),"core")),""," "&INDEX(segments_table,2,1)) | D15: =IF(OR(INDEX(segments_table,2,1)="",EXACT(INDEX(segments_table,2,19),"core")),0,D79) -> 0 | E15: =IF(OR(INDEX(segments_table,2,1)="",EXACT(INDEX(segments_table,2,19),"core")),0,E79) -> 0 | F15: =IF(OR(INDEX(segments_table,2,1)="",EXACT(INDEX(segments_table,2,19),"core")),0,F79) -> 0 | G15: =IF(OR(INDEX(segments_table,2,1)="",EXACT(INDEX(segments_table,2,19),"core")),0,G79) -> 0 | H15: =IF(OR(INDEX(segments_table,2,1)="",EXACT(INDEX(segments_table,2,19),"core")),0,H79) -> 0
A16: =IF(OR(INDEX(segments_table,3,1)="",EXACT(INDEX(segments_table,3,19),"core")),""," "&INDEX(segments_table,3,1)) | D16: =IF(OR(INDEX(segments_table,3,1)="",EXACT(INDEX(segments_table,3,19),"core")),0,D83) -> 0 | E16: =IF(OR(INDEX(segments_table,3,1)="",EXACT(INDEX(segments_table,3,19),"core")),0,E83) -> 0 | F16: =IF(OR(INDEX(segments_table,3,1)="",EXACT(INDEX(segments_table,3,19),"core")),0,F83) -> 0 | G16: =IF(OR(INDEX(segments_table,3,1)="",EXACT(INDEX(segments_table,3,19),"core")),0,G83) -> 0 | H16: =IF(OR(INDEX(segments_table,3,1)="",EXACT(INDEX(segments_table,3,19),"core")),0,H83) -> 0
A17: =IF(OR(INDEX(segments_table,4,1)="",EXACT(INDEX(segments_table,4,19),"core")),""," "&INDEX(segments_table,4,1)) | D17: =IF(OR(INDEX(segments_table,4,1)="",EXACT(INDEX(segments_table,4,19),"core")),0,D87) -> 0 | E17: =IF(OR(INDEX(segments_table,4,1)="",EXACT(INDEX(segments_table,4,19),"core")),0,E87) -> 0 | F17: =IF(OR(INDEX(segments_table,4,1)="",EXACT(INDEX(segments_table,4,19),"core")),0,F87) -> 0 | G17: =IF(OR(INDEX(segments_table,4,1)="",EXACT(INDEX(segments_table,4,19),"core")),0,G87) -> 0 | H17: =IF(OR(INDEX(segments_table,4,1)="",EXACT(INDEX(segments_table,4,19),"core")),0,H87) -> 0
A18: =IF(OR(INDEX(segments_table,5,1)="",EXACT(INDEX(segments_table,5,19),"core")),""," "&INDEX(segments_table,5,1)) | D18: =IF(OR(INDEX(segments_table,5,1)="",EXACT(INDEX(segments_table,5,19),"core")),0,D91) -> 0 | E18: =IF(OR(INDEX(segments_table,5,1)="",EXACT(INDEX(segments_table,5,19),"core")),0,E91) -> 0 | F18: =IF(OR(INDEX(segments_table,5,1)="",EXACT(INDEX(segments_table,5,19),"core")),0,F91) -> 0 | G18: =IF(OR(INDEX(segments_table,5,1)="",EXACT(INDEX(segments_table,5,19),"core")),0,G91) -> 0 | H18: =IF(OR(INDEX(segments_table,5,1)="",EXACT(INDEX(segments_table,5,19),"core")),0,H91) -> 0
A19: =IF(OR(INDEX(segments_table,6,1)="",EXACT(INDEX(segments_table,6,19),"core")),""," "&INDEX(segments_table,6,1)) | D19: =IF(OR(INDEX(segments_table,6,1)="",EXACT(INDEX(segments_table,6,19),"core")),0,D95) -> 0 | E19: =IF(OR(INDEX(segments_table,6,1)="",EXACT(INDEX(segments_table,6,19),"core")),0,E95) -> 0 | F19: =IF(OR(INDEX(segments_table,6,1)="",EXACT(INDEX(segments_table,6,19),"core")),0,F95) -> 0 | G19: =IF(OR(INDEX(segments_table,6,1)="",EXACT(INDEX(segments_table,6,19),"core")),0,G95) -> 0 | H19: =IF(OR(INDEX(segments_table,6,1)="",EXACT(INDEX(segments_table,6,19),"core")),0,H95) -> 0
A20: =IF(OR(INDEX(segments_table,7,1)="",EXACT(INDEX(segments_table,7,19),"core")),""," "&INDEX(segments_table,7,1)) | D20: =IF(OR(INDEX(segments_table,7,1)="",EXACT(INDEX(segments_table,7,19),"core")),0,D99) -> 0 | E20: =IF(OR(INDEX(segments_table,7,1)="",EXACT(INDEX(segments_table,7,19),"core")),0,E99) -> 0 | F20: =IF(OR(INDEX(segments_table,7,1)="",EXACT(INDEX(segments_table,7,19),"core")),0,F99) -> 0 | G20: =IF(OR(INDEX(segments_table,7,1)="",EXACT(INDEX(segments_table,7,19),"core")),0,G99) -> 0 | H20: =IF(OR(INDEX(segments_table,7,1)="",EXACT(INDEX(segments_table,7,19),"core")),0,H99) -> 0
A21: =IF(OR(INDEX(segments_table,8,1)="",EXACT(INDEX(segments_table,8,19),"core")),""," "&INDEX(segments_table,8,1)) | D21: =IF(OR(INDEX(segments_table,8,1)="",EXACT(INDEX(segments_table,8,19),"core")),0,D103) -> 0 | E21: =IF(OR(INDEX(segments_table,8,1)="",EXACT(INDEX(segments_table,8,19),"core")),0,E103) -> 0 | F21: =IF(OR(INDEX(segments_table,8,1)="",EXACT(INDEX(segments_table,8,19),"core")),0,F103) -> 0 | G21: =IF(OR(INDEX(segments_table,8,1)="",EXACT(INDEX(segments_table,8,19),"core")),0,G103) -> 0 | H21: =IF(OR(INDEX(segments_table,8,1)="",EXACT(INDEX(segments_table,8,19),"core")),0,H103) -> 0
A22: Unallocated model adjustment | D22: =D12-D13-SUM(D14:D21) -> 145000 | E22: =E12-E13-SUM(E14:E21) -> 188500 | F22: =F12-F13-SUM(F14:F21) -> 229970 | G22: =G12-G13-SUM(G14:G21) -> 266765.2 | H22: =H12-H13-SUM(H14:H21) -> 293441.72
A23: Sum of Revenue - Others (tie-out) | D23: =SUM(D13:D22) -> 0 | E23: =SUM(E13:E22) -> 0 | F23: =SUM(F13:F22) -> 0 | G23: =SUM(G13:G22) -> 0 | H23: =SUM(H13:H22) -> 0
A24: Other revenue growth | B24: % | D24: =IFERROR(D12/C12-1,"") | E24: =IFERROR(E12/D12-1,"") | F24: =IFERROR(F12/E12-1,"") | G24: =IFERROR(G12/F12-1,"") | H24: =IFERROR(H12/G12-1,"")
A25: Total Revenue | B25: (from Inputs) | C25: =revenue_y0 -> 100000 | D25: =C25*(1+revenue_growth_y1) -> 145000 | E25: =D25*(1+revenue_growth_y2) -> 188500 | F25: =E25*(1+revenue_growth_y3) -> 229970 | G25: =F25*(1+revenue_growth_y4) -> 266765.2 | H25: =G25*(1+revenue_growth_y5) -> 293441.72
A26: Revenue growth (total) | B26: % | D26: =revenue_growth_y1 -> 0.45 | E26: =revenue_growth_y2 -> 0.3 | F26: =revenue_growth_y3 -> 0.22 | G26: =revenue_growth_y4 -> 0.16 | H26: =revenue_growth_y5 -> 0.1
A28: Cost of goods sold
A30: COGS - Primary
A31: =A9 -> Core business baseline carryover | D31: =IFERROR((D25-D47)*D9/D25,0) -> 38000 | E31: =IFERROR((E25-E47)*E9/E25,0) -> 52200 | F31: =IFERROR((F25-F47)*F9/F25,0) -> 65975 | G31: =IFERROR((G25-G47)*G9/G25,0) -> 80489.5 | H31: =IFERROR((H25-H47)*H9/H25,0) -> 90700.168
A32: =A10 -> Capped baseline growth | D32: =IFERROR((D25-D47)*D10/D25,0) -> 17100 | E32: =IFERROR((E25-E47)*E10/E25,0) -> 15660 | F32: =IFERROR((F25-F47)*F10/F25,0) -> 14514.5 | G32: =IFERROR((G25-G47)*G10/G25,0) -> 12878.32 | H32: =IFERROR((H25-H47)*H10/H25,0) -> 9070.0168
A33: COGS - Others
A34: =A13 -> Core business excess upside | D34: =IFERROR((D25-D47)*D13/D25,0) -> -55100 | E34: =IFERROR((E25-E47)*E13/E25,0) -> -67860 | F34: =IFERROR((F25-F47)*F13/F25,0) -> -80489.5 | G34: =IFERROR((G25-G47)*G13/G25,0) -> -93367.82 | H34: =IFERROR((H25-H47)*H13/H25,0) -> -99770.185
A35: =A14 | D35: =IFERROR((D25-D47)*D14/D25,0) -> 0 | E35: =IFERROR((E25-E47)*E14/E25,0) -> 0 | F35: =IFERROR((F25-F47)*F14/F25,0) -> 0 | G35: =IFERROR((G25-G47)*G14/G25,0) -> 0 | H35: =IFERROR((H25-H47)*H14/H25,0) -> 0
A36: =A15 | D36: =IFERROR((D25-D47)*D15/D25,0) -> 0 | E36: =IFERROR((E25-E47)*E15/E25,0) -> 0 | F36: =IFERROR((F25-F47)*F15/F25,0) -> 0 | G36: =IFERROR((G25-G47)*G15/G25,0) -> 0 | H36: =IFERROR((H25-H47)*H15/H25,0) -> 0
A37: =A16 | D37: =IFERROR((D25-D47)*D16/D25,0) -> 0 | E37: =IFERROR((E25-E47)*E16/E25,0) -> 0 | F37: =IFERROR((F25-F47)*F16/F25,0) -> 0 | G37: =IFERROR((G25-G47)*G16/G25,0) -> 0 | H37: =IFERROR((H25-H47)*H16/H25,0) -> 0
A38: =A17 | D38: =IFERROR((D25-D47)*D17/D25,0) -> 0 | E38: =IFERROR((E25-E47)*E17/E25,0) -> 0 | F38: =IFERROR((F25-F47)*F17/F25,0) -> 0 | G38: =IFERROR((G25-G47)*G17/G25,0) -> 0 | H38: =IFERROR((H25-H47)*H17/H25,0) -> 0
A39: =A18 | D39: =IFERROR((D25-D47)*D18/D25,0) -> 0 | E39: =IFERROR((E25-E47)*E18/E25,0) -> 0 | F39: =IFERROR((F25-F47)*F18/F25,0) -> 0 | G39: =IFERROR((G25-G47)*G18/G25,0) -> 0 | H39: =IFERROR((H25-H47)*H18/H25,0) -> 0
A40: =A19 | D40: =IFERROR((D25-D47)*D19/D25,0) -> 0 | E40: =IFERROR((E25-E47)*E19/E25,0) -> 0 | F40: =IFERROR((F25-F47)*F19/F25,0) -> 0 | G40: =IFERROR((G25-G47)*G19/G25,0) -> 0 | H40: =IFERROR((H25-H47)*H19/H25,0) -> 0
A41: =A20 | D41: =IFERROR((D25-D47)*D20/D25,0) -> 0 | E41: =IFERROR((E25-E47)*E20/E25,0) -> 0 | F41: =IFERROR((F25-F47)*F20/F25,0) -> 0 | G41: =IFERROR((G25-G47)*G20/G25,0) -> 0 | H41: =IFERROR((H25-H47)*H20/H25,0) -> 0
A42: =A21 | D42: =IFERROR((D25-D47)*D21/D25,0) -> 0 | E42: =IFERROR((E25-E47)*E21/E25,0) -> 0 | F42: =IFERROR((F25-F47)*F21/F25,0) -> 0 | G42: =IFERROR((G25-G47)*G21/G25,0) -> 0 | H42: =IFERROR((H25-H47)*H21/H25,0) -> 0
A43: =A22 -> Unallocated model adjustment | D43: =IFERROR((D25-D47)*D22/D25,0) -> 55100 | E43: =IFERROR((E25-E47)*E22/E25,0) -> 67860 | F43: =IFERROR((F25-F47)*F22/F25,0) -> 80489.5 | G43: =IFERROR((G25-G47)*G22/G25,0) -> 93367.82 | H43: =IFERROR((H25-H47)*H22/H25,0) -> 99770.185
A44: Total COGS | B44: (currency × unit) | D44: =SUM(D31:D43) -> 55100 | E44: =SUM(E31:E43) -> 67860 | F44: =SUM(F31:F43) -> 80489.5 | G44: =SUM(G31:G43) -> 93367.82 | H44: =SUM(H31:H43) -> 99770.185
A46: Profitability
A47: Gross profit | B47: (currency × unit) | C47: =IFERROR(gross_profit_y0,"") -> 0 | D47: =D25*gross_margin_y1 -> 89900 | E47: =E25*gross_margin_y2 -> 120640 | F47: =F25*gross_margin_y3 -> 149480.5 | G47: =G25*gross_margin_y4 -> 173397.38 | H47: =H25*gross_margin_y5 -> 193671.54
A48: Gross margin | B48: % | C48: =IFERROR(gross_profit_y0/revenue_y0,"") -> 0 | D48: =gross_margin_y1 -> 0.62 | E48: =gross_margin_y2 -> 0.64 | F48: =gross_margin_y3 -> 0.65 | G48: =gross_margin_y4 -> 0.65 | H48: =gross_margin_y5 -> 0.66
A49: Operating expenses | B49: (currency × unit) | C49: =IFERROR(opex_y0,"") -> 0 | D49: =-(D25-D107)*opex_pct_revenue_y1+D108 -> -79750 | E49: =-(E25-E107)*opex_pct_revenue_y2+E108 -> -94250 | F49: =-(F25-F107)*opex_pct_revenue_y3+F108 -> -103486.5 | G49: =-(G25-G107)*opex_pct_revenue_y4+G108 -> -112041.38 | H49: =-(H25-H107)*opex_pct_revenue_y5+H108 -> -117376.69
A50: EBITDA | B50: (currency × unit) | C50: =IFERROR(ebitda_y0,"") -> 0 | D50: =D47+D49 -> 10150 | E50: =E47+E49 -> 26390 | F50: =F47+F49 -> 45994 | G50: =G47+G49 -> 61355.996 | H50: =H47+H49 -> 76294.847
A51: EBITDA margin | B51: % | C51: =IFERROR(ebitda_y0/revenue_y0,"") -> 0 | D51: =IFERROR(D50/D25,0) -> 0.07 | E51: =IFERROR(E50/E25,0) -> 0.14 | F51: =IFERROR(F50/F25,0) -> 0.2 | G51: =IFERROR(G50/G25,0) -> 0.23 | H51: =IFERROR(H50/H25,0) -> 0.26
A52: Depreciation & amortization | B52: (currency × unit) | D52: =-D25*dep_pct_revenue_y1 -> -5800 | E52: =-E25*dep_pct_revenue_y2 -> -7540 | F52: =-F25*dep_pct_revenue_y3 -> -9198.8 | G52: =-G25*dep_pct_revenue_y4 -> -10670.608 | H52: =-H25*dep_pct_revenue_y5 -> -11737.669
A53: EBIT | B53: (currency × unit) | C53: =IFERROR(ebit_y0,"") -> 0 | D53: =D50+D52 -> 4350 | E53: =E50+E52 -> 18850 | F53: =F50+F52 -> 36795.2 | G53: =G50+G52 -> 50685.388 | H53: =H50+H52 -> 64557.178
A54: EBIT margin | B54: % | C54: =IFERROR(ebit_y0/revenue_y0,"") -> 0 | D54: =IFERROR(D53/D25,0) -> 0.03 | E54: =IFERROR(E53/E25,0) -> 0.1 | F54: =IFERROR(F53/F25,0) -> 0.16 | G54: =IFERROR(G53/G25,0) -> 0.19 | H54: =IFERROR(H53/H25,0) -> 0.22
A56: Tax & net income
A57: Tax | B57: (currency × unit) | C57: =IFERROR(tax_y0,"") -> 0 | D57: =IF(ISNUMBER(tax_effective_rate),-MAX(D53,0)*tax_effective_rate,IF(EXACT(tax_type,"two_tier"),IF(D53<=tax_threshold,-MAX(D53,0)*tax_rate_low,-(tax_threshold*tax_rate_low+MAX(D53-tax_threshold,0)*tax_rate_high)),-MAX(D53,0)*tax_rate_high)) -> -739.5 | E57: =IF(ISNUMBER(tax_effective_rate),-MAX(E53,0)*tax_effective_rate,IF(EXACT(tax_type,"two_tier"),IF(E53<=tax_threshold,-MAX(E53,0)*tax_rate_low,-(tax_threshold*tax_rate_low+MAX(E53-tax_threshold,0)*tax_rate_high)),-MAX(E53,0)*tax_rate_high)) -> -3204.5 | F57: =IF(ISNUMBER(tax_effective_rate),-MAX(F53,0)*tax_effective_rate,IF(EXACT(tax_type,"two_tier"),IF(F53<=tax_threshold,-MAX(F53,0)*tax_rate_low,-(tax_threshold*tax_rate_low+MAX(F53-tax_threshold,0)*tax_rate_high)),-MAX(F53,0)*tax_rate_high)) -> -6255.184 | G57: =IF(ISNUMBER(tax_effective_rate),-MAX(G53,0)*tax_effective_rate,IF(EXACT(tax_type,"two_tier"),IF(G53<=tax_threshold,-MAX(G53,0)*tax_rate_low,-(tax_threshold*tax_rate_low+MAX(G53-tax_threshold,0)*tax_rate_high)),-MAX(G53,0)*tax_rate_high)) -> -8616.516 | H57: =IF(ISNUMBER(tax_effective_rate),-MAX(H53,0)*tax_effective_rate,IF(EXACT(tax_type,"two_tier"),IF(H53<=tax_threshold,-MAX(H53,0)*tax_rate_low,-(tax_threshold*tax_rate_low+MAX(H53-tax_threshold,0)*tax_rate_high)),-MAX(H53,0)*tax_rate_high)) -> -10974.72
A58: Net income | B58: (currency × unit) | C58: =IFERROR(net_income_y0,"") -> 0 | D58: =D53+D57 -> 3610.5 | E58: =E53+E57 -> 15645.5 | F58: =F53+F57 -> 30540.016 | G58: =G53+G57 -> 42068.872 | H58: =H53+H57 -> 53582.458
A60: Capex & working capital
A61: Capex | B61: (currency × unit) | D61: =-D25*capex_pct_revenue_y1 -> -8700 | E61: =-E25*capex_pct_revenue_y2 -> -9425 | F61: =-F25*capex_pct_revenue_y3 -> -9198.8 | G61: =-G25*capex_pct_revenue_y4 -> -10670.608 | H61: =-H25*capex_pct_revenue_y5 -> -11737.669
A62: Net working capital | B62: (from Inputs) | C62: =nwc_y0 -> 8000 | D62: =D25*nwc_pct_sales_y1 -> 11600 | E62: =E25*nwc_pct_sales_y2 -> 15080 | F62: =F25*nwc_pct_sales_y3 -> 18397.6 | G62: =G25*nwc_pct_sales_y4 -> 21341.216 | H62: =H25*nwc_pct_sales_y5 -> 23475.338
A63: Δ Working capital | B63: (currency × unit) | D63: =-(D62-C62) -> -3600 | E63: =-(E62-D62) -> -3480 | F63: =-(F62-E62) -> -3317.6 | G63: =-(G62-F62) -> -2943.616 | H63: =-(H62-G62) -> -2134.1216
A65: FCFF construction
A66: EBIT | B66: (currency × unit) | D66: =D53 -> 4350 | E66: =E53 -> 18850 | F66: =F53 -> 36795.2 | G66: =G53 -> 50685.388 | H66: =H53 -> 64557.178
A67: Less: Tax on EBIT | B67: (currency × unit) | D67: =D57 -> -739.5 | E67: =E57 -> -3204.5 | F67: =F57 -> -6255.184 | G67: =G57 -> -8616.516 | H67: =H57 -> -10974.72
A68: Add: Depreciation | B68: (currency × unit) | D68: =-D52 -> 5800 | E68: =-E52 -> 7540 | F68: =-F52 -> 9198.8 | G68: =-G52 -> 10670.608 | H68: =-H52 -> 11737.669
A69: Less: Capex | B69: (currency × unit) | D69: =D61 -> -8700 | E69: =E61 -> -9425 | F69: =F61 -> -9198.8 | G69: =G61 -> -10670.608 | H69: =H61 -> -11737.669
A70: Less: Δ Working capital | B70: (currency × unit) | D70: =D63 -> -3600 | E70: =E63 -> -3480 | F70: =F63 -> -3317.6 | G70: =G63 -> -2943.616 | H70: =H63 -> -2134.1216
A71: Free Cash Flow to Firm (FCFF) | B71: (currency × unit) | D71: =SUM(D66:D70) -> -2889.5 | E71: =SUM(E66:E70) -> 10280.5 | F71: =SUM(F66:F70) -> 27222.416 | G71: =SUM(G66:G70) -> 39125.256 | H71: =SUM(H66:H70) -> 51448.336
A73: Revenue streams — per-segment breakdown
A74: Driven by the Inputs 'Revenue segments' table. Unused slots stay blank. 'Direct expenses' uses the stream's own Opex% when provided (carved out of the top-level opex base), otherwise an allocation at the top-level ratio.
A75: =IF(INDEX(segments_table,1,1)="","(segment slot 1 — unused)","Revenue — "&INDEX(segments_table,1,1)) -> (segment slot 1 — unused) | C75: =IF(INDEX(segments_table,1,1)="",0,IF(N(INDEX(segments_table,1,2))=0,N(INDEX(segments_table,1,3)),0)) -> 0 | D75: =IF(INDEX(segments_table,1,1)="",0,IF(1<N(INDEX(segments_table,1,2)),0,IF(1=N(INDEX(segments_table,1,2)),N(INDEX(segments_table,1,3)),C75*(1+N(INDEX(segments_table,1,3+(1-N(INDEX(segments_table,1,2))))))))) -> 0 | E75: =IF(INDEX(segments_table,1,1)="",0,IF(2<N(INDEX(segments_table,1,2)),0,IF(2=N(INDEX(segments_table,1,2)),N(INDEX(segments_table,1,3)),D75*(1+N(INDEX(segments_table,1,3+(2-N(INDEX(segments_table,1,2))))))))) -> 0 | F75: =IF(INDEX(segments_table,1,1)="",0,IF(3<N(INDEX(segments_table,1,2)),0,IF(3=N(INDEX(segments_table,1,2)),N(INDEX(segments_table,1,3)),E75*(1+N(INDEX(segments_table,1,3+(3-N(INDEX(segments_table,1,2))))))))) -> 0 | G75: =IF(INDEX(segments_table,1,1)="",0,IF(4<N(INDEX(segments_table,1,2)),0,IF(4=N(INDEX(segments_table,1,2)),N(INDEX(segments_table,1,3)),F75*(1+N(INDEX(segments_table,1,3+(4-N(INDEX(segments_table,1,2))))))))) -> 0 | H75: =IF(INDEX(segments_table,1,1)="",0,IF(5<N(INDEX(segments_table,1,2)),0,IF(5=N(INDEX(segments_table,1,2)),N(INDEX(segments_table,1,3)),G75*(1+N(INDEX(segments_table,1,3+(5-N(INDEX(segments_table,1,2))))))))) -> 0
A76: =IF(INDEX(segments_table,1,1)="","","COGS — "&INDEX(segments_table,1,1)) | D76: =IF(INDEX(segments_table,1,1)="","",-D75*(1-N(INDEX(segments_table,1,MIN(9+(1-N(INDEX(segments_table,1,2))),13))))) | E76: =IF(INDEX(segments_table,1,1)="","",-E75*(1-N(INDEX(segments_table,1,MIN(9+(2-N(INDEX(segments_table,1,2))),13))))) | F76: =IF(INDEX(segments_table,1,1)="","",-F75*(1-N(INDEX(segments_table,1,MIN(9+(3-N(INDEX(segments_table,1,2))),13))))) | G76: =IF(INDEX(segments_table,1,1)="","",-G75*(1-N(INDEX(segments_table,1,MIN(9+(4-N(INDEX(segments_table,1,2))),13))))) | H76: =IF(INDEX(segments_table,1,1)="","",-H75*(1-N(INDEX(segments_table,1,MIN(9+(5-N(INDEX(segments_table,1,2))),13)))))
A77: =IF(INDEX(segments_table,1,1)="","",IF(COUNT(INDEX(segments_table,1,14):INDEX(segments_table,1,18))>0,"Direct expenses — "&INDEX(segments_table,1,1),"Direct expenses (allocated) — "&INDEX(segments_table,1,1))) | D77: =IF(INDEX(segments_table,1,1)="","",IF(COUNT(INDEX(segments_table,1,14):INDEX(segments_table,1,18))>0,-D75*N(INDEX(segments_table,1,MIN(14+(1-N(INDEX(segments_table,1,2))),18))),-D75*opex_pct_revenue_y1)) | E77: =IF(INDEX(segments_table,1,1)="","",IF(COUNT(INDEX(segments_table,1,14):INDEX(segments_table,1,18))>0,-E75*N(INDEX(segments_table,1,MIN(14+(2-N(INDEX(segments_table,1,2))),18))),-E75*opex_pct_revenue_y2)) | F77: =IF(INDEX(segments_table,1,1)="","",IF(COUNT(INDEX(segments_table,1,14):INDEX(segments_table,1,18))>0,-F75*N(INDEX(segments_table,1,MIN(14+(3-N(INDEX(segments_table,1,2))),18))),-F75*opex_pct_revenue_y3)) | G77: =IF(INDEX(segments_table,1,1)="","",IF(COUNT(INDEX(segments_table,1,14):INDEX(segments_table,1,18))>0,-G75*N(INDEX(segments_table,1,MIN(14+(4-N(INDEX(segments_table,1,2))),18))),-G75*opex_pct_revenue_y4)) | H77: =IF(INDEX(segments_table,1,1)="","",IF(COUNT(INDEX(segments_table,1,14):INDEX(segments_table,1,18))>0,-H75*N(INDEX(segments_table,1,MIN(14+(5-N(INDEX(segments_table,1,2))),18))),-H75*opex_pct_revenue_y5))
A79: =IF(INDEX(segments_table,2,1)="","(segment slot 2 — unused)","Revenue — "&INDEX(segments_table,2,1)) -> (segment slot 2 — unused) | C79: =IF(INDEX(segments_table,2,1)="",0,IF(N(INDEX(segments_table,2,2))=0,N(INDEX(segments_table,2,3)),0)) -> 0 | D79: =IF(INDEX(segments_table,2,1)="",0,IF(1<N(INDEX(segments_table,2,2)),0,IF(1=N(INDEX(segments_table,2,2)),N(INDEX(segments_table,2,3)),C79*(1+N(INDEX(segments_table,2,3+(1-N(INDEX(segments_table,2,2))))))))) -> 0 | E79: =IF(INDEX(segments_table,2,1)="",0,IF(2<N(INDEX(segments_table,2,2)),0,IF(2=N(INDEX(segments_table,2,2)),N(INDEX(segments_table,2,3)),D79*(1+N(INDEX(segments_table,2,3+(2-N(INDEX(segments_table,2,2))))))))) -> 0 | F79: =IF(INDEX(segments_table,2,1)="",0,IF(3<N(INDEX(segments_table,2,2)),0,IF(3=N(INDEX(segments_table,2,2)),N(INDEX(segments_table,2,3)),E79*(1+N(INDEX(segments_table,2,3+(3-N(INDEX(segments_table,2,2))))))))) -> 0 | G79: =IF(INDEX(segments_table,2,1)="",0,IF(4<N(INDEX(segments_table,2,2)),0,IF(4=N(INDEX(segments_table,2,2)),N(INDEX(segments_table,2,3)),F79*(1+N(INDEX(segments_table,2,3+(4-N(INDEX(segments_table,2,2))))))))) -> 0 | H79: =IF(INDEX(segments_table,2,1)="",0,IF(5<N(INDEX(segments_table,2,2)),0,IF(5=N(INDEX(segments_table,2,2)),N(INDEX(segments_table,2,3)),G79*(1+N(INDEX(segments_table,2,3+(5-N(INDEX(segments_table,2,2))))))))) -> 0
A80: =IF(INDEX(segments_table,2,1)="","","COGS — "&INDEX(segments_table,2,1)) | D80: =IF(INDEX(segments_table,2,1)="","",-D79*(1-N(INDEX(segments_table,2,MIN(9+(1-N(INDEX(segments_table,2,2))),13))))) | E80: =IF(INDEX(segments_table,2,1)="","",-E79*(1-N(INDEX(segments_table,2,MIN(9+(2-N(INDEX(segments_table,2,2))),13))))) | F80: =IF(INDEX(segments_table,2,1)="","",-F79*(1-N(INDEX(segments_table,2,MIN(9+(3-N(INDEX(segments_table,2,2))),13))))) | G80: =IF(INDEX(segments_table,2,1)="","",-G79*(1-N(INDEX(segments_table,2,MIN(9+(4-N(INDEX(segments_table,2,2))),13))))) | H80: =IF(INDEX(segments_table,2,1)="","",-H79*(1-N(INDEX(segments_table,2,MIN(9+(5-N(INDEX(segments_table,2,2))),13)))))
A81: =IF(INDEX(segments_table,2,1)="","",IF(COUNT(INDEX(segments_table,2,14):INDEX(segments_table,2,18))>0,"Direct expenses — "&INDEX(segments_table,2,1),"Direct expenses (allocated) — "&INDEX(segments_table,2,1))) | D81: =IF(INDEX(segments_table,2,1)="","",IF(COUNT(INDEX(segments_table,2,14):INDEX(segments_table,2,18))>0,-D79*N(INDEX(segments_table,2,MIN(14+(1-N(INDEX(segments_table,2,2))),18))),-D79*opex_pct_revenue_y1)) | E81: =IF(INDEX(segments_table,2,1)="","",IF(COUNT(INDEX(segments_table,2,14):INDEX(segments_table,2,18))>0,-E79*N(INDEX(segments_table,2,MIN(14+(2-N(INDEX(segments_table,2,2))),18))),-E79*opex_pct_revenue_y2)) | F81: =IF(INDEX(segments_table,2,1)="","",IF(COUNT(INDEX(segments_table,2,14):INDEX(segments_table,2,18))>0,-F79*N(INDEX(segments_table,2,MIN(14+(3-N(INDEX(segments_table,2,2))),18))),-F79*opex_pct_revenue_y3)) | G81: =IF(INDEX(segments_table,2,1)="","",IF(COUNT(INDEX(segments_table,2,14):INDEX(segments_table,2,18))>0,-G79*N(INDEX(segments_table,2,MIN(14+(4-N(INDEX(segments_table,2,2))),18))),-G79*opex_pct_revenue_y4)) | H81: =IF(INDEX(segments_table,2,1)="","",IF(COUNT(INDEX(segments_table,2,14):INDEX(segments_table,2,18))>0,-H79*N(INDEX(segments_table,2,MIN(14+(5-N(INDEX(segments_table,2,2))),18))),-H79*opex_pct_revenue_y5))
A83: =IF(INDEX(segments_table,3,1)="","(segment slot 3 — unused)","Revenue — "&INDEX(segments_table,3,1)) -> (segment slot 3 — unused) | C83: =IF(INDEX(segments_table,3,1)="",0,IF(N(INDEX(segments_table,3,2))=0,N(INDEX(segments_table,3,3)),0)) -> 0 | D83: =IF(INDEX(segments_table,3,1)="",0,IF(1<N(INDEX(segments_table,3,2)),0,IF(1=N(INDEX(segments_table,3,2)),N(INDEX(segments_table,3,3)),C83*(1+N(INDEX(segments_table,3,3+(1-N(INDEX(segments_table,3,2))))))))) -> 0 | E83: =IF(INDEX(segments_table,3,1)="",0,IF(2<N(INDEX(segments_table,3,2)),0,IF(2=N(INDEX(segments_table,3,2)),N(INDEX(segments_table,3,3)),D83*(1+N(INDEX(segments_table,3,3+(2-N(INDEX(segments_table,3,2))))))))) -> 0 | F83: =IF(INDEX(segments_table,3,1)="",0,IF(3<N(INDEX(segments_table,3,2)),0,IF(3=N(INDEX(segments_table,3,2)),N(INDEX(segments_table,3,3)),E83*(1+N(INDEX(segments_table,3,3+(3-N(INDEX(segments_table,3,2))))))))) -> 0 | G83: =IF(INDEX(segments_table,3,1)="",0,IF(4<N(INDEX(segments_table,3,2)),0,IF(4=N(INDEX(segments_table,3,2)),N(INDEX(segments_table,3,3)),F83*(1+N(INDEX(segments_table,3,3+(4-N(INDEX(segments_table,3,2))))))))) -> 0 | H83: =IF(INDEX(segments_table,3,1)="",0,IF(5<N(INDEX(segments_table,3,2)),0,IF(5=N(INDEX(segments_table,3,2)),N(INDEX(segments_table,3,3)),G83*(1+N(INDEX(segments_table,3,3+(5-N(INDEX(segments_table,3,2))))))))) -> 0
A84: =IF(INDEX(segments_table,3,1)="","","COGS — "&INDEX(segments_table,3,1)) | D84: =IF(INDEX(segments_table,3,1)="","",-D83*(1-N(INDEX(segments_table,3,MIN(9+(1-N(INDEX(segments_table,3,2))),13))))) | E84: =IF(INDEX(segments_table,3,1)="","",-E83*(1-N(INDEX(segments_table,3,MIN(9+(2-N(INDEX(segments_table,3,2))),13))))) | F84: =IF(INDEX(segments_table,3,1)="","",-F83*(1-N(INDEX(segments_table,3,MIN(9+(3-N(INDEX(segments_table,3,2))),13))))) | G84: =IF(INDEX(segments_table,3,1)="","",-G83*(1-N(INDEX(segments_table,3,MIN(9+(4-N(INDEX(segments_table,3,2))),13))))) | H84: =IF(INDEX(segments_table,3,1)="","",-H83*(1-N(INDEX(segments_table,3,MIN(9+(5-N(INDEX(segments_table,3,2))),13)))))
A85: =IF(INDEX(segments_table,3,1)="","",IF(COUNT(INDEX(segments_table,3,14):INDEX(segments_table,3,18))>0,"Direct expenses — "&INDEX(segments_table,3,1),"Direct expenses (allocated) — "&INDEX(segments_table,3,1))) | D85: =IF(INDEX(segments_table,3,1)="","",IF(COUNT(INDEX(segments_table,3,14):INDEX(segments_table,3,18))>0,-D83*N(INDEX(segments_table,3,MIN(14+(1-N(INDEX(segments_table,3,2))),18))),-D83*opex_pct_revenue_y1)) | E85: =IF(INDEX(segments_table,3,1)="","",IF(COUNT(INDEX(segments_table,3,14):INDEX(segments_table,3,18))>0,-E83*N(INDEX(segments_table,3,MIN(14+(2-N(INDEX(segments_table,3,2))),18))),-E83*opex_pct_revenue_y2)) | F85: =IF(INDEX(segments_table,3,1)="","",IF(COUNT(INDEX(segments_table,3,14):INDEX(segments_table,3,18))>0,-F83*N(INDEX(segments_table,3,MIN(14+(3-N(INDEX(segments_table,3,2))),18))),-F83*opex_pct_revenue_y3)) | G85: =IF(INDEX(segments_table,3,1)="","",IF(COUNT(INDEX(segments_table,3,14):INDEX(segments_table,3,18))>0,-G83*N(INDEX(segments_table,3,MIN(14+(4-N(INDEX(segments_table,3,2))),18))),-G83*opex_pct_revenue_y4)) | H85: =IF(INDEX(segments_table,3,1)="","",IF(COUNT(INDEX(segments_table,3,14):INDEX(segments_table,3,18))>0,-H83*N(INDEX(segments_table,3,MIN(14+(5-N(INDEX(segments_table,3,2))),18))),-H83*opex_pct_revenue_y5))
A87: =IF(INDEX(segments_table,4,1)="","(segment slot 4 — unused)","Revenue — "&INDEX(segments_table,4,1)) -> (segment slot 4 — unused) | C87: =IF(INDEX(segments_table,4,1)="",0,IF(N(INDEX(segments_table,4,2))=0,N(INDEX(segments_table,4,3)),0)) -> 0 | D87: =IF(INDEX(segments_table,4,1)="",0,IF(1<N(INDEX(segments_table,4,2)),0,IF(1=N(INDEX(segments_table,4,2)),N(INDEX(segments_table,4,3)),C87*(1+N(INDEX(segments_table,4,3+(1-N(INDEX(segments_table,4,2))))))))) -> 0 | E87: =IF(INDEX(segments_table,4,1)="",0,IF(2<N(INDEX(segments_table,4,2)),0,IF(2=N(INDEX(segments_table,4,2)),N(INDEX(segments_table,4,3)),D87*(1+N(INDEX(segments_table,4,3+(2-N(INDEX(segments_table,4,2))))))))) -> 0 | F87: =IF(INDEX(segments_table,4,1)="",0,IF(3<N(INDEX(segments_table,4,2)),0,IF(3=N(INDEX(segments_table,4,2)),N(INDEX(segments_table,4,3)),E87*(1+N(INDEX(segments_table,4,3+(3-N(INDEX(segments_table,4,2))))))))) -> 0 | G87: =IF(INDEX(segments_table,4,1)="",0,IF(4<N(INDEX(segments_table,4,2)),0,IF(4=N(INDEX(segments_table,4,2)),N(INDEX(segments_table,4,3)),F87*(1+N(INDEX(segments_table,4,3+(4-N(INDEX(segments_table,4,2))))))))) -> 0 | H87: =IF(INDEX(segments_table,4,1)="",0,IF(5<N(INDEX(segments_table,4,2)),0,IF(5=N(INDEX(segments_table,4,2)),N(INDEX(segments_table,4,3)),G87*(1+N(INDEX(segments_table,4,3+(5-N(INDEX(segments_table,4,2))))))))) -> 0
A88: =IF(INDEX(segments_table,4,1)="","","COGS — "&INDEX(segments_table,4,1)) | D88: =IF(INDEX(segments_table,4,1)="","",-D87*(1-N(INDEX(segments_table,4,MIN(9+(1-N(INDEX(segments_table,4,2))),13))))) | E88: =IF(INDEX(segments_table,4,1)="","",-E87*(1-N(INDEX(segments_table,4,MIN(9+(2-N(INDEX(segments_table,4,2))),13))))) | F88: =IF(INDEX(segments_table,4,1)="","",-F87*(1-N(INDEX(segments_table,4,MIN(9+(3-N(INDEX(segments_table,4,2))),13))))) | G88: =IF(INDEX(segments_table,4,1)="","",-G87*(1-N(INDEX(segments_table,4,MIN(9+(4-N(INDEX(segments_table,4,2))),13))))) | H88: =IF(INDEX(segments_table,4,1)="","",-H87*(1-N(INDEX(segments_table,4,MIN(9+(5-N(INDEX(segments_table,4,2))),13)))))
A89: =IF(INDEX(segments_table,4,1)="","",IF(COUNT(INDEX(segments_table,4,14):INDEX(segments_table,4,18))>0,"Direct expenses — "&INDEX(segments_table,4,1),"Direct expenses (allocated) — "&INDEX(segments_table,4,1))) | D89: =IF(INDEX(segments_table,4,1)="","",IF(COUNT(INDEX(segments_table,4,14):INDEX(segments_table,4,18))>0,-D87*N(INDEX(segments_table,4,MIN(14+(1-N(INDEX(segments_table,4,2))),18))),-D87*opex_pct_revenue_y1)) | E89: =IF(INDEX(segments_table,4,1)="","",IF(COUNT(INDEX(segments_table,4,14):INDEX(segments_table,4,18))>0,-E87*N(INDEX(segments_table,4,MIN(14+(2-N(INDEX(segments_table,4,2))),18))),-E87*opex_pct_revenue_y2)) | F89: =IF(INDEX(segments_table,4,1)="","",IF(COUNT(INDEX(segments_table,4,14):INDEX(segments_table,4,18))>0,-F87*N(INDEX(segments_table,4,MIN(14+(3-N(INDEX(segments_table,4,2))),18))),-F87*opex_pct_revenue_y3)) | G89: =IF(INDEX(segments_table,4,1)="","",IF(COUNT(INDEX(segments_table,4,14):INDEX(segments_table,4,18))>0,-G87*N(INDEX(segments_table,4,MIN(14+(4-N(INDEX(segments_table,4,2))),18))),-G87*opex_pct_revenue_y4)) | H89: =IF(INDEX(segments_table,4,1)="","",IF(COUNT(INDEX(segments_table,4,14):INDEX(segments_table,4,18))>0,-H87*N(INDEX(segments_table,4,MIN(14+(5-N(INDEX(segments_table,4,2))),18))),-H87*opex_pct_revenue_y5))
A91: =IF(INDEX(segments_table,5,1)="","(segment slot 5 — unused)","Revenue — "&INDEX(segments_table,5,1)) -> (segment slot 5 — unused) | C91: =IF(INDEX(segments_table,5,1)="",0,IF(N(INDEX(segments_table,5,2))=0,N(INDEX(segments_table,5,3)),0)) -> 0 | D91: =IF(INDEX(segments_table,5,1)="",0,IF(1<N(INDEX(segments_table,5,2)),0,IF(1=N(INDEX(segments_table,5,2)),N(INDEX(segments_table,5,3)),C91*(1+N(INDEX(segments_table,5,3+(1-N(INDEX(segments_table,5,2))))))))) -> 0 | E91: =IF(INDEX(segments_table,5,1)="",0,IF(2<N(INDEX(segments_table,5,2)),0,IF(2=N(INDEX(segments_table,5,2)),N(INDEX(segments_table,5,3)),D91*(1+N(INDEX(segments_table,5,3+(2-N(INDEX(segments_table,5,2))))))))) -> 0 | F91: =IF(INDEX(segments_table,5,1)="",0,IF(3<N(INDEX(segments_table,5,2)),0,IF(3=N(INDEX(segments_table,5,2)),N(INDEX(segments_table,5,3)),E91*(1+N(INDEX(segments_table,5,3+(3-N(INDEX(segments_table,5,2))))))))) -> 0 | G91: =IF(INDEX(segments_table,5,1)="",0,IF(4<N(INDEX(segments_table,5,2)),0,IF(4=N(INDEX(segments_table,5,2)),N(INDEX(segments_table,5,3)),F91*(1+N(INDEX(segments_table,5,3+(4-N(INDEX(segments_table,5,2))))))))) -> 0 | H91: =IF(INDEX(segments_table,5,1)="",0,IF(5<N(INDEX(segments_table,5,2)),0,IF(5=N(INDEX(segments_table,5,2)),N(INDEX(segments_table,5,3)),G91*(1+N(INDEX(segments_table,5,3+(5-N(INDEX(segments_table,5,2))))))))) -> 0
A92: =IF(INDEX(segments_table,5,1)="","","COGS — "&INDEX(segments_table,5,1)) | D92: =IF(INDEX(segments_table,5,1)="","",-D91*(1-N(INDEX(segments_table,5,MIN(9+(1-N(INDEX(segments_table,5,2))),13))))) | E92: =IF(INDEX(segments_table,5,1)="","",-E91*(1-N(INDEX(segments_table,5,MIN(9+(2-N(INDEX(segments_table,5,2))),13))))) | F92: =IF(INDEX(segments_table,5,1)="","",-F91*(1-N(INDEX(segments_table,5,MIN(9+(3-N(INDEX(segments_table,5,2))),13))))) | G92: =IF(INDEX(segments_table,5,1)="","",-G91*(1-N(INDEX(segments_table,5,MIN(9+(4-N(INDEX(segments_table,5,2))),13))))) | H92: =IF(INDEX(segments_table,5,1)="","",-H91*(1-N(INDEX(segments_table,5,MIN(9+(5-N(INDEX(segments_table,5,2))),13)))))
A93: =IF(INDEX(segments_table,5,1)="","",IF(COUNT(INDEX(segments_table,5,14):INDEX(segments_table,5,18))>0,"Direct expenses — "&INDEX(segments_table,5,1),"Direct expenses (allocated) — "&INDEX(segments_table,5,1))) | D93: =IF(INDEX(segments_table,5,1)="","",IF(COUNT(INDEX(segments_table,5,14):INDEX(segments_table,5,18))>0,-D91*N(INDEX(segments_table,5,MIN(14+(1-N(INDEX(segments_table,5,2))),18))),-D91*opex_pct_revenue_y1)) | E93: =IF(INDEX(segments_table,5,1)="","",IF(COUNT(INDEX(segments_table,5,14):INDEX(segments_table,5,18))>0,-E91*N(INDEX(segments_table,5,MIN(14+(2-N(INDEX(segments_table,5,2))),18))),-E91*opex_pct_revenue_y2)) | F93: =IF(INDEX(segments_table,5,1)="","",IF(COUNT(INDEX(segments_table,5,14):INDEX(segments_table,5,18))>0,-F91*N(INDEX(segments_table,5,MIN(14+(3-N(INDEX(segments_table,5,2))),18))),-F91*opex_pct_revenue_y3)) | G93: =IF(INDEX(segments_table,5,1)="","",IF(COUNT(INDEX(segments_table,5,14):INDEX(segments_table,5,18))>0,-G91*N(INDEX(segments_table,5,MIN(14+(4-N(INDEX(segments_table,5,2))),18))),-G91*opex_pct_revenue_y4)) | H93: =IF(INDEX(segments_table,5,1)="","",IF(COUNT(INDEX(segments_table,5,14):INDEX(segments_table,5,18))>0,-H91*N(INDEX(segments_table,5,MIN(14+(5-N(INDEX(segments_table,5,2))),18))),-H91*opex_pct_revenue_y5))
A95: =IF(INDEX(segments_table,6,1)="","(segment slot 6 — unused)","Revenue — "&INDEX(segments_table,6,1)) -> (segment slot 6 — unused) | C95: =IF(INDEX(segments_table,6,1)="",0,IF(N(INDEX(segments_table,6,2))=0,N(INDEX(segments_table,6,3)),0)) -> 0 | D95: =IF(INDEX(segments_table,6,1)="",0,IF(1<N(INDEX(segments_table,6,2)),0,IF(1=N(INDEX(segments_table,6,2)),N(INDEX(segments_table,6,3)),C95*(1+N(INDEX(segments_table,6,3+(1-N(INDEX(segments_table,6,2))))))))) -> 0 | E95: =IF(INDEX(segments_table,6,1)="",0,IF(2<N(INDEX(segments_table,6,2)),0,IF(2=N(INDEX(segments_table,6,2)),N(INDEX(segments_table,6,3)),D95*(1+N(INDEX(segments_table,6,3+(2-N(INDEX(segments_table,6,2))))))))) -> 0 | F95: =IF(INDEX(segments_table,6,1)="",0,IF(3<N(INDEX(segments_table,6,2)),0,IF(3=N(INDEX(segments_table,6,2)),N(INDEX(segments_table,6,3)),E95*(1+N(INDEX(segments_table,6,3+(3-N(INDEX(segments_table,6,2))))))))) -> 0 | G95: =IF(INDEX(segments_table,6,1)="",0,IF(4<N(INDEX(segments_table,6,2)),0,IF(4=N(INDEX(segments_table,6,2)),N(INDEX(segments_table,6,3)),F95*(1+N(INDEX(segments_table,6,3+(4-N(INDEX(segments_table,6,2))))))))) -> 0 | H95: =IF(INDEX(segments_table,6,1)="",0,IF(5<N(INDEX(segments_table,6,2)),0,IF(5=N(INDEX(segments_table,6,2)),N(INDEX(segments_table,6,3)),G95*(1+N(INDEX(segments_table,6,3+(5-N(INDEX(segments_table,6,2))))))))) -> 0
A96: =IF(INDEX(segments_table,6,1)="","","COGS — "&INDEX(segments_table,6,1)) | D96: =IF(INDEX(segments_table,6,1)="","",-D95*(1-N(INDEX(segments_table,6,MIN(9+(1-N(INDEX(segments_table,6,2))),13))))) | E96: =IF(INDEX(segments_table,6,1)="","",-E95*(1-N(INDEX(segments_table,6,MIN(9+(2-N(INDEX(segments_table,6,2))),13))))) | F96: =IF(INDEX(segments_table,6,1)="","",-F95*(1-N(INDEX(segments_table,6,MIN(9+(3-N(INDEX(segments_table,6,2))),13))))) | G96: =IF(INDEX(segments_table,6,1)="","",-G95*(1-N(INDEX(segments_table,6,MIN(9+(4-N(INDEX(segments_table,6,2))),13))))) | H96: =IF(INDEX(segments_table,6,1)="","",-H95*(1-N(INDEX(segments_table,6,MIN(9+(5-N(INDEX(segments_table,6,2))),13)))))
A97: =IF(INDEX(segments_table,6,1)="","",IF(COUNT(INDEX(segments_table,6,14):INDEX(segments_table,6,18))>0,"Direct expenses — "&INDEX(segments_table,6,1),"Direct expenses (allocated) — "&INDEX(segments_table,6,1))) | D97: =IF(INDEX(segments_table,6,1)="","",IF(COUNT(INDEX(segments_table,6,14):INDEX(segments_table,6,18))>0,-D95*N(INDEX(segments_table,6,MIN(14+(1-N(INDEX(segments_table,6,2))),18))),-D95*opex_pct_revenue_y1)) | E97: =IF(INDEX(segments_table,6,1)="","",IF(COUNT(INDEX(segments_table,6,14):INDEX(segments_table,6,18))>0,-E95*N(INDEX(segments_table,6,MIN(14+(2-N(INDEX(segments_table,6,2))),18))),-E95*opex_pct_revenue_y2)) | F97: =IF(INDEX(segments_table,6,1)="","",IF(COUNT(INDEX(segments_table,6,14):INDEX(segments_table,6,18))>0,-F95*N(INDEX(segments_table,6,MIN(14+(3-N(INDEX(segments_table,6,2))),18))),-F95*opex_pct_revenue_y3)) | G97: =IF(INDEX(segments_table,6,1)="","",IF(COUNT(INDEX(segments_table,6,14):INDEX(segments_table,6,18))>0,-G95*N(INDEX(segments_table,6,MIN(14+(4-N(INDEX(segments_table,6,2))),18))),-G95*opex_pct_revenue_y4)) | H97: =IF(INDEX(segments_table,6,1)="","",IF(COUNT(INDEX(segments_table,6,14):INDEX(segments_table,6,18))>0,-H95*N(INDEX(segments_table,6,MIN(14+(5-N(INDEX(segments_table,6,2))),18))),-H95*opex_pct_revenue_y5))
A99: =IF(INDEX(segments_table,7,1)="","(segment slot 7 — unused)","Revenue — "&INDEX(segments_table,7,1)) -> (segment slot 7 — unused) | C99: =IF(INDEX(segments_table,7,1)="",0,IF(N(INDEX(segments_table,7,2))=0,N(INDEX(segments_table,7,3)),0)) -> 0 | D99: =IF(INDEX(segments_table,7,1)="",0,IF(1<N(INDEX(segments_table,7,2)),0,IF(1=N(INDEX(segments_table,7,2)),N(INDEX(segments_table,7,3)),C99*(1+N(INDEX(segments_table,7,3+(1-N(INDEX(segments_table,7,2))))))))) -> 0 | E99: =IF(INDEX(segments_table,7,1)="",0,IF(2<N(INDEX(segments_table,7,2)),0,IF(2=N(INDEX(segments_table,7,2)),N(INDEX(segments_table,7,3)),D99*(1+N(INDEX(segments_table,7,3+(2-N(INDEX(segments_table,7,2))))))))) -> 0 | F99: =IF(INDEX(segments_table,7,1)="",0,IF(3<N(INDEX(segments_table,7,2)),0,IF(3=N(INDEX(segments_table,7,2)),N(INDEX(segments_table,7,3)),E99*(1+N(INDEX(segments_table,7,3+(3-N(INDEX(segments_table,7,2))))))))) -> 0 | G99: =IF(INDEX(segments_table,7,1)="",0,IF(4<N(INDEX(segments_table,7,2)),0,IF(4=N(INDEX(segments_table,7,2)),N(INDEX(segments_table,7,3)),F99*(1+N(INDEX(segments_table,7,3+(4-N(INDEX(segments_table,7,2))))))))) -> 0 | H99: =IF(INDEX(segments_table,7,1)="",0,IF(5<N(INDEX(segments_table,7,2)),0,IF(5=N(INDEX(segments_table,7,2)),N(INDEX(segments_table,7,3)),G99*(1+N(INDEX(segments_table,7,3+(5-N(INDEX(segments_table,7,2))))))))) -> 0
A100: =IF(INDEX(segments_table,7,1)="","","COGS — "&INDEX(segments_table,7,1)) | D100: =IF(INDEX(segments_table,7,1)="","",-D99*(1-N(INDEX(segments_table,7,MIN(9+(1-N(INDEX(segments_table,7,2))),13))))) | E100: =IF(INDEX(segments_table,7,1)="","",-E99*(1-N(INDEX(segments_table,7,MIN(9+(2-N(INDEX(segments_table,7,2))),13))))) | F100: =IF(INDEX(segments_table,7,1)="","",-F99*(1-N(INDEX(segments_table,7,MIN(9+(3-N(INDEX(segments_table,7,2))),13))))) | G100: =IF(INDEX(segments_table,7,1)="","",-G99*(1-N(INDEX(segments_table,7,MIN(9+(4-N(INDEX(segments_table,7,2))),13))))) | H100: =IF(INDEX(segments_table,7,1)="","",-H99*(1-N(INDEX(segments_table,7,MIN(9+(5-N(INDEX(segments_table,7,2))),13)))))
A101: =IF(INDEX(segments_table,7,1)="","",IF(COUNT(INDEX(segments_table,7,14):INDEX(segments_table,7,18))>0,"Direct expenses — "&INDEX(segments_table,7,1),"Direct expenses (allocated) — "&INDEX(segments_table,7,1))) | D101: =IF(INDEX(segments_table,7,1)="","",IF(COUNT(INDEX(segments_table,7,14):INDEX(segments_table,7,18))>0,-D99*N(INDEX(segments_table,7,MIN(14+(1-N(INDEX(segments_table,7,2))),18))),-D99*opex_pct_revenue_y1)) | E101: =IF(INDEX(segments_table,7,1)="","",IF(COUNT(INDEX(segments_table,7,14):INDEX(segments_table,7,18))>0,-E99*N(INDEX(segments_table,7,MIN(14+(2-N(INDEX(segments_table,7,2))),18))),-E99*opex_pct_revenue_y2)) | F101: =IF(INDEX(segments_table,7,1)="","",IF(COUNT(INDEX(segments_table,7,14):INDEX(segments_table,7,18))>0,-F99*N(INDEX(segments_table,7,MIN(14+(3-N(INDEX(segments_table,7,2))),18))),-F99*opex_pct_revenue_y3)) | G101: =IF(INDEX(segments_table,7,1)="","",IF(COUNT(INDEX(segments_table,7,14):INDEX(segments_table,7,18))>0,-G99*N(INDEX(segments_table,7,MIN(14+(4-N(INDEX(segments_table,7,2))),18))),-G99*opex_pct_revenue_y4)) | H101: =IF(INDEX(segments_table,7,1)="","",IF(COUNT(INDEX(segments_table,7,14):INDEX(segments_table,7,18))>0,-H99*N(INDEX(segments_table,7,MIN(14+(5-N(INDEX(segments_table,7,2))),18))),-H99*opex_pct_revenue_y5))
A103: =IF(INDEX(segments_table,8,1)="","(segment slot 8 — unused)","Revenue — "&INDEX(segments_table,8,1)) -> (segment slot 8 — unused) | C103: =IF(INDEX(segments_table,8,1)="",0,IF(N(INDEX(segments_table,8,2))=0,N(INDEX(segments_table,8,3)),0)) -> 0 | D103: =IF(INDEX(segments_table,8,1)="",0,IF(1<N(INDEX(segments_table,8,2)),0,IF(1=N(INDEX(segments_table,8,2)),N(INDEX(segments_table,8,3)),C103*(1+N(INDEX(segments_table,8,3+(1-N(INDEX(segments_table,8,2))))))))) -> 0 | E103: =IF(INDEX(segments_table,8,1)="",0,IF(2<N(INDEX(segments_table,8,2)),0,IF(2=N(INDEX(segments_table,8,2)),N(INDEX(segments_table,8,3)),D103*(1+N(INDEX(segments_table,8,3+(2-N(INDEX(segments_table,8,2))))))))) -> 0 | F103: =IF(INDEX(segments_table,8,1)="",0,IF(3<N(INDEX(segments_table,8,2)),0,IF(3=N(INDEX(segments_table,8,2)),N(INDEX(segments_table,8,3)),E103*(1+N(INDEX(segments_table,8,3+(3-N(INDEX(segments_table,8,2))))))))) -> 0 | G103: =IF(INDEX(segments_table,8,1)="",0,IF(4<N(INDEX(segments_table,8,2)),0,IF(4=N(INDEX(segments_table,8,2)),N(INDEX(segments_table,8,3)),F103*(1+N(INDEX(segments_table,8,3+(4-N(INDEX(segments_table,8,2))))))))) -> 0 | H103: =IF(INDEX(segments_table,8,1)="",0,IF(5<N(INDEX(segments_table,8,2)),0,IF(5=N(INDEX(segments_table,8,2)),N(INDEX(segments_table,8,3)),G103*(1+N(INDEX(segments_table,8,3+(5-N(INDEX(segments_table,8,2))))))))) -> 0
A104: =IF(INDEX(segments_table,8,1)="","","COGS — "&INDEX(segments_table,8,1)) | D104: =IF(INDEX(segments_table,8,1)="","",-D103*(1-N(INDEX(segments_table,8,MIN(9+(1-N(INDEX(segments_table,8,2))),13))))) | E104: =IF(INDEX(segments_table,8,1)="","",-E103*(1-N(INDEX(segments_table,8,MIN(9+(2-N(INDEX(segments_table,8,2))),13))))) | F104: =IF(INDEX(segments_table,8,1)="","",-F103*(1-N(INDEX(segments_table,8,MIN(9+(3-N(INDEX(segments_table,8,2))),13))))) | G104: =IF(INDEX(segments_table,8,1)="","",-G103*(1-N(INDEX(segments_table,8,MIN(9+(4-N(INDEX(segments_table,8,2))),13))))) | H104: =IF(INDEX(segments_table,8,1)="","",-H103*(1-N(INDEX(segments_table,8,MIN(9+(5-N(INDEX(segments_table,8,2))),13)))))
A105: =IF(INDEX(segments_table,8,1)="","",IF(COUNT(INDEX(segments_table,8,14):INDEX(segments_table,8,18))>0,"Direct expenses — "&INDEX(segments_table,8,1),"Direct expenses (allocated) — "&INDEX(segments_table,8,1))) | D105: =IF(INDEX(segments_table,8,1)="","",IF(COUNT(INDEX(segments_table,8,14):INDEX(segments_table,8,18))>0,-D103*N(INDEX(segments_table,8,MIN(14+(1-N(INDEX(segments_table,8,2))),18))),-D103*opex_pct_revenue_y1)) | E105: =IF(INDEX(segments_table,8,1)="","",IF(COUNT(INDEX(segments_table,8,14):INDEX(segments_table,8,18))>0,-E103*N(INDEX(segments_table,8,MIN(14+(2-N(INDEX(segments_table,8,2))),18))),-E103*opex_pct_revenue_y2)) | F105: =IF(INDEX(segments_table,8,1)="","",IF(COUNT(INDEX(segments_table,8,14):INDEX(segments_table,8,18))>0,-F103*N(INDEX(segments_table,8,MIN(14+(3-N(INDEX(segments_table,8,2))),18))),-F103*opex_pct_revenue_y3)) | G105: =IF(INDEX(segments_table,8,1)="","",IF(COUNT(INDEX(segments_table,8,14):INDEX(segments_table,8,18))>0,-G103*N(INDEX(segments_table,8,MIN(14+(4-N(INDEX(segments_table,8,2))),18))),-G103*opex_pct_revenue_y4)) | H105: =IF(INDEX(segments_table,8,1)="","",IF(COUNT(INDEX(segments_table,8,14):INDEX(segments_table,8,18))>0,-H103*N(INDEX(segments_table,8,MIN(14+(5-N(INDEX(segments_table,8,2))),18))),-H103*opex_pct_revenue_y5))
A107: Carved-out revenue (streams with own Opex%) | C107: 0 | D107: =IF(COUNT(INDEX(segments_table,1,14):INDEX(segments_table,1,18))>0,D75,0)+IF(COUNT(INDEX(segments_table,2,14):INDEX(segments_table,2,18))>0,D79,0)+IF(COUNT(INDEX(segments_table,3,14):INDEX(segments_table,3,18))>0,D83,0)+IF(COUNT(INDEX(segments_table,4,14):INDEX(segments_table,4,18))>0,D87,0)+IF(COUNT(INDEX(segments_table,5,14):INDEX(segments_table,5,18))>0,D91,0)+IF(COUNT(INDEX(segments_table,6,14):INDEX(segments_table,6,18))>0,D95,0)+IF(COUNT(INDEX(segments_table,7,14):INDEX(segments_table,7,18))>0,D99,0)+IF(COUNT(INDEX(segments_table,8,14):INDEX(segments_table,8,18))>0,D103,0) -> 0 | E107: =IF(COUNT(INDEX(segments_table,1,14):INDEX(segments_table,1,18))>0,E75,0)+IF(COUNT(INDEX(segments_table,2,14):INDEX(segments_table,2,18))>0,E79,0)+IF(COUNT(INDEX(segments_table,3,14):INDEX(segments_table,3,18))>0,E83,0)+IF(COUNT(INDEX(segments_table,4,14):INDEX(segments_table,4,18))>0,E87,0)+IF(COUNT(INDEX(segments_table,5,14):INDEX(segments_table,5,18))>0,E91,0)+IF(COUNT(INDEX(segments_table,6,14):INDEX(segments_table,6,18))>0,E95,0)+IF(COUNT(INDEX(segments_table,7,14):INDEX(segments_table,7,18))>0,E99,0)+IF(COUNT(INDEX(segments_table,8,14):INDEX(segments_table,8,18))>0,E103,0) -> 0 | F107: =IF(COUNT(INDEX(segments_table,1,14):INDEX(segments_table,1,18))>0,F75,0)+IF(COUNT(INDEX(segments_table,2,14):INDEX(segments_table,2,18))>0,F79,0)+IF(COUNT(INDEX(segments_table,3,14):INDEX(segments_table,3,18))>0,F83,0)+IF(COUNT(INDEX(segments_table,4,14):INDEX(segments_table,4,18))>0,F87,0)+IF(COUNT(INDEX(segments_table,5,14):INDEX(segments_table,5,18))>0,F91,0)+IF(COUNT(INDEX(segments_table,6,14):INDEX(segments_table,6,18))>0,F95,0)+IF(COUNT(INDEX(segments_table,7,14):INDEX(segments_table,7,18))>0,F99,0)+IF(COUNT(INDEX(segments_table,8,14):INDEX(segments_table,8,18))>0,F103,0) -> 0 | G107: =IF(COUNT(INDEX(segments_table,1,14):INDEX(segments_table,1,18))>0,G75,0)+IF(COUNT(INDEX(segments_table,2,14):INDEX(segments_table,2,18))>0,G79,0)+IF(COUNT(INDEX(segments_table,3,14):INDEX(segments_table,3,18))>0,G83,0)+IF(COUNT(INDEX(segments_table,4,14):INDEX(segments_table,4,18))>0,G87,0)+IF(COUNT(INDEX(segments_table,5,14):INDEX(segments_table,5,18))>0,G91,0)+IF(COUNT(INDEX(segments_table,6,14):INDEX(segments_table,6,18))>0,G95,0)+IF(COUNT(INDEX(segments_table,7,14):INDEX(segments_table,7,18))>0,G99,0)+IF(COUNT(INDEX(segments_table,8,14):INDEX(segments_table,8,18))>0,G103,0) -> 0 | H107: =IF(COUNT(INDEX(segments_table,1,14):INDEX(segments_table,1,18))>0,H75,0)+IF(COUNT(INDEX(segments_table,2,14):INDEX(segments_table,2,18))>0,H79,0)+IF(COUNT(INDEX(segments_table,3,14):INDEX(segments_table,3,18))>0,H83,0)+IF(COUNT(INDEX(segments_table,4,14):INDEX(segments_table,4,18))>0,H87,0)+IF(COUNT(INDEX(segments_table,5,14):INDEX(segments_table,5,18))>0,H91,0)+IF(COUNT(INDEX(segments_table,6,14):INDEX(segments_table,6,18))>0,H95,0)+IF(COUNT(INDEX(segments_table,7,14):INDEX(segments_table,7,18))>0,H99,0)+IF(COUNT(INDEX(segments_table,8,14):INDEX(segments_table,8,18))>0,H103,0) -> 0
A108: Direct expenses — carved-out streams subtotal | C108: 0 | D108: =IF(COUNT(INDEX(segments_table,1,14):INDEX(segments_table,1,18))>0,N(D77),0)+IF(COUNT(INDEX(segments_table,2,14):INDEX(segments_table,2,18))>0,N(D81),0)+IF(COUNT(INDEX(segments_table,3,14):INDEX(segments_table,3,18))>0,N(D85),0)+IF(COUNT(INDEX(segments_table,4,14):INDEX(segments_table,4,18))>0,N(D89),0)+IF(COUNT(INDEX(segments_table,5,14):INDEX(segments_table,5,18))>0,N(D93),0)+IF(COUNT(INDEX(segments_table,6,14):INDEX(segments_table,6,18))>0,N(D97),0)+IF(COUNT(INDEX(segments_table,7,14):INDEX(segments_table,7,18))>0,N(D101),0)+IF(COUNT(INDEX(segments_table,8,14):INDEX(segments_table,8,18))>0,N(D105),0) -> 0 | E108: =IF(COUNT(INDEX(segments_table,1,14):INDEX(segments_table,1,18))>0,N(E77),0)+IF(COUNT(INDEX(segments_table,2,14):INDEX(segments_table,2,18))>0,N(E81),0)+IF(COUNT(INDEX(segments_table,3,14):INDEX(segments_table,3,18))>0,N(E85),0)+IF(COUNT(INDEX(segments_table,4,14):INDEX(segments_table,4,18))>0,N(E89),0)+IF(COUNT(INDEX(segments_table,5,14):INDEX(segments_table,5,18))>0,N(E93),0)+IF(COUNT(INDEX(segments_table,6,14):INDEX(segments_table,6,18))>0,N(E97),0)+IF(COUNT(INDEX(segments_table,7,14):INDEX(segments_table,7,18))>0,N(E101),0)+IF(COUNT(INDEX(segments_table,8,14):INDEX(segments_table,8,18))>0,N(E105),0) -> 0 | F108: =IF(COUNT(INDEX(segments_table,1,14):INDEX(segments_table,1,18))>0,N(F77),0)+IF(COUNT(INDEX(segments_table,2,14):INDEX(segments_table,2,18))>0,N(F81),0)+IF(COUNT(INDEX(segments_table,3,14):INDEX(segments_table,3,18))>0,N(F85),0)+IF(COUNT(INDEX(segments_table,4,14):INDEX(segments_table,4,18))>0,N(F89),0)+IF(COUNT(INDEX(segments_table,5,14):INDEX(segments_table,5,18))>0,N(F93),0)+IF(COUNT(INDEX(segments_table,6,14):INDEX(segments_table,6,18))>0,N(F97),0)+IF(COUNT(INDEX(segments_table,7,14):INDEX(segments_table,7,18))>0,N(F101),0)+IF(COUNT(INDEX(segments_table,8,14):INDEX(segments_table,8,18))>0,N(F105),0) -> 0 | G108: =IF(COUNT(INDEX(segments_table,1,14):INDEX(segments_table,1,18))>0,N(G77),0)+IF(COUNT(INDEX(segments_table,2,14):INDEX(segments_table,2,18))>0,N(G81),0)+IF(COUNT(INDEX(segments_table,3,14):INDEX(segments_table,3,18))>0,N(G85),0)+IF(COUNT(INDEX(segments_table,4,14):INDEX(segments_table,4,18))>0,N(G89),0)+IF(COUNT(INDEX(segments_table,5,14):INDEX(segments_table,5,18))>0,N(G93),0)+IF(COUNT(INDEX(segments_table,6,14):INDEX(segments_table,6,18))>0,N(G97),0)+IF(COUNT(INDEX(segments_table,7,14):INDEX(segments_table,7,18))>0,N(G101),0)+IF(COUNT(INDEX(segments_table,8,14):INDEX(segments_table,8,18))>0,N(G105),0) -> 0 | H108: =IF(COUNT(INDEX(segments_table,1,14):INDEX(segments_table,1,18))>0,N(H77),0)+IF(COUNT(INDEX(segments_table,2,14):INDEX(segments_table,2,18))>0,N(H81),0)+IF(COUNT(INDEX(segments_table,3,14):INDEX(segments_table,3,18))>0,N(H85),0)+IF(COUNT(INDEX(segments_table,4,14):INDEX(segments_table,4,18))>0,N(H89),0)+IF(COUNT(INDEX(segments_table,5,14):INDEX(segments_table,5,18))>0,N(H93),0)+IF(COUNT(INDEX(segments_table,6,14):INDEX(segments_table,6,18))>0,N(H97),0)+IF(COUNT(INDEX(segments_table,7,14):INDEX(segments_table,7,18))>0,N(H101),0)+IF(COUNT(INDEX(segments_table,8,14):INDEX(segments_table,8,18))>0,N(H105),0) -> 0

Sheet DCF
A1: DCF — Per Management scenario
A2: FCFF schedule from Projections, discounted at scenario WACC. Convention: full-period discounting (no stub-year partial); terminal value computed at end of Y5 and PV'd at the same Y5 discount factor.
A4: Item | B4: Unit | D4: Y1 | E4: Y2 | F4: Y3 | G4: Y4 | H4: Y5 | I4: Terminal
A6: Discount inputs
A7: WACC (this scenario) | B7: % | D7: =wacc_per_mgmt -> 0.13905529
A8: Terminal growth rate | B8: % | D8: =terminal_growth_rate -> 0.03
A10: FCFF & discount mechanics
A11: FCFF | B11: (currency × unit) | D11: =Projections!D71 -> -2889.5 | E11: =Projections!E71 -> 10280.5 | F11: =Projections!F71 -> 27222.416 | G11: =Projections!G71 -> 39125.256 | H11: =Projections!H71 -> 51448.336
A12: Discount period | B12: years | D12: 1 | E12: 2 | F12: 3 | G12: 4 | H12: 5
A13: Discount factor | B13: x | D13: =1/(1+wacc_per_mgmt)^D12 -> 0.87792051 | E13: =1/(1+wacc_per_mgmt)^E12 -> 0.77074441 | F13: =1/(1+wacc_per_mgmt)^F12 -> 0.67665232 | G13: =1/(1+wacc_per_mgmt)^G12 -> 0.59404695 | H13: =1/(1+wacc_per_mgmt)^H12 -> 0.521526
A14: PV of FCFF | B14: (currency × unit) | D14: =D11*D13 -> -2536.7513 | E14: =E11*E13 -> 7923.6379 | F14: =F11*F13 -> 18420.111 | G14: =G11*G13 -> 23242.239 | H14: =H11*H13 -> 26831.645
A16: Terminal value
A17: Method | I17: =terminal_method -> gordon_growth
A18: Y5 FCFF | B18: (currency × unit) | I18: =Projections!H71 -> 51448.336
A19: Terminal value — Gordon Growth | B19: (currency × unit) | I19: =IFERROR(I18*(1+terminal_growth_rate)/(wacc_per_mgmt-terminal_growth_rate),0) -> 485916.68
A20: Terminal value — Exit Multiple | B20: (currency × unit) | I20: =IF(EXACT(terminal_exit_multiple_type,"EV/EBITDA"),Projections!H50*terminal_exit_multiple_value,IF(EXACT(terminal_exit_multiple_type,"EV/Sales"),Projections!H25*terminal_exit_multiple_value,IF(EXACT(terminal_exit_multiple_type,"P/E"),Projections!H58*terminal_exit_multiple_value,0))) -> 0
A21: Selected terminal value | B21: (currency × unit) | I21: =IF(EXACT(terminal_method,"exit_multiple"),I20,I19) -> 485916.68
A22: PV of terminal value | B22: (currency × unit) | I22: =I21*H13 -> 253418.18
A24: Enterprise Value
A25: Sum of PV of explicit-period FCFF | I25: =SUM(D14:H14) -> 73880.882
A26: + PV of terminal value | I26: =I22 -> 253418.18
A27: Enterprise Value | I27: =I25+I26 -> 327299.06

Sheet DCF (Independent)
A1: DCF — Independent scenario
A2: FCFF schedule from Projections, discounted at scenario WACC. Convention: full-period discounting (no stub-year partial); terminal value computed at end of Y5 and PV'd at the same Y5 discount factor.
A4: Item | B4: Unit | D4: Y1 | E4: Y2 | F4: Y3 | G4: Y4 | H4: Y5 | I4: Terminal
A6: Discount inputs
A7: WACC (this scenario) | B7: % | D7: =wacc_indep -> 0.1558895
A8: Terminal growth rate | B8: % | D8: =terminal_growth_rate -> 0.03
A10: FCFF & discount mechanics
A11: FCFF | B11: (currency × unit) | D11: =Projections!D71 -> -2889.5 | E11: =Projections!E71 -> 10280.5 | F11: =Projections!F71 -> 27222.416 | G11: =Projections!G71 -> 39125.256 | H11: =Projections!H71 -> 51448.336
A12: Discount period | B12: years | D12: 1 | E12: 2 | F12: 3 | G12: 4 | H12: 5
A13: Discount factor | B13: x | D13: =1/(1+wacc_indep)^D12 -> 0.8651346 | E13: =1/(1+wacc_indep)^E12 -> 0.74845788 | F13: =1/(1+wacc_indep)^F12 -> 0.6475168 | G13: =1/(1+wacc_indep)^G12 -> 0.56018919 | H13: =1/(1+wacc_indep)^H12 -> 0.48463905
A14: PV of FCFF | B14: (currency × unit) | D14: =D11*D13 -> -2499.8064 | E14: =E11*E13 -> 7694.5212 | F14: =F11*F13 -> 17626.972 | G14: =G11*G13 -> 21917.546 | H14: =H11*H13 -> 24933.873
A16: Terminal value
A17: Method | I17: =terminal_method -> gordon_growth
A18: Y5 FCFF | B18: (currency × unit) | I18: =Projections!H71 -> 51448.336
A19: Terminal value — Gordon Growth | B19: (currency × unit) | I19: =IFERROR(I18*(1+terminal_growth_rate)/(wacc_indep-terminal_growth_rate),0) -> 420938.89
A20: Terminal value — Exit Multiple | B20: (currency × unit) | I20: =IF(EXACT(terminal_exit_multiple_type,"EV/EBITDA"),Projections!H50*terminal_exit_multiple_value,IF(EXACT(terminal_exit_multiple_type,"EV/Sales"),Projections!H25*terminal_exit_multiple_value,IF(EXACT(terminal_exit_multiple_type,"P/E"),Projections!H58*terminal_exit_multiple_value,0))) -> 0
A21: Selected terminal value | B21: (currency × unit) | I21: =IF(EXACT(terminal_method,"exit_multiple"),I20,I19) -> 420938.89
A22: PV of terminal value | B22: (currency × unit) | I22: =I21*H13 -> 204003.43
A24: Enterprise Value
A25: Sum of PV of explicit-period FCFF | I25: =SUM(D14:H14) -> 69673.105
A26: + PV of terminal value | I26: =I22 -> 204003.43
A27: Enterprise Value | I27: =I25+I26 -> 273676.53

Sheet Comps
A1: Comps — comparable companies cross-check
A2: Apply CoCo NTM trading multiples to target Y1 metrics. Implied EV from EV/Sales × Revenue and EV/EBITDA × EBITDA cross-check the DCF. P/E × Net Income gives implied Equity (bridge to EV via surplus/net debt).
A4: Multiple | B4: Target metric (Y1) | C4: CoCo Q1 | D4: CoCo Median | E4: CoCo Q3 | F4: Implied (low) | G4: Implied (mid) | H4: Implied (high)
A6: NTM-based multiples (applied to Y1)
A7: EV/Sales NTM | B7: =Projections!D25 -> 145000 | C7: ='CoCo Multiples'!F41 -> 3.075 | D7: ='CoCo Multiples'!F39 -> 3.35 | E7: ='CoCo Multiples'!F38 -> 3.775 | F7: =IFERROR(B7*C7,"n/a") -> 445875 | G7: =IFERROR(B7*D7,"n/a") -> 485750 | H7: =IFERROR(B7*E7,"n/a") -> 547375
A8: EV/EBITDA NTM | B8: =Projections!D50 -> 10150 | C8: ='CoCo Multiples'!H41 -> 13.125 | D8: ='CoCo Multiples'!H39 -> 14.25 | E8: ='CoCo Multiples'!H38 -> 15.75 | F8: =IFERROR(B8*C8,"n/a") -> 133218.75 | G8: =IFERROR(B8*D8,"n/a") -> 144637.5 | H8: =IFERROR(B8*E8,"n/a") -> 159862.5
A9: P/E NTM (gives Equity) | B9: =Projections!D58 -> 3610.5 | C9: ='CoCo Multiples'!J41 -> 19.5 | D9: ='CoCo Multiples'!J39 -> 21 | E9: ='CoCo Multiples'!J38 -> 23 | F9: =IFERROR(B9*C9,"n/a") -> 70404.75 | G9: =IFERROR(B9*D9,"n/a") -> 75820.5 | H9: =IFERROR(B9*E9,"n/a") -> 83041.5
A11: LTM-based multiples (not wired in v1 — needs Historical FS link)
A12: TODO: when Historical FS sheet is built, wire LTM target metrics here and apply 'CoCo Multiples'!E/G/I (LTM) columns.
A14: Cross-check summary — DCF vs CoCo-implied
A15: DCF EV — Per Management | B15: =DCF!I27 -> 327299.06
A16: DCF EV — Independent | B16: ='DCF (Independent)'!I27 -> 273676.53
A17: CoCo-implied EV — EV/Sales NTM (Median) | B17: =G7 -> 485750
A18: CoCo-implied EV — EV/EBITDA NTM (Median) | B18: =G8 -> 144637.5
A19: CoCo-implied Equity — P/E NTM (Median) | B19: =G9 -> 75820.5
A20: CoCo-implied EV — P/E NTM (bridged from Equity) | B20: =G9-surplus_assets-non_operating_assets+IF(ISNUMBER(net_debt_override),net_debt_override,0)+minority_interests -> 50820.5
A21: Mean of CoCo-implied EVs (Sales + EBITDA + P/E) | B21: =AVERAGE(B17,B18,B20) -> 227069.33

Sheet Football Field
A1: Football Field — methodology ranges (DCF primary; others cross-checks)
A2: Range chart input. DCF range comes from the two WACC scenarios and is the primary methodology (weight_dcf = 1.0). Comps range from CoCo Q1/Median/Q3 and Precedent range from precedents_table are retained as cross-checks against the DCF EV (±10% band, see rows 22-26).
A4: Methodology | B4: Low | C4: Mid | D4: High | E4: Weight | F4: Weighted Mid | G4: Notes
A6: Methodology ranges (EV in currency × unit)
A7: DCF (across scenarios) | B7: =MIN(DCF!I27,'DCF (Independent)'!I27) -> 273676.53 | C7: =AVERAGE(DCF!I27,'DCF (Independent)'!I27) -> 300487.8 | D7: =MAX(DCF!I27,'DCF (Independent)'!I27) -> 327299.06 | E7: =weight_dcf -> 0.5 | F7: =C7*E7 -> 150243.9 | G7: Low = Per-Mgmt vs Indep min; High = max; Mid = average
A8: Comps — EV/Sales NTM | B8: =Comps!F7 -> 445875 | C8: =Comps!G7 -> 485750 | D8: =Comps!H7 -> 547375 | G8: Reference; weighted via combined Comps row below
A9: Comps — EV/EBITDA NTM | B9: =Comps!F8 -> 133218.75 | C9: =Comps!G8 -> 144637.5 | D9: =Comps!H8 -> 159862.5 | G9: Reference
A10: Comps — P/E NTM (EV after bridge) | B10: =Comps!F9-surplus_assets-non_operating_assets+IF(ISNUMBER(net_debt_override),net_debt_override,0)+minority_interests -> 45404.75 | C10: =Comps!G9-surplus_assets-non_operating_assets+IF(ISNUMBER(net_debt_override),net_debt_override,0)+minority_interests -> 50820.5 | D10: =Comps!H9-surplus_assets-non_operating_assets+IF(ISNUMBER(net_debt_override),net_debt_override,0)+minority_interests -> 58041.5 | G10: Reference; bridged from Equity
A11: Comps — combined (mean of 3 methodologies) | B11: =MIN(C8,C9,C10) -> 50820.5 | C11: =AVERAGE(C8,C9,C10) -> 227069.33 | D11: =MAX(C8,C9,C10) -> 485750 | E11: =weight_comps -> 0.3 | F11: =C11*E11 -> 68120.8 | G11: Low/High across the 3 mids; Mid is mean
A12: Precedent transactions | B12: =IFERROR(MIN(IF(INDEX(precedents_table,0,1)=TRUE(),INDEX(precedents_table,0,7)*Projections!D50,"")),0) -> 0 | C12: =IFERROR(AVERAGEIFS(INDEX(precedents_table,0,7),INDEX(precedents_table,0,1),TRUE())*Projections!D50,0) -> 243600 | D12: =IFERROR(MAX(IF(INDEX(precedents_table,0,1)=TRUE(),INDEX(precedents_table,0,7)*Projections!D50,"")),0) -> 0 | E12: =weight_precedent -> 0.2 | F12: =C12*E12 -> 48720 | G12: Mean EV/EBITDA × Y1 EBITDA across included precedents
A14: Concluded valuation (DCF primary)
A15: Total weight applied | E15: =E7+E11+E12 -> 1
A16: Concluded EV (DCF primary) | F16: =IFERROR((F7+F11+F12)/E15,0) -> 267084.7
A17: Selected valuation (manual override)
A18: Selected low | B18: =selected_low -> 0
A19: Selected mid | C19: =selected_mid -> 0
A20: Selected high | D20: =selected_high -> 0
A22: Cross-checks vs DCF enterprise value (±10% band)
A23: Cross-check | B23: Implied EV | C23: Variance vs DCF | D23: Assessment
A24: Market approach (Comps combined) | B24: =C11 -> 227069.33 | C24: =IF(OR(C11=0,DCF!I27=0),"n/a",C11/DCF!I27-1) -> -0.30623286 | D24: =IF(OR(C11=0,DCF!I27=0),"Not available",IF(ABS(C11/DCF!I27-1)<=0.1,"Within reasonable range","Outside cross-check range")) -> Outside cross-check range
A25: Precedent transactions | B25: =C12 -> 243600 | C25: =IF(OR(C12=0,DCF!I27=0),"n/a",C12/DCF!I27-1) -> -0.25572656 | D25: =IF(OR(C12=0,DCF!I27=0),"Not available",IF(ABS(C12/DCF!I27-1)<=0.1,"Within reasonable range","Outside cross-check range")) -> Outside cross-check range
A26: Overall cross-check verdict | D26: =IF(AND(D24="Not available",D25="Not available"),"Not available",IF(OR(D24="Outside cross-check range",D25="Outside cross-check range"),"Outside cross-check range","Within reasonable range")) -> Outside cross-check range

Sheet WACC
A1: WACC — discount rate build-up
A2: Two scenarios. Inputs (Rf, ERP, country premium) shared; beta / D/E / size / specific / Kd are scenario-specific. Calculated outputs (levered beta, Ke, after-tax Kd, WACC) cycle back to the Inputs sheet.
A4: Component | C4: Type | E4: Per Management | F4: Independent
A6: Cost of Equity (Ke)
A7: Effective tax rate | C7: % | E7: =IF(ISNUMBER(tax_effective_rate),tax_effective_rate,tax_rate_high) -> 0.17 | F7: =IF(ISNUMBER(tax_effective_rate),tax_effective_rate,tax_rate_high) -> 0.17
A8: Unlevered beta | C8: x | E8: =unlevered_beta_per_mgmt -> 1.05 | F8: =unlevered_beta_indep -> 1.15
A9: D/E ratio | C9: % | E9: =target_debt_to_equity_per_mgmt -> 0.2 | F9: =target_debt_to_equity_indep -> 0.25
A10: Levered beta (calc) | C10: x | E10: =E8*(1+(1-E7)*E9) -> 1.2243 | F10: =F8*(1+(1-F7)*F9) -> 1.388625
A11: Risk-free rate | C11: % | E11: =risk_free_rate -> 0.045 | F11: =risk_free_rate -> 0.045
A12: Equity risk premium (ERP) | C12: % | E12: =equity_risk_premium -> 0.055 | F12: =equity_risk_premium -> 0.055
A13: Country risk premium | C13: % | E13: =country_risk_premium -> 0.005 | F13: =country_risk_premium -> 0.005
A14: Size premium | C14: % | E14: =size_premium_per_mgmt -> 0.02 | F14: =size_premium_indep -> 0.025
A15: Specific risk premium | C15: % | E15: =specific_risk_premium_per_mgmt -> 0.02 | F15: =specific_risk_premium_indep -> 0.03
A16: Cost of Equity (calc) | C16: % | E16: =E11+E10*E12+E13+E14+E15 -> 0.1573365 | F16: =F11+F10*F12+F13+F14+F15 -> 0.18137438
A18: Cost of Debt (Kd)
A19: Pre-tax cost of debt | C19: % | E19: =pretax_cost_of_debt_per_mgmt -> 0.06 | F19: =pretax_cost_of_debt_indep -> 0.065
A20: After-tax cost of debt (calc) | C20: % | E20: =E19*(1-E7) -> 0.0498 | F20: =F19*(1-F7) -> 0.05395
A22: Capital structure & WACC
A23: D/V (debt weight) | C23: % | E23: =target_debt_weight_per_mgmt -> 0.17 | F23: =target_debt_weight_indep -> 0.2
A24: E/V (equity weight) | C24: % | E24: =target_equity_weight_per_mgmt -> 0.83 | F24: =target_equity_weight_indep -> 0.8
A25: WACC (calc) | C25: % | E25: =E16*E24+E20*E23 -> 0.13905529 | F25: =F16*F24+F20*F23 -> 0.1558895

Sheet CoCo Selection
A1: CoCo Selection — comparable companies
A2: Mirror view of the comparable companies table on the Inputs sheet. Edit values on Inputs; this sheet refreshes automatically.
A4: Tier | B4: Include | C4: Company | D4: Ticker | E4: Business description | F4: Country | G4: Accounting standard | H4: Market cap (USD mm) | I4: D/E ratio | J4: Raw levered beta | K4: Effective tax rate | L4: Unlevered beta (calculated)
A6: =Inputs!A127 -> selected_mid | B6: =Inputs!B127 -> Selected valuation mid | C6: =Inputs!C127 -> currency | D6: =Inputs!D127 -> 0 | E6: =Inputs!E127 -> 0 | F6: =Inputs!F127 -> 0 | G6: =Inputs!G127 -> 0 | H6: =Inputs!H127 -> 0 | ... K6: =Inputs!K127 -> 0 | L6: =IFERROR(Inputs!J127/(1+(1-Inputs!K127)*Inputs!I127),"") -> 0
A7: =Inputs!A128 -> selected_high | B7: =Inputs!B128 -> Selected valuation high | C7: =Inputs!C128 -> currency | D7: =Inputs!D128 -> 0 | E7: =Inputs!E128 -> 0 | F7: =Inputs!F128 -> 0 | G7: =Inputs!G128 -> 0 | H7: =Inputs!H128 -> 0 | ... K7: =Inputs!K128 -> 0 | L7: =IFERROR(Inputs!J128/(1+(1-Inputs!K128)*Inputs!I128),"") -> 0
A8: =Inputs!A129 -> 0 | B8: =Inputs!B129 -> 0 | C8: =Inputs!C129 -> 0 | D8: =Inputs!D129 -> 0 | E8: =Inputs!E129 -> 0 | F8: =Inputs!F129 -> 0 | G8: =Inputs!G129 -> 0 | H8: =Inputs!H129 -> 0 | ... K8: =Inputs!K129 -> 0 | L8: =IFERROR(Inputs!J129/(1+(1-Inputs!K129)*Inputs!I129),"") -> 0
A9: =Inputs!A130 -> Section L — Sensitivity ranges (Extended) | B9: =Inputs!B130 -> 0 | C9: =Inputs!C130 -> 0 | D9: =Inputs!D130 -> 0 | E9: =Inputs!E130 -> 0 | F9: =Inputs!F130 -> 0 | G9: =Inputs!G130 -> 0 | H9: =Inputs!H130 -> 0 | ... K9: =Inputs!K130 -> 0 | L9: =IFERROR(Inputs!J130/(1+(1-Inputs!K130)*Inputs!I130),"") -> 0
A10: =Inputs!A131 -> sens_wacc_step | B10: =Inputs!B131 -> WACC sensitivity step | C10: =Inputs!C131 -> percentage | D10: =Inputs!D131 -> 0.005 | E10: =Inputs!E131 -> 0 | F10: =Inputs!F131 -> 0 | G10: =Inputs!G131 -> 0 | H10: =Inputs!H131 -> 0 | ... K10: =Inputs!K131 -> 0 | L10: =IFERROR(Inputs!J131/(1+(1-Inputs!K131)*Inputs!I131),"") -> 0
A11: =Inputs!A132 -> sens_wacc_count | B11: =Inputs!B132 -> WACC steps each side of base | C11: =Inputs!C132 -> number | D11: =Inputs!D132 -> 5 | E11: =Inputs!E132 -> 0 | F11: =Inputs!F132 -> 0 | G11: =Inputs!G132 -> 0 | H11: =Inputs!H132 -> 0 | ... K11: =Inputs!K132 -> 0 | L11: =IFERROR(Inputs!J132/(1+(1-Inputs!K132)*Inputs!I132),"") -> 0
A12: =Inputs!A133 -> sens_terminal_g_step | B12: =Inputs!B133 -> Terminal g sensitivity step | C12: =Inputs!C133 -> percentage | D12: =Inputs!D133 -> 0.005 | E12: =Inputs!E133 -> 0 | F12: =Inputs!F133 -> 0 | G12: =Inputs!G133 -> 0 | H12: =Inputs!H133 -> 0 | ... K12: =Inputs!K133 -> 0 | L12: =IFERROR(Inputs!J133/(1+(1-Inputs!K133)*Inputs!I133),"") -> 0
A13: =Inputs!A134 -> sens_terminal_g_count | B13: =Inputs!B134 -> Terminal g steps each side | C13: =Inputs!C134 -> number | D13: =Inputs!D134 -> 5 | E13: =Inputs!E134 -> 0 | F13: =Inputs!F134 -> 0 | G13: =Inputs!G134 -> 0 | H13: =Inputs!H134 -> 0 | ... K13: =Inputs!K134 -> 0 | L13: =IFERROR(Inputs!J134/(1+(1-Inputs!K134)*Inputs!I134),"") -> 0
A14: =Inputs!A135 -> sens_revenue_g_step | B14: =Inputs!B135 -> Revenue growth sens step | C14: =Inputs!C135 -> percentage | D14: =Inputs!D135 -> 0.02 | E14: =Inputs!E135 -> 0 | F14: =Inputs!F135 -> 0 | G14: =Inputs!G135 -> 0 | H14: =Inputs!H135 -> 0 | ... K14: =Inputs!K135 -> 0 | L14: =IFERROR(Inputs!J135/(1+(1-Inputs!K135)*Inputs!I135),"") -> 0
A15: =Inputs!A136 -> sens_ebitda_margin_step | B15: =Inputs!B136 -> EBITDA margin sens step | C15: =Inputs!C136 -> percentage | D15: =Inputs!D136 -> 0.02 | E15: =Inputs!E136 -> 0 | F15: =Inputs!F136 -> 0 | G15: =Inputs!G136 -> 0 | H15: =Inputs!H136 -> 0 | ... K15: =Inputs!K136 -> 0 | L15: =IFERROR(Inputs!J136/(1+(1-Inputs!K136)*Inputs!I136),"") -> 0
A16: =Inputs!A137 -> 0 | B16: =Inputs!B137 -> 0 | C16: =Inputs!C137 -> 0 | D16: =Inputs!D137 -> 0 | E16: =Inputs!E137 -> 0 | F16: =Inputs!F137 -> 0 | G16: =Inputs!G137 -> 0 | H16: =Inputs!H137 -> 0 | ... K16: =Inputs!K137 -> 0 | L16: =IFERROR(Inputs!J137/(1+(1-Inputs!K137)*Inputs!I137),"") -> 0
A17: =Inputs!A138 -> Section G — Comparable companies table (Core) | B17: =Inputs!B138 -> 0 | C17: =Inputs!C138 -> 0 | D17: =Inputs!D138 -> 0 | E17: =Inputs!E138 -> 0 | F17: =Inputs!F138 -> 0 | G17: =Inputs!G138 -> 0 | H17: =Inputs!H138 -> 0 | ... K17: =Inputs!K138 -> 0 | L17: =IFERROR(Inputs!J138/(1+(1-Inputs!K138)*Inputs!I138),"") -> 0
... A35: =Inputs!A156 -> 0 | B35: =Inputs!B156 -> 0 | C35: =Inputs!C156 -> 0 | D35: =Inputs!D156 -> 0 | E35: =Inputs!E156 -> 0 | F35: =Inputs!F156 -> 0 | G35: =Inputs!G156 -> 0 | H35: =Inputs!H156 -> 0 | ... K35: =Inputs!K156 -> 0 | L35: =IFERROR(Inputs!J156/(1+(1-Inputs!K156)*Inputs!I156),"") -> 0

Sheet CoCo Multiples
A1: CoCo Multiples — trading multiples per comparable
A2: Per-CoCo metric values (Capital IQ / Bloomberg). Cols A-D mirror Inputs. Cols E onward are manual data entry. Summary stats compute below.
A4: Tier | B4: Include | C4: Company | D4: Ticker | E4: EV/Sales LTM | F4: EV/Sales NTM | G4: EV/EBITDA LTM | H4: EV/EBITDA NTM | I4: P/E LTM | J4: P/E NTM
A6: =Inputs!A127 -> selected_mid | B6: =Inputs!B127 -> Selected valuation mid | C6: =Inputs!C127 -> currency | D6: =Inputs!D127 -> 0 | E6: 4.2 | F6: 3.5 | G6: 18 | H6: 15 | I6: 26 | J6: 22
A7: =Inputs!A128 -> selected_high | B7: =Inputs!B128 -> Selected valuation high | C7: =Inputs!C128 -> currency | D7: =Inputs!D128 -> 0 | E7: 3.8 | F7: 3.2 | G7: 16.5 | H7: 13.5 | I7: 24 | J7: 20
A8: =Inputs!A129 -> 0 | B8: =Inputs!B129 -> 0 | C8: =Inputs!C129 -> 0 | D8: =Inputs!D129 -> 0 | E8: 5.5 | F8: 4.6 | G8: 22 | H8: 18 | I8: 32 | J8: 26
A9: =Inputs!A130 -> Section L — Sensitivity ranges (Extended) | B9: =Inputs!B130 -> 0 | C9: =Inputs!C130 -> 0 | D9: =Inputs!D130 -> 0 | E9: 3.1 | F9: 2.7 | G9: 14 | H9: 12 | I9: 21 | J9: 18
A10: =Inputs!A131 -> sens_wacc_step | B10: =Inputs!B131 -> WACC sensitivity step | C10: =Inputs!C131 -> percentage | D10: =Inputs!D131 -> 0.005
A11: =Inputs!A132 -> sens_wacc_count | B11: =Inputs!B132 -> WACC steps each side of base | C11: =Inputs!C132 -> number | D11: =Inputs!D132 -> 5
A12: =Inputs!A133 -> sens_terminal_g_step | B12: =Inputs!B133 -> Terminal g sensitivity step | C12: =Inputs!C133 -> percentage | D12: =Inputs!D133 -> 0.005
A13: =Inputs!A134 -> sens_terminal_g_count | B13: =Inputs!B134 -> Terminal g steps each side | C13: =Inputs!C134 -> number | D13: =Inputs!D134 -> 5
A14: =Inputs!A135 -> sens_revenue_g_step | B14: =Inputs!B135 -> Revenue growth sens step | C14: =Inputs!C135 -> percentage | D14: =Inputs!D135 -> 0.02
A15: =Inputs!A136 -> sens_ebitda_margin_step | B15: =Inputs!B136 -> EBITDA margin sens step | C15: =Inputs!C136 -> percentage | D15: =Inputs!D136 -> 0.02
A16: =Inputs!A137 -> 0 | B16: =Inputs!B137 -> 0 | C16: =Inputs!C137 -> 0 | D16: =Inputs!D137 -> 0
A17: =Inputs!A138 -> Section G — Comparable companies table (Core) | B17: =Inputs!B138 -> 0 | C17: =Inputs!C138 -> 0 | D17: =Inputs!D138 -> 0
A18: =Inputs!A139 -> Tier | B18: =Inputs!B139 -> Include | C18: =Inputs!C139 -> Company | D18: =Inputs!D139 -> Ticker
A19: =Inputs!A140 -> 1 | B19: =Inputs!B140 -> TRUE | C19: =Inputs!C140 -> Atlassian | D19: =Inputs!D140 -> NASDAQ:TEAM
A20: =Inputs!A141 -> 1 | B20: =Inputs!B141 -> TRUE | C20: =Inputs!C141 -> Datadog | D20: =Inputs!D141 -> NASDAQ:DDOG
A21: =Inputs!A142 -> 2 | B21: =Inputs!B142 -> TRUE | C21: =Inputs!C142 -> MongoDB | D21: =Inputs!D142 -> NASDAQ:MDB
... A35: =Inputs!A156 -> 0 | B35: =Inputs!B156 -> 0 | C35: =Inputs!C156 -> 0 | D35: =Inputs!D156 -> 0
D37: Maximum | E37: =IFERROR(MAX(E6:E35),"n/a") -> 5.5 | F37: =IFERROR(MAX(F6:F35),"n/a") -> 4.6 | G37: =IFERROR(MAX(G6:G35),"n/a") -> 22 | H37: =IFERROR(MAX(H6:H35),"n/a") -> 18 | I37: =IFERROR(MAX(I6:I35),"n/a") -> 32 | J37: =IFERROR(MAX(J6:J35),"n/a") -> 26
D38: Q3 (75%) | E38: =IFERROR(QUARTILE(E6:E35,3),"n/a") -> 4.525 | F38: =IFERROR(QUARTILE(F6:F35,3),"n/a") -> 3.775 | G38: =IFERROR(QUARTILE(G6:G35,3),"n/a") -> 19 | H38: =IFERROR(QUARTILE(H6:H35,3),"n/a") -> 15.75 | I38: =IFERROR(QUARTILE(I6:I35,3),"n/a") -> 27.5 | J38: =IFERROR(QUARTILE(J6:J35,3),"n/a") -> 23
D39: Median | E39: =IFERROR(MEDIAN(E6:E35),"n/a") -> 4 | F39: =IFERROR(MEDIAN(F6:F35),"n/a") -> 3.35 | G39: =IFERROR(MEDIAN(G6:G35),"n/a") -> 17.25 | H39: =IFERROR(MEDIAN(H6:H35),"n/a") -> 14.25 | I39: =IFERROR(MEDIAN(I6:I35),"n/a") -> 25 | J39: =IFERROR(MEDIAN(J6:J35),"n/a") -> 21
D40: Mean | E40: =IFERROR(AVERAGE(E6:E35),"n/a") -> 4.15 | F40: =IFERROR(AVERAGE(F6:F35),"n/a") -> 3.5 | G40: =IFERROR(AVERAGE(G6:G35),"n/a") -> 17.625 | H40: =IFERROR(AVERAGE(H6:H35),"n/a") -> 14.625 | I40: =IFERROR(AVERAGE(I6:I35),"n/a") -> 25.75 | J40: =IFERROR(AVERAGE(J6:J35),"n/a") -> 21.5
D41: Q1 (25%) | E41: =IFERROR(QUARTILE(E6:E35,1),"n/a") -> 3.625 | F41: =IFERROR(QUARTILE(F6:F35,1),"n/a") -> 3.075 | G41: =IFERROR(QUARTILE(G6:G35,1),"n/a") -> 15.875 | H41: =IFERROR(QUARTILE(H6:H35,1),"n/a") -> 13.125 | I41: =IFERROR(QUARTILE(I6:I35,1),"n/a") -> 23.25 | J41: =IFERROR(QUARTILE(J6:J35,1),"n/a") -> 19.5
D42: Minimum | E42: =IFERROR(MIN(E6:E35),"n/a") -> 3.1 | F42: =IFERROR(MIN(F6:F35),"n/a") -> 2.7 | G42: =IFERROR(MIN(G6:G35),"n/a") -> 14 | H42: =IFERROR(MIN(H6:H35),"n/a") -> 12 | I42: =IFERROR(MIN(I6:I35),"n/a") -> 21 | J42: =IFERROR(MIN(J6:J35),"n/a") -> 18
D44: Tier-filtered (include=TRUE)
D45: Tier 1 mean | E45: =IFERROR(AVERAGEIFS(E6:E35,$A$6:$A$35,1,$B$6:$B$35,TRUE()),"n/a") -> n/a | F45: =IFERROR(AVERAGEIFS(F6:F35,$A$6:$A$35,1,$B$6:$B$35,TRUE()),"n/a") -> n/a | G45: =IFERROR(AVERAGEIFS(G6:G35,$A$6:$A$35,1,$B$6:$B$35,TRUE()),"n/a") -> n/a | H45: =IFERROR(AVERAGEIFS(H6:H35,$A$6:$A$35,1,$B$6:$B$35,TRUE()),"n/a") -> n/a | I45: =IFERROR(AVERAGEIFS(I6:I35,$A$6:$A$35,1,$B$6:$B$35,TRUE()),"n/a") -> n/a | J45: =IFERROR(AVERAGEIFS(J6:J35,$A$6:$A$35,1,$B$6:$B$35,TRUE()),"n/a") -> n/a
D46: Tier 2 mean | E46: =IFERROR(AVERAGEIFS(E6:E35,$A$6:$A$35,2,$B$6:$B$35,TRUE()),"n/a") -> n/a | F46: =IFERROR(AVERAGEIFS(F6:F35,$A$6:$A$35,2,$B$6:$B$35,TRUE()),"n/a") -> n/a | G46: =IFERROR(AVERAGEIFS(G6:G35,$A$6:$A$35,2,$B$6:$B$35,TRUE()),"n/a") -> n/a | H46: =IFERROR(AVERAGEIFS(H6:H35,$A$6:$A$35,2,$B$6:$B$35,TRUE()),"n/a") -> n/a | I46: =IFERROR(AVERAGEIFS(I6:I35,$A$6:$A$35,2,$B$6:$B$35,TRUE()),"n/a") -> n/a | J46: =IFERROR(AVERAGEIFS(J6:J35,$A$6:$A$35,2,$B$6:$B$35,TRUE()),"n/a") -> n/a
D47: Tier 3 mean | E47: =IFERROR(AVERAGEIFS(E6:E35,$A$6:$A$35,3,$B$6:$B$35,TRUE()),"n/a") -> n/a | F47: =IFERROR(AVERAGEIFS(F6:F35,$A$6:$A$35,3,$B$6:$B$35,TRUE()),"n/a") -> n/a | G47: =IFERROR(AVERAGEIFS(G6:G35,$A$6:$A$35,3,$B$6:$B$35,TRUE()),"n/a") -> n/a | H47: =IFERROR(AVERAGEIFS(H6:H35,$A$6:$A$35,3,$B$6:$B$35,TRUE()),"n/a") -> n/a | I47: =IFERROR(AVERAGEIFS(I6:I35,$A$6:$A$35,3,$B$6:$B$35,TRUE()),"n/a") -> n/a | J47: =IFERROR(AVERAGEIFS(J6:J35,$A$6:$A$35,3,$B$6:$B$35,TRUE()),"n/a") -> n/a

Sheet CoCo Margins
A1: CoCo Margins — profitability per comparable
A2: Per-CoCo metric values (Capital IQ / Bloomberg). Cols A-D mirror Inputs. Cols E onward are manual data entry. Summary stats compute below.
A4: Tier | B4: Include | C4: Company | D4: Ticker | E4: Gross margin | F4: EBIT margin | G4: Net margin
A6: =Inputs!A127 -> selected_mid | B6: =Inputs!B127 -> Selected valuation mid | C6: =Inputs!C127 -> currency | D6: =Inputs!D127 -> 0 | E6: 0.55 | F6: 0.18 | G6: 0.12
A7: =Inputs!A128 -> selected_high | B7: =Inputs!B128 -> Selected valuation high | C7: =Inputs!C128 -> currency | D7: =Inputs!D128 -> 0 | E7: 0.52 | F7: 0.16 | G7: 0.1
A8: =Inputs!A129 -> 0 | B8: =Inputs!B129 -> 0 | C8: =Inputs!C129 -> 0 | D8: =Inputs!D129 -> 0 | E8: 0.62 | F8: 0.22 | G8: 0.16
A9: =Inputs!A130 -> Section L — Sensitivity ranges (Extended) | B9: =Inputs!B130 -> 0 | C9: =Inputs!C130 -> 0 | D9: =Inputs!D130 -> 0 | E9: 0.48 | F9: 0.14 | G9: 0.09
A10: =Inputs!A131 -> sens_wacc_step | B10: =Inputs!B131 -> WACC sensitivity step | C10: =Inputs!C131 -> percentage | D10: =Inputs!D131 -> 0.005
A11: =Inputs!A132 -> sens_wacc_count | B11: =Inputs!B132 -> WACC steps each side of base | C11: =Inputs!C132 -> number | D11: =Inputs!D132 -> 5
A12: =Inputs!A133 -> sens_terminal_g_step | B12: =Inputs!B133 -> Terminal g sensitivity step | C12: =Inputs!C133 -> percentage | D12: =Inputs!D133 -> 0.005
A13: =Inputs!A134 -> sens_terminal_g_count | B13: =Inputs!B134 -> Terminal g steps each side | C13: =Inputs!C134 -> number | D13: =Inputs!D134 -> 5
A14: =Inputs!A135 -> sens_revenue_g_step | B14: =Inputs!B135 -> Revenue growth sens step | C14: =Inputs!C135 -> percentage | D14: =Inputs!D135 -> 0.02
A15: =Inputs!A136 -> sens_ebitda_margin_step | B15: =Inputs!B136 -> EBITDA margin sens step | C15: =Inputs!C136 -> percentage | D15: =Inputs!D136 -> 0.02
A16: =Inputs!A137 -> 0 | B16: =Inputs!B137 -> 0 | C16: =Inputs!C137 -> 0 | D16: =Inputs!D137 -> 0
A17: =Inputs!A138 -> Section G — Comparable companies table (Core) | B17: =Inputs!B138 -> 0 | C17: =Inputs!C138 -> 0 | D17: =Inputs!D138 -> 0
A18: =Inputs!A139 -> Tier | B18: =Inputs!B139 -> Include | C18: =Inputs!C139 -> Company | D18: =Inputs!D139 -> Ticker
A19: =Inputs!A140 -> 1 | B19: =Inputs!B140 -> TRUE | C19: =Inputs!C140 -> Atlassian | D19: =Inputs!D140 -> NASDAQ:TEAM
A20: =Inputs!A141 -> 1 | B20: =Inputs!B141 -> TRUE | C20: =Inputs!C141 -> Datadog | D20: =Inputs!D141 -> NASDAQ:DDOG
A21: =Inputs!A142 -> 2 | B21: =Inputs!B142 -> TRUE | C21: =Inputs!C142 -> MongoDB | D21: =Inputs!D142 -> NASDAQ:MDB
... A35: =Inputs!A156 -> 0 | B35: =Inputs!B156 -> 0 | C35: =Inputs!C156 -> 0 | D35: =Inputs!D156 -> 0
D37: Maximum | E37: =IFERROR(MAX(E6:E35),"n/a") -> 0.62 | F37: =IFERROR(MAX(F6:F35),"n/a") -> 0.22 | G37: =IFERROR(MAX(G6:G35),"n/a") -> 0.16
D38: Q3 (75%) | E38: =IFERROR(QUARTILE(E6:E35,3),"n/a") -> 0.5675 | F38: =IFERROR(QUARTILE(F6:F35,3),"n/a") -> 0.19 | G38: =IFERROR(QUARTILE(G6:G35,3),"n/a") -> 0.13
D39: Median | E39: =IFERROR(MEDIAN(E6:E35),"n/a") -> 0.535 | F39: =IFERROR(MEDIAN(F6:F35),"n/a") -> 0.17 | G39: =IFERROR(MEDIAN(G6:G35),"n/a") -> 0.11
D40: Mean | E40: =IFERROR(AVERAGE(E6:E35),"n/a") -> 0.5425 | F40: =IFERROR(AVERAGE(F6:F35),"n/a") -> 0.175 | G40: =IFERROR(AVERAGE(G6:G35),"n/a") -> 0.1175
D41: Q1 (25%) | E41: =IFERROR(QUARTILE(E6:E35,1),"n/a") -> 0.51 | F41: =IFERROR(QUARTILE(F6:F35,1),"n/a") -> 0.155 | G41: =IFERROR(QUARTILE(G6:G35,1),"n/a") -> 0.0975
D42: Minimum | E42: =IFERROR(MIN(E6:E35),"n/a") -> 0.48 | F42: =IFERROR(MIN(F6:F35),"n/a") -> 0.14 | G42: =IFERROR(MIN(G6:G35),"n/a") -> 0.09
D44: Tier-filtered (include=TRUE)
D45: Tier 1 mean | E45: =IFERROR(AVERAGEIFS(E6:E35,$A$6:$A$35,1,$B$6:$B$35,TRUE()),"n/a") -> n/a | F45: =IFERROR(AVERAGEIFS(F6:F35,$A$6:$A$35,1,$B$6:$B$35,TRUE()),"n/a") -> n/a | G45: =IFERROR(AVERAGEIFS(G6:G35,$A$6:$A$35,1,$B$6:$B$35,TRUE()),"n/a") -> n/a
D46: Tier 2 mean | E46: =IFERROR(AVERAGEIFS(E6:E35,$A$6:$A$35,2,$B$6:$B$35,TRUE()),"n/a") -> n/a | F46: =IFERROR(AVERAGEIFS(F6:F35,$A$6:$A$35,2,$B$6:$B$35,TRUE()),"n/a") -> n/a | G46: =IFERROR(AVERAGEIFS(G6:G35,$A$6:$A$35,2,$B$6:$B$35,TRUE()),"n/a") -> n/a
D47: Tier 3 mean | E47: =IFERROR(AVERAGEIFS(E6:E35,$A$6:$A$35,3,$B$6:$B$35,TRUE()),"n/a") -> n/a | F47: =IFERROR(AVERAGEIFS(F6:F35,$A$6:$A$35,3,$B$6:$B$35,TRUE()),"n/a") -> n/a | G47: =IFERROR(AVERAGEIFS(G6:G35,$A$6:$A$35,3,$B$6:$B$35,TRUE()),"n/a") -> n/a

Sheet CoCo Ratios
A1: CoCo Ratios — financial ratios per comparable
A2: Per-CoCo metric values (Capital IQ / Bloomberg). Cols A-D mirror Inputs. Cols E onward are manual data entry. Summary stats compute below.
A4: Tier | B4: Include | C4: Company | D4: Ticker | E4: ROE | F4: ROA | G4: D/E | H4: Current ratio
A6: =Inputs!A127 -> selected_mid | B6: =Inputs!B127 -> Selected valuation mid | C6: =Inputs!C127 -> currency | D6: =Inputs!D127 -> 0 | E6: 0.18 | F6: 0.08 | G6: 0.2 | H6: 2.1
A7: =Inputs!A128 -> selected_high | B7: =Inputs!B128 -> Selected valuation high | C7: =Inputs!C128 -> currency | D7: =Inputs!D128 -> 0 | E7: 0.16 | F7: 0.07 | G7: 0.25 | H7: 1.9
A8: =Inputs!A129 -> 0 | B8: =Inputs!B129 -> 0 | C8: =Inputs!C129 -> 0 | D8: =Inputs!D129 -> 0 | E8: 0.22 | F8: 0.1 | G8: 0.15 | H8: 2.5
A9: =Inputs!A130 -> Section L — Sensitivity ranges (Extended) | B9: =Inputs!B130 -> 0 | C9: =Inputs!C130 -> 0 | D9: =Inputs!D130 -> 0 | E9: 0.14 | F9: 0.06 | G9: 0.3 | H9: 1.7
A10: =Inputs!A131 -> sens_wacc_step | B10: =Inputs!B131 -> WACC sensitivity step | C10: =Inputs!C131 -> percentage | D10: =Inputs!D131 -> 0.005
A11: =Inputs!A132 -> sens_wacc_count | B11: =Inputs!B132 -> WACC steps each side of base | C11: =Inputs!C132 -> number | D11: =Inputs!D132 -> 5
A12: =Inputs!A133 -> sens_terminal_g_step | B12: =Inputs!B133 -> Terminal g sensitivity step | C12: =Inputs!C133 -> percentage | D12: =Inputs!D133 -> 0.005
A13: =Inputs!A134 -> sens_terminal_g_count | B13: =Inputs!B134 -> Terminal g steps each side | C13: =Inputs!C134 -> number | D13: =Inputs!D134 -> 5
A14: =Inputs!A135 -> sens_revenue_g_step | B14: =Inputs!B135 -> Revenue growth sens step | C14: =Inputs!C135 -> percentage | D14: =Inputs!D135 -> 0.02
A15: =Inputs!A136 -> sens_ebitda_margin_step | B15: =Inputs!B136 -> EBITDA margin sens step | C15: =Inputs!C136 -> percentage | D15: =Inputs!D136 -> 0.02
A16: =Inputs!A137 -> 0 | B16: =Inputs!B137 -> 0 | C16: =Inputs!C137 -> 0 | D16: =Inputs!D137 -> 0
A17: =Inputs!A138 -> Section G — Comparable companies table (Core) | B17: =Inputs!B138 -> 0 | C17: =Inputs!C138 -> 0 | D17: =Inputs!D138 -> 0
A18: =Inputs!A139 -> Tier | B18: =Inputs!B139 -> Include | C18: =Inputs!C139 -> Company | D18: =Inputs!D139 -> Ticker
A19: =Inputs!A140 -> 1 | B19: =Inputs!B140 -> TRUE | C19: =Inputs!C140 -> Atlassian | D19: =Inputs!D140 -> NASDAQ:TEAM
A20: =Inputs!A141 -> 1 | B20: =Inputs!B141 -> TRUE | C20: =Inputs!C141 -> Datadog | D20: =Inputs!D141 -> NASDAQ:DDOG
A21: =Inputs!A142 -> 2 | B21: =Inputs!B142 -> TRUE | C21: =Inputs!C142 -> MongoDB | D21: =Inputs!D142 -> NASDAQ:MDB
... A35: =Inputs!A156 -> 0 | B35: =Inputs!B156 -> 0 | C35: =Inputs!C156 -> 0 | D35: =Inputs!D156 -> 0
D37: Maximum | E37: =IFERROR(MAX(E6:E35),"n/a") -> 0.22 | F37: =IFERROR(MAX(F6:F35),"n/a") -> 0.1 | G37: =IFERROR(MAX(G6:G35),"n/a") -> 0.3 | H37: =IFERROR(MAX(H6:H35),"n/a") -> 2.5
D38: Q3 (75%) | E38: =IFERROR(QUARTILE(E6:E35,3),"n/a") -> 0.19 | F38: =IFERROR(QUARTILE(F6:F35,3),"n/a") -> 0.085 | G38: =IFERROR(QUARTILE(G6:G35,3),"n/a") -> 0.2625 | H38: =IFERROR(QUARTILE(H6:H35,3),"n/a") -> 2.2
D39: Median | E39: =IFERROR(MEDIAN(E6:E35),"n/a") -> 0.17 | F39: =IFERROR(MEDIAN(F6:F35),"n/a") -> 0.075 | G39: =IFERROR(MEDIAN(G6:G35),"n/a") -> 0.225 | H39: =IFERROR(MEDIAN(H6:H35),"n/a") -> 2
D40: Mean | E40: =IFERROR(AVERAGE(E6:E35),"n/a") -> 0.175 | F40: =IFERROR(AVERAGE(F6:F35),"n/a") -> 0.0775 | G40: =IFERROR(AVERAGE(G6:G35),"n/a") -> 0.225 | H40: =IFERROR(AVERAGE(H6:H35),"n/a") -> 2.05
D41: Q1 (25%) | E41: =IFERROR(QUARTILE(E6:E35,1),"n/a") -> 0.155 | F41: =IFERROR(QUARTILE(F6:F35,1),"n/a") -> 0.0675 | G41: =IFERROR(QUARTILE(G6:G35,1),"n/a") -> 0.1875 | H41: =IFERROR(QUARTILE(H6:H35,1),"n/a") -> 1.85
D42: Minimum | E42: =IFERROR(MIN(E6:E35),"n/a") -> 0.14 | F42: =IFERROR(MIN(F6:F35),"n/a") -> 0.06 | G42: =IFERROR(MIN(G6:G35),"n/a") -> 0.15 | H42: =IFERROR(MIN(H6:H35),"n/a") -> 1.7
D44: Tier-filtered (include=TRUE)
D45: Tier 1 mean | E45: =IFERROR(AVERAGEIFS(E6:E35,$A$6:$A$35,1,$B$6:$B$35,TRUE()),"n/a") -> n/a | F45: =IFERROR(AVERAGEIFS(F6:F35,$A$6:$A$35,1,$B$6:$B$35,TRUE()),"n/a") -> n/a | G45: =IFERROR(AVERAGEIFS(G6:G35,$A$6:$A$35,1,$B$6:$B$35,TRUE()),"n/a") -> n/a | H45: =IFERROR(AVERAGEIFS(H6:H35,$A$6:$A$35,1,$B$6:$B$35,TRUE()),"n/a") -> n/a
D46: Tier 2 mean | E46: =IFERROR(AVERAGEIFS(E6:E35,$A$6:$A$35,2,$B$6:$B$35,TRUE()),"n/a") -> n/a | F46: =IFERROR(AVERAGEIFS(F6:F35,$A$6:$A$35,2,$B$6:$B$35,TRUE()),"n/a") -> n/a | G46: =IFERROR(AVERAGEIFS(G6:G35,$A$6:$A$35,2,$B$6:$B$35,TRUE()),"n/a") -> n/a | H46: =IFERROR(AVERAGEIFS(H6:H35,$A$6:$A$35,2,$B$6:$B$35,TRUE()),"n/a") -> n/a
D47: Tier 3 mean | E47: =IFERROR(AVERAGEIFS(E6:E35,$A$6:$A$35,3,$B$6:$B$35,TRUE()),"n/a") -> n/a | F47: =IFERROR(AVERAGEIFS(F6:F35,$A$6:$A$35,3,$B$6:$B$35,TRUE()),"n/a") -> n/a | G47: =IFERROR(AVERAGEIFS(G6:G35,$A$6:$A$35,3,$B$6:$B$35,TRUE()),"n/a") -> n/a | H47: =IFERROR(AVERAGEIFS(H6:H35,$A$6:$A$35,3,$B$6:$B$35,TRUE()),"n/a") -> n/a

Sheet CIQ Data Timeline
A1: CIQ Data Timeline
A2: Capital IQ data import audit trail FY-4 to FY-1
A4: TODO — formulas to be added in subsequent build pass.

Sheet Country ERP
A1: Country ERP — equity risk premium reference
A2: Reference table for country risk premium (CRP) and total ERP. Approximates Damodaran's mid-2025 published figures. **Refresh annually** from pages.stern.nyu.edu/~adamodar/ before any binding valuation. Look up your jurisdiction by ISO2 in column B, take ERP from column D and CRP from column E.
A4: Country | B4: ISO2 | C4: Moody's rating | D4: ERP | E4: Country Risk Premium | F4: Corporate Tax Rate | G4: Region
A5: United States | B5: US | C5: Aaa | D5: 0.0457 | E5: 0 | F5: 0.21 | G5: North America
A6: United Kingdom | B6: GB | C6: Aa3 | D6: 0.0507 | E6: 0.005 | F6: 0.25 | G6: Western Europe
A7: Germany | B7: DE | C7: Aaa | D7: 0.0457 | E7: 0 | F7: 0.298 | G7: Western Europe
A8: France | B8: FR | C8: Aa3 | D8: 0.0507 | E8: 0.005 | F8: 0.258 | G8: Western Europe
A9: Switzerland | B9: CH | C9: Aaa | D9: 0.0457 | E9: 0 | F9: 0.144 | G9: Western Europe
A10: Netherlands | B10: NL | C10: Aaa | D10: 0.0457 | E10: 0 | F10: 0.258 | G10: Western Europe
A11: Australia | B11: AU | C11: Aaa | D11: 0.0457 | E11: 0 | F11: 0.3 | G11: Australia & NZ
A12: New Zealand | B12: NZ | C12: Aaa | D12: 0.0457 | E12: 0 | F12: 0.28 | G12: Australia & NZ
A13: Canada | B13: CA | C13: Aaa | D13: 0.0457 | E13: 0 | F13: 0.265 | G13: North America
A14: Japan | B14: JP | C14: A1 | D14: 0.0567 | E14: 0.011 | F14: 0.305 | G14: Asia
A15: South Korea | B15: KR | C15: Aa2 | D15: 0.0489 | E15: 0.0032 | F15: 0.275 | G15: Asia
A16: Taiwan | B16: TW | C16: Aa3 | D16: 0.0507 | E16: 0.005 | F16: 0.2 | G16: Asia
... A35: Israel | B35: IL | C35: A2 | D35: 0.0596 | E35: 0.0139 | F35: 0.23 | G35: Middle East
A37: Source: Aswath Damodaran (NYU Stern) country ERP methodology. Mature-market ERP baseline ≈ 4.57%; CRP is the country-specific premium added for non-AAA jurisdictions. Numbers above are 2024-2025 approximations — REFRESH from the live source before binding work.

Sheet Industry Averages
A1: Industry Averages — Damodaran US-industry reference (mid-2025)
A2: Reference table for unlevered beta, margin, capex-intensity, and EV/EBITDA NTM by industry. Approximates Damodaran's mid-2025 published US figures. **Refresh annually** from pages.stern.nyu.edu/~adamodar/ before binding work. For Asia-Pac targets, betas tend to run ~10-15% higher than the US baseline.
A4: Industry | B4: n firms | C4: Unlevered β | D4: Gross margin | E4: EBITDA margin | F4: Operating margin | G4: Capex / Revenue | H4: D&A / Revenue | I4: EV/EBITDA NTM
A5: Advertising | B5: 58 | C5: 0.97 | D5: 0.4 | E5: 0.16 | F5: 0.1 | G5: 0.018 | H5: 0.024 | I5: 14
A6: Aerospace/Defense | B6: 71 | C6: 0.92 | D6: 0.27 | E6: 0.18 | F6: 0.12 | G6: 0.03 | H6: 0.03 | I6: 16.5
A7: Auto & Truck (manufacturers) | B7: 44 | C7: 0.95 | D7: 0.18 | E7: 0.12 | F7: 0.07 | G7: 0.045 | H7: 0.04 | I7: 9.5
A8: Bank (Money Center) | B8: 17 | C8: 0.78 | D8: 0.55 | E8: 0.4 | F8: 0.35 | G8: 0.005 | H8: 0.01 | I8: 8.5
A9: Beverage (Alcoholic) | B9: 27 | C9: 0.62 | D9: 0.48 | E9: 0.27 | F9: 0.22 | G9: 0.04 | H9: 0.03 | I9: 14
A10: Beverage (Soft) | B10: 29 | C10: 0.71 | D10: 0.55 | E10: 0.28 | F10: 0.22 | G10: 0.045 | H10: 0.03 | I10: 16
A11: Biotechnology | B11: 532 | C11: 1.18 | D11: 0.6 | E11: -0.1 | F11: -0.3 | G11: 0.02 | H11: 0.03 | I11: 12
A12: Broadcasting | B12: 21 | C12: 0.95 | D12: 0.42 | E12: 0.32 | F12: 0.22 | G12: 0.02 | H12: 0.06 | I12: 8.5
A13: Building Materials | B13: 31 | C13: 1.08 | D13: 0.3 | E13: 0.18 | F13: 0.13 | G13: 0.04 | H13: 0.04 | I13: 9
A14: Business & Consumer Services | B14: 168 | C14: 1.1 | D14: 0.45 | E14: 0.18 | F14: 0.12 | G14: 0.025 | H14: 0.035 | I14: 13
A15: Cable TV | B15: 10 | C15: 0.85 | D15: 0.55 | E15: 0.36 | F15: 0.2 | G15: 0.13 | H15: 0.14 | I15: 7
A16: Chemical (Diversified) | B16: 23 | C16: 1.04 | D16: 0.22 | E16: 0.16 | F16: 0.12 | G16: 0.04 | H16: 0.03 | I16: 9.5
... A84: Utility (Water) | B84: 15 | C84: 0.6 | D84: 0.42 | E84: 0.45 | F84: 0.3 | G84: 0.18 | H84: 0.15 | I84: 14
A86: Source: Aswath Damodaran (NYU Stern) US-industry data, mid-2025 approximation. Use unlevered β as starting point; relever to target capital structure on the WACC sheet. EV/EBITDA NTM ranges are observed market trading bands — apply with judgment.

Sheet Adjustments
A1: Adjustments — EV → Equity bridge
A2: Applies surplus assets, net debt, minority interests, then DLOM and DLOC, to derive Fair Value of the client's equity interest. Both scenarios computed side by side.
A4: Item | C4: Per Management | D4: Independent | E4: Notes
A6: EV → Equity bridge
A7: Enterprise Value (from DCF) | C7: =DCF!I27 -> 327299.06 | D7: ='DCF (Independent)'!I27 -> 273676.53
A8: + Surplus assets | C8: =surplus_assets -> 25000 | D8: =surplus_assets -> 25000
A9: + Non-operating assets | C9: =non_operating_assets -> 0 | D9: =non_operating_assets -> 0
A10: − Net debt | C10: =-IF(ISNUMBER(net_debt_override),net_debt_override,0) -> 0 | D10: =-IF(ISNUMBER(net_debt_override),net_debt_override,0) -> 0
A11: − Minority interests | C11: =-minority_interests -> 0 | D11: =-minority_interests -> 0
A12: Equity value (pre-discounts) | C12: =C7+C8+C9+C10+C11 -> 352299.06 | D12: =D7+D8+D9+D10+D11 -> 298676.53
A14: Marketability & control discounts
A15: DLOM rate | C15: =dlom_pct -> 0.2 | D15: =dlom_pct -> 0.2
A16: Less: DLOM | C16: =-C12*C15 -> -70459.812 | D16: =-D12*D15 -> -59735.306
A17: Equity value after DLOM | C17: =C12+C16 -> 281839.25 | D17: =D12+D16 -> 238941.22
A18: DLOC rate | C18: =dloc_pct -> 0.15 | D18: =dloc_pct -> 0.15
A19: Less: DLOC | C19: =-C17*C18 -> -42275.887 | D19: =-D17*D18 -> -35841.184
A20: Equity value after DLOM and DLOC | C20: =C17+C19 -> 239563.36 | D20: =D17+D19 -> 203100.04
A22: Client's equity interest
A23: Equity interest held by client | C23: =equity_interest_pct -> 1 | D23: =equity_interest_pct -> 1
A24: Fair value of client's interest | C24: =C20*C23 -> 239563.36 | D24: =D20*D23 -> 203100.04

Sheet Sensitivity
A1: Sensitivity — WACC × Terminal growth rate
A2: Each cell recomputes EV = Σ FCFF_y / (1+WACC)^y + FCFF_y5 × (1+g) / (WACC−g) / (1+WACC)^5. Step sizes from sens_wacc_step / sens_terminal_g_step on Inputs. Base case is current wacc_per_mgmt × terminal_growth_rate.
A4: Sensitivity grid: rows = WACC; columns = Terminal growth rate
B6: WACC ↓ / g → | C6: =terminal_growth_rate+(-3)*sens_terminal_g_step -> 0.015 | D6: =terminal_growth_rate+(-2)*sens_terminal_g_step -> 0.02 | E6: =terminal_growth_rate+(-1)*sens_terminal_g_step -> 0.025 | F6: =terminal_growth_rate+(0)*sens_terminal_g_step -> 0.03 | G6: =terminal_growth_rate+(1)*sens_terminal_g_step -> 0.035 | H6: =terminal_growth_rate+(2)*sens_terminal_g_step -> 0.04 | I6: =terminal_growth_rate+(3)*sens_terminal_g_step -> 0.045
B7: =wacc_per_mgmt+(-3)*sens_wacc_step -> 0.12405529 | C7: =IFERROR(Projections!D71/(1+$B$7)^1+Projections!E71/(1+$B$7)^2+Projections!F71/(1+$B$7)^3+Projections!G71/(1+$B$7)^4+Projections!H71/(1+$B$7)^5+Projections!H71*(1+C$6)/($B$7-C$6)/(1+$B$7)^5,"err") -> 344752.41 | D7: =IFERROR(Projections!D71/(1+$B$7)^1+Projections!E71/(1+$B$7)^2+Projections!F71/(1+$B$7)^3+Projections!G71/(1+$B$7)^4+Projections!H71/(1+$B$7)^5+Projections!H71*(1+D$6)/($B$7-D$6)/(1+$B$7)^5,"err") -> 358952.13 | E7: =IFERROR(Projections!D71/(1+$B$7)^1+Projections!E71/(1+$B$7)^2+Projections!F71/(1+$B$7)^3+Projections!G71/(1+$B$7)^4+Projections!H71/(1+$B$7)^5+Projections!H71*(1+E$6)/($B$7-E$6)/(1+$B$7)^5,"err") -> 374585.36 | F7: =IFERROR(Projections!D71/(1+$B$7)^1+Projections!E71/(1+$B$7)^2+Projections!F71/(1+$B$7)^3+Projections!G71/(1+$B$7)^4+Projections!H71/(1+$B$7)^5+Projections!H71*(1+F$6)/($B$7-F$6)/(1+$B$7)^5,"err") -> 391880.73 | G7: =IFERROR(Projections!D71/(1+$B$7)^1+Projections!E71/(1+$B$7)^2+Projections!F71/(1+$B$7)^3+Projections!G71/(1+$B$7)^4+Projections!H71/(1+$B$7)^5+Projections!H71*(1+G$6)/($B$7-G$6)/(1+$B$7)^5,"err") -> 411118.18 | H7: =IFERROR(Projections!D71/(1+$B$7)^1+Projections!E71/(1+$B$7)^2+Projections!F71/(1+$B$7)^3+Projections!G71/(1+$B$7)^4+Projections!H71/(1+$B$7)^5+Projections!H71*(1+H$6)/($B$7-H$6)/(1+$B$7)^5,"err") -> 432644.31 | I7: =IFERROR(Projections!D71/(1+$B$7)^1+Projections!E71/(1+$B$7)^2+Projections!F71/(1+$B$7)^3+Projections!G71/(1+$B$7)^4+Projections!H71/(1+$B$7)^5+Projections!H71*(1+I$6)/($B$7-I$6)/(1+$B$7)^5,"err") -> 456893.35
B8: =wacc_per_mgmt+(-2)*sens_wacc_step -> 0.12905529 | C8: =IFERROR(Projections!D71/(1+$B$8)^1+Projections!E71/(1+$B$8)^2+Projections!F71/(1+$B$8)^3+Projections!G71/(1+$B$8)^4+Projections!H71/(1+$B$8)^5+Projections!H71*(1+C$6)/($B$8-C$6)/(1+$B$8)^5,"err") -> 326080.35 | D8: =IFERROR(Projections!D71/(1+$B$8)^1+Projections!E71/(1+$B$8)^2+Projections!F71/(1+$B$8)^3+Projections!G71/(1+$B$8)^4+Projections!H71/(1+$B$8)^5+Projections!H71*(1+D$6)/($B$8-D$6)/(1+$B$8)^5,"err") -> 338807.12 | E8: =IFERROR(Projections!D71/(1+$B$8)^1+Projections!E71/(1+$B$8)^2+Projections!F71/(1+$B$8)^3+Projections!G71/(1+$B$8)^4+Projections!H71/(1+$B$8)^5+Projections!H71*(1+E$6)/($B$8-E$6)/(1+$B$8)^5,"err") -> 352756.97 | F8: =IFERROR(Projections!D71/(1+$B$8)^1+Projections!E71/(1+$B$8)^2+Projections!F71/(1+$B$8)^3+Projections!G71/(1+$B$8)^4+Projections!H71/(1+$B$8)^5+Projections!H71*(1+F$6)/($B$8-F$6)/(1+$B$8)^5,"err") -> 368115.11 | G8: =IFERROR(Projections!D71/(1+$B$8)^1+Projections!E71/(1+$B$8)^2+Projections!F71/(1+$B$8)^3+Projections!G71/(1+$B$8)^4+Projections!H71/(1+$B$8)^5+Projections!H71*(1+G$6)/($B$8-G$6)/(1+$B$8)^5,"err") -> 385106.14 | H8: =IFERROR(Projections!D71/(1+$B$8)^1+Projections!E71/(1+$B$8)^2+Projections!F71/(1+$B$8)^3+Projections!G71/(1+$B$8)^4+Projections!H71/(1+$B$8)^5+Projections!H71*(1+H$6)/($B$8-H$6)/(1+$B$8)^5,"err") -> 404005.08 | I8: =IFERROR(Projections!D71/(1+$B$8)^1+Projections!E71/(1+$B$8)^2+Projections!F71/(1+$B$8)^3+Projections!G71/(1+$B$8)^4+Projections!H71/(1+$B$8)^5+Projections!H71*(1+I$6)/($B$8-I$6)/(1+$B$8)^5,"err") -> 425152.42
B9: =wacc_per_mgmt+(-1)*sens_wacc_step -> 0.13405529 | C9: =IFERROR(Projections!D71/(1+$B$9)^1+Projections!E71/(1+$B$9)^2+Projections!F71/(1+$B$9)^3+Projections!G71/(1+$B$9)^4+Projections!H71/(1+$B$9)^5+Projections!H71*(1+C$6)/($B$9-C$6)/(1+$B$9)^5,"err") -> 309033.09 | D9: =IFERROR(Projections!D71/(1+$B$9)^1+Projections!E71/(1+$B$9)^2+Projections!F71/(1+$B$9)^3+Projections!G71/(1+$B$9)^4+Projections!H71/(1+$B$9)^5+Projections!H71*(1+D$6)/($B$9-D$6)/(1+$B$9)^5,"err") -> 320486.65 | E9: =IFERROR(Projections!D71/(1+$B$9)^1+Projections!E71/(1+$B$9)^2+Projections!F71/(1+$B$9)^3+Projections!G71/(1+$B$9)^4+Projections!H71/(1+$B$9)^5+Projections!H71*(1+E$6)/($B$9-E$6)/(1+$B$9)^5,"err") -> 332990.45 | F9: =IFERROR(Projections!D71/(1+$B$9)^1+Projections!E71/(1+$B$9)^2+Projections!F71/(1+$B$9)^3+Projections!G71/(1+$B$9)^4+Projections!H71/(1+$B$9)^5+Projections!H71*(1+F$6)/($B$9-F$6)/(1+$B$9)^5,"err") -> 346695.91 | G9: =IFERROR(Projections!D71/(1+$B$9)^1+Projections!E71/(1+$B$9)^2+Projections!F71/(1+$B$9)^3+Projections!G71/(1+$B$9)^4+Projections!H71/(1+$B$9)^5+Projections!H71*(1+G$6)/($B$9-G$6)/(1+$B$9)^5,"err") -> 361784.98 | H9: =IFERROR(Projections!D71/(1+$B$9)^1+Projections!E71/(1+$B$9)^2+Projections!F71/(1+$B$9)^3+Projections!G71/(1+$B$9)^4+Projections!H71/(1+$B$9)^5+Projections!H71*(1+H$6)/($B$9-H$6)/(1+$B$9)^5,"err") -> 378478.33 | I9: =IFERROR(Projections!D71/(1+$B$9)^1+Projections!E71/(1+$B$9)^2+Projections!F71/(1+$B$9)^3+Projections!G71/(1+$B$9)^4+Projections!H71/(1+$B$9)^5+Projections!H71*(1+I$6)/($B$9-I$6)/(1+$B$9)^5,"err") -> 397046.17
B10: =wacc_per_mgmt+(0)*sens_wacc_step -> 0.13905529 | C10: =IFERROR(Projections!D71/(1+$B$10)^1+Projections!E71/(1+$B$10)^2+Projections!F71/(1+$B$10)^3+Projections!G71/(1+$B$10)^4+Projections!H71/(1+$B$10)^5+Projections!H71*(1+C$6)/($B$10-C$6)/(1+$B$10)^5,"err") -> 293412.98 | D10: =IFERROR(Projections!D71/(1+$B$10)^1+Projections!E71/(1+$B$10)^2+Projections!F71/(1+$B$10)^3+Projections!G71/(1+$B$10)^4+Projections!H71/(1+$B$10)^5+Projections!H71*(1+D$6)/($B$10-D$6)/(1+$B$10)^5,"err") -> 303759.59 | E10: =IFERROR(Projections!D71/(1+$B$10)^1+Projections!E71/(1+$B$10)^2+Projections!F71/(1+$B$10)^3+Projections!G71/(1+$B$10)^4+Projections!H71/(1+$B$10)^5+Projections!H71*(1+E$6)/($B$10-E$6)/(1+$B$10)^5,"err") -> 315013.36 | F10: =IFERROR(Projections!D71/(1+$B$10)^1+Projections!E71/(1+$B$10)^2+Projections!F71/(1+$B$10)^3+Projections!G71/(1+$B$10)^4+Projections!H71/(1+$B$10)^5+Projections!H71*(1+F$6)/($B$10-F$6)/(1+$B$10)^5,"err") -> 327299.06 | G10: =IFERROR(Projections!D71/(1+$B$10)^1+Projections!E71/(1+$B$10)^2+Projections!F71/(1+$B$10)^3+Projections!G71/(1+$B$10)^4+Projections!H71/(1+$B$10)^5+Projections!H71*(1+G$6)/($B$10-G$6)/(1+$B$10)^5,"err") -> 340765.45 | H10: =IFERROR(Projections!D71/(1+$B$10)^1+Projections!E71/(1+$B$10)^2+Projections!F71/(1+$B$10)^3+Projections!G71/(1+$B$10)^4+Projections!H71/(1+$B$10)^5+Projections!H71*(1+H$6)/($B$10-H$6)/(1+$B$10)^5,"err") -> 355591.32 | I10: =IFERROR(Projections!D71/(1+$B$10)^1+Projections!E71/(1+$B$10)^2+Projections!F71/(1+$B$10)^3+Projections!G71/(1+$B$10)^4+Projections!H71/(1+$B$10)^5+Projections!H71*(1+I$6)/($B$10-I$6)/(1+$B$10)^5,"err") -> 371993.49
B11: =wacc_per_mgmt+(1)*sens_wacc_step -> 0.14405529 | C11: =IFERROR(Projections!D71/(1+$B$11)^1+Projections!E71/(1+$B$11)^2+Projections!F71/(1+$B$11)^3+Projections!G71/(1+$B$11)^4+Projections!H71/(1+$B$11)^5+Projections!H71*(1+C$6)/($B$11-C$6)/(1+$B$11)^5,"err") -> 279053.03 | D11: =IFERROR(Projections!D71/(1+$B$11)^1+Projections!E71/(1+$B$11)^2+Projections!F71/(1+$B$11)^3+Projections!G71/(1+$B$11)^4+Projections!H71/(1+$B$11)^5+Projections!H71*(1+D$6)/($B$11-D$6)/(1+$B$11)^5,"err") -> 288432.15 | E11: =IFERROR(Projections!D71/(1+$B$11)^1+Projections!E71/(1+$B$11)^2+Projections!F71/(1+$B$11)^3+Projections!G71/(1+$B$11)^4+Projections!H71/(1+$B$11)^5+Projections!H71*(1+E$6)/($B$11-E$6)/(1+$B$11)^5,"err") -> 298599.07 | F11: =IFERROR(Projections!D71/(1+$B$11)^1+Projections!E71/(1+$B$11)^2+Projections!F71/(1+$B$11)^3+Projections!G71/(1+$B$11)^4+Projections!H71/(1+$B$11)^5+Projections!H71*(1+F$6)/($B$11-F$6)/(1+$B$11)^5,"err") -> 309657.39 | G11: =IFERROR(Projections!D71/(1+$B$11)^1+Projections!E71/(1+$B$11)^2+Projections!F71/(1+$B$11)^3+Projections!G71/(1+$B$11)^4+Projections!H71/(1+$B$11)^5+Projections!H71*(1+G$6)/($B$11-G$6)/(1+$B$11)^5,"err") -> 321729.72 | H11: =IFERROR(Projections!D71/(1+$B$11)^1+Projections!E71/(1+$B$11)^2+Projections!F71/(1+$B$11)^3+Projections!G71/(1+$B$11)^4+Projections!H71/(1+$B$11)^5+Projections!H71*(1+H$6)/($B$11-H$6)/(1+$B$11)^5,"err") -> 334962.23 | I11: =IFERROR(Projections!D71/(1+$B$11)^1+Projections!E71/(1+$B$11)^2+Projections!F71/(1+$B$11)^3+Projections!G71/(1+$B$11)^4+Projections!H71/(1+$B$11)^5+Projections!H71*(1+I$6)/($B$11-I$6)/(1+$B$11)^5,"err") -> 349530.61
B12: =wacc_per_mgmt+(2)*sens_wacc_step -> 0.1490553 | C12: =IFERROR(Projections!D71/(1+$B$12)^1+Projections!E71/(1+$B$12)^2+Projections!F71/(1+$B$12)^3+Projections!G71/(1+$B$12)^4+Projections!H71/(1+$B$12)^5+Projections!H71*(1+C$6)/($B$12-C$6)/(1+$B$12)^5,"err") -> 265811.18 | D12: =IFERROR(Projections!D71/(1+$B$12)^1+Projections!E71/(1+$B$12)^2+Projections!F71/(1+$B$12)^3+Projections!G71/(1+$B$12)^4+Projections!H71/(1+$B$12)^5+Projections!H71*(1+D$6)/($B$12-D$6)/(1+$B$12)^5,"err") -> 274340.56 | E12: =IFERROR(Projections!D71/(1+$B$12)^1+Projections!E71/(1+$B$12)^2+Projections!F71/(1+$B$12)^3+Projections!G71/(1+$B$12)^4+Projections!H71/(1+$B$12)^5+Projections!H71*(1+E$6)/($B$12-E$6)/(1+$B$12)^5,"err") -> 283557.5 | F12: =IFERROR(Projections!D71/(1+$B$12)^1+Projections!E71/(1+$B$12)^2+Projections!F71/(1+$B$12)^3+Projections!G71/(1+$B$12)^4+Projections!H71/(1+$B$12)^5+Projections!H71*(1+F$6)/($B$12-F$6)/(1+$B$12)^5,"err") -> 293548.61 | G12: =IFERROR(Projections!D71/(1+$B$12)^1+Projections!E71/(1+$B$12)^2+Projections!F71/(1+$B$12)^3+Projections!G71/(1+$B$12)^4+Projections!H71/(1+$B$12)^5+Projections!H71*(1+G$6)/($B$12-G$6)/(1+$B$12)^5,"err") -> 304415.7 | H12: =IFERROR(Projections!D71/(1+$B$12)^1+Projections!E71/(1+$B$12)^2+Projections!F71/(1+$B$12)^3+Projections!G71/(1+$B$12)^4+Projections!H71/(1+$B$12)^5+Projections!H71*(1+H$6)/($B$12-H$6)/(1+$B$12)^5,"err") -> 316279.27 | I12: =IFERROR(Projections!D71/(1+$B$12)^1+Projections!E71/(1+$B$12)^2+Projections!F71/(1+$B$12)^3+Projections!G71/(1+$B$12)^4+Projections!H71/(1+$B$12)^5+Projections!H71*(1+I$6)/($B$12-I$6)/(1+$B$12)^5,"err") -> 329282.96
B13: =wacc_per_mgmt+(3)*sens_wacc_step -> 0.1540553 | C13: =IFERROR(Projections!D71/(1+$B$13)^1+Projections!E71/(1+$B$13)^2+Projections!F71/(1+$B$13)^3+Projections!G71/(1+$B$13)^4+Projections!H71/(1+$B$13)^5+Projections!H71*(1+C$6)/($B$13-C$6)/(1+$B$13)^5,"err") -> 253565.83 | D13: =IFERROR(Projections!D71/(1+$B$13)^1+Projections!E71/(1+$B$13)^2+Projections!F71/(1+$B$13)^3+Projections!G71/(1+$B$13)^4+Projections!H71/(1+$B$13)^5+Projections!H71*(1+D$6)/($B$13-D$6)/(1+$B$13)^5,"err") -> 261345.54 | E13: =IFERROR(Projections!D71/(1+$B$13)^1+Projections!E71/(1+$B$13)^2+Projections!F71/(1+$B$13)^3+Projections!G71/(1+$B$13)^4+Projections!H71/(1+$B$13)^5+Projections!H71*(1+E$6)/($B$13-E$6)/(1+$B$13)^5,"err") -> 269728.07 | F13: =IFERROR(Projections!D71/(1+$B$13)^1+Projections!E71/(1+$B$13)^2+Projections!F71/(1+$B$13)^3+Projections!G71/(1+$B$13)^4+Projections!H71/(1+$B$13)^5+Projections!H71*(1+F$6)/($B$13-F$6)/(1+$B$13)^5,"err") -> 278786.31 | G13: =IFERROR(Projections!D71/(1+$B$13)^1+Projections!E71/(1+$B$13)^2+Projections!F71/(1+$B$13)^3+Projections!G71/(1+$B$13)^4+Projections!H71/(1+$B$13)^5+Projections!H71*(1+G$6)/($B$13-G$6)/(1+$B$13)^5,"err") -> 288605.39 | H13: =IFERROR(Projections!D71/(1+$B$13)^1+Projections!E71/(1+$B$13)^2+Projections!F71/(1+$B$13)^3+Projections!G71/(1+$B$13)^4+Projections!H71/(1+$B$13)^5+Projections!H71*(1+H$6)/($B$13-H$6)/(1+$B$13)^5,"err") -> 299285.38 | I13: =IFERROR(Projections!D71/(1+$B$13)^1+Projections!E71/(1+$B$13)^2+Projections!F71/(1+$B$13)^3+Projections!G71/(1+$B$13)^4+Projections!H71/(1+$B$13)^5+Projections!H71*(1+I$6)/($B$13-I$6)/(1+$B$13)^5,"err") -> 310944.68
A15: Highlighted cell = base case (current wacc_per_mgmt and terminal_growth_rate). EV in (currency × unit). Values do not include the EV→Equity bridge — apply surplus / debt / DLOM / DLOC manually for equity sensitivity.

Sheet Valuation Summary
A1: Valuation Summary
A2: Headline outputs across both scenarios. Per-share values convert from (currency × unit) to actual currency using the unit selected on Inputs.
A4: Metric | B4: Unit | C4: Per Management | D4: Independent | E4: Average
A6: Headline values
A7: Enterprise Value | B7: (currency × unit) | C7: =Adjustments!C7 -> 327299.06 | D7: =Adjustments!D7 -> 273676.53 | E7: =AVERAGE(C7:D7) -> 300487.8
A8: Equity value (pre-discounts) | B8: (currency × unit) | C8: =Adjustments!C12 -> 352299.06 | D8: =Adjustments!D12 -> 298676.53 | E8: =AVERAGE(C8:D8) -> 325487.8
A9: Equity value after DLOM | B9: (currency × unit) | C9: =Adjustments!C17 -> 281839.25 | D9: =Adjustments!D17 -> 238941.22 | E9: =AVERAGE(C9:D9) -> 260390.24
A10: Equity value after DLOM and DLOC | B10: (currency × unit) | C10: =Adjustments!C20 -> 239563.36 | D10: =Adjustments!D20 -> 203100.04 | E10: =AVERAGE(C10:D10) -> 221331.7
A11: Fair value of client's interest | B11: (currency × unit) | C11: =Adjustments!C24 -> 239563.36 | D11: =Adjustments!D24 -> 203100.04 | E11: =AVERAGE(C11:D11) -> 221331.7
A13: Per-share value
A14: Unit multiplier (to actual currency) | B14: x | C14: =IF(EXACT(unit,"'000"),1000,IF(EXACT(unit,"million"),1000000,1)) -> 1000 | D14: =IF(EXACT(unit,"'000"),1000,IF(EXACT(unit,"million"),1000000,1)) -> 1000
A15: Shares outstanding (basic) | B15: shares | C15: =shares_outstanding -> 250000000 | D15: =shares_outstanding -> 250000000
A16: Equity value per share (basic) | B16: actual currency | C16: =IFERROR(Adjustments!C20*C14/C15,0) -> 0.95825345 | D16: =IFERROR(Adjustments!D20*D14/D15,0) -> 0.81240016 | E16: =AVERAGE(C16:D16) -> 0.88532681
A17: Shares outstanding (diluted) | B17: shares | C17: =shares_outstanding_diluted -> 285000000 | D17: =shares_outstanding_diluted -> 285000000
A18: Equity value per share (diluted) | B18: actual currency | C18: =IFERROR(Adjustments!C20*C14/C17,0) -> 0.8405732 | D18: =IFERROR(Adjustments!D20*D14/D17,0) -> 0.71263172 | E18: =AVERAGE(C18:D18) -> 0.77660246
A20: Discount rate inputs (reference)
A21: WACC | B21: % | C21: =wacc_per_mgmt -> 0.13905529 | D21: =wacc_indep -> 0.1558895
A22: Terminal growth rate | B22: % | C22: =terminal_growth_rate -> 0.03 | D22: =terminal_growth_rate -> 0.03

Sheet _dropdowns
A1: report_purpose | B1: accounting_standard | C1: tax_type | D1: terminal_method | E1: currency | F1: unit | G1: coco_tier | H1: revenue_growth_method
A2: BEV review | B2: IFRS | C2: flat | D2: gordon_growth | E2: USD | F2: '000 | G2: 1 | H2: flat
A3: IPO pricing | B3: US GAAP | C3: two_tier | D3: exit_multiple | E3: HKD | F3: million | G3: 2 | H3: declining
A4: Fairness opinion | B4: IFRS 9 + IFRS 13 | C4: progressive | E4: SGD | F4: actual | G4: 3 | H4: staged
A5: M&A | E5: MYR | G5: Excluded | H5: per_year
A6: Fundraising | E6: CNY
E7: JPY
E8: KRW
E9: EUR
E10: GBP
E11: AUD

Sheet _meta
A1: inputs_json_baseline
A2: {"engagement": {"company_name": "Sample TechCo Holdings Limited", "company_country": "SG", "company_industry_us": "Software (Internet)", "company_industry_global": "Software (Internet)", "valuation_date": "2026-03-31", "target_valuation": 500000000, "exchange_platform": "NASDAQ", "report_purpose": "IPO pricing", "accounting_standard": "IFRS", "engagement_team": {"partner": "A. Lee", "manager": "T. Wong", "department": "Valuation Advisory"}, "client_name": "Sample TechCo Holdings Limited"}, "currency": {"primary": "USD", "unit": "'000", "alt": null, "fx_rate_alt": null}, "tax": {"jurisdiction": "SG", "type": "flat", "rate_low": 0.17, "rate_high": 0.17, "threshold": null, "effective_rate_override": null}, "projections": {"years": 5, "revenue_growth_method": "per_year", "revenue_growth": [0.45, 0.3, 0.22, 0.16, 0.1], "gross_margin": [0.62, 0.64, 0.65, 0.65, 0.66], "opex_pct_revenue": [0.55, 0.5, 0.45, 0.42, 0.4], "capex_pct_revenue": [0.06, 0.05, 0.04, 0.04, 0.04], "dep_pct_revenue": [0.04, 0.04, 0.04, 0.04, 0.04], "nwc_pct_sales": [0.08, 0.08, 0.08, 0.08, 0.08], "revenue_y0": 100000, "nwc_y0": 8000}, "terminal": {"method": "gordon_growth", "growth_rate": 0.03, "exit_multiple_type": null, "exit_multiple_value": null}, "wacc": {"shared": {"risk_free_rate": 0.045, "risk_free_rate_source": "10y UST as at 2026-04-29", "equity_risk_premium": 0.055, "country_risk_premium": 0.005}, "per_management": {"unlevered_beta": 1.05, "target_debt_to_equity": 0.2, "size_premium": 0.02, "specific_risk_premium": 0.02, "pretax_cost_of_debt": 0.06, "target_debt_weight": 0.17, "target_equity_weight": 0.83}, "independent": {"unlevered_beta": 1.15, "target_debt_to_equity": 0.25, "size_premium": 0.025, "specific_risk_premium": 0.03, "pretax_cost_of_debt": 0.065, "target_debt_weight": 0.2, "target_equity_weight": 0.8}}, "cocos": [{"tier": 1, "include": true, "company": "Atlassian", "ticker": "NASDAQ:TEAM", "exchange": "NASDAQ", "business_description": "Team collaboration and productivity software (Jira, Confluence)", "selected_for_wacc": true, "country": "AU", "accounting": "US GAAP", "market_cap_usd_mm": 50000, "d_to_e": 0.05, "raw_beta": 1.2, "tax_rate": 0.21}, {"tier": 1, "include": true, "company": "Datadog", "ticker": "NASDAQ:DDOG", "exchange": "NASDAQ", "business_description": "Cloud observability and monitoring platform", "selected_for_wacc": true, "country": "US", "accounting": "US GAAP", "market_cap_usd_mm": 38000, "d_to_e": 0.1, "raw_beta": 1.3, "tax_rate": 0.21}, {"tier": 2, "include": true, "company": "MongoDB", "ticker": "NASDAQ:MDB", "exchange": "NASDAQ", "business_description": "Document-oriented NoSQL database (Atlas managed service)", "selected_for_wacc": true, "country": "US", "accounting": "US GAAP", "market_cap_usd_mm": 22000, "d_to_e": 0.08, "raw_beta": 1.25, "tax_rate": 0.21}, {"tier": 3, "include": true, "company": "Box", "ticker": "NASDAQ:BOX", "exchange": "NASDAQ", "business_description": "Cloud content management and file sharing for enterprise", "selected_for_wacc": false, "country": "US", "accounting": "US GAAP", "market_cap_usd_mm": 4500, "d_to_e": 0.35, "raw_beta": 1.1, "tax_rate": 0.21}], "precedents": [{"include": true, "date": "2024-09-12", "acquirer": "Cisco", "target": "Splunk", "ev_usd_mm": 28000, "ev_revenue": 7.2, "ev_ebitda": 24.0, "premium": 0.31, "rationale": "Strategic \u2014 observability stack"}], "bridge": {"surplus_assets": 25000, "net_debt_override": null, "minority_interests": 0, "non_operating_assets": 0, "dlom_pct": 0.2, "dloc_pct": 0.15, "equity_interest_pct": 1.0, "shares_outstanding": 250000000, "shares_outstanding_diluted": 285000000, "pre_money_pct": 0.85}, "adjustments": {"capitalize_rd": true, "rd_amortization_years": 5, "convert_operating_leases": false, "lease_discount_rate": null}, "football_field": {"weight_dcf": 0.5, "weight_comps": 0.3, "weight_precedent": 0.2, "weight_nav": 0.0, "selected_low": null, "selected_mid": null, "selected_high": null}, "sensitivity": {"wacc_step": 0.005, "wacc_count": 5, "terminal_g_step": 0.005, "terminal_g_count": 5, "revenue_g_step": 0.02, "ebitda_margin_step": 0.02}, "sources": {"company_name": {"source": "Engagement Letter", "detail": "EL dated 2026-03-15", "notes": ""}, "valuation_date": {"source": "Engagement Letter", "detail": "EL dated 2026-03-15", "notes": ""}, "revenue_y0": {"source": "Audited FS", "detail": "FY2025 Audited FS, Consolidated P&L, p.34", "notes": "Last full reported year", "rationale": "Y0 revenue is taken from the most recently audited full fiscal year. This is the cascade base \u2014 every projected year multiplies forward from this number, so accuracy here matters more than any single growth assumption downstream."}, "nwc_y0": {"source": "Audited FS", "detail": "FY2025 Audited FS, Balance Sheet, p.36 (current assets ex-cash \u2212 current liabilities ex-debt)", "notes": ""}, "unlevered_beta_per_mgmt": {"source": "Calculated", "detail": "Median unlevered beta of comparable companies marked selected_for_wacc, re-levered to target capital structure", "notes": "", "rationale": "Built from the three Tier-1/2 SaaS comps marked selected_for_wacc (Atlassian, Datadog, MongoDB). Each comp's levered beta is unlevered via Hamada using the comp's own D/E and tax rate, then the median is re-levered at the target's planned capital structure inside the DCF. This produces a beta that reflects the target's industry risk and the chosen post-IPO leverage profile, rather than an arbitrary industry-average number."}, "shares_outstanding": {"source": "Prospectus", "detail": "Draft prospectus, share capital section", "notes": "Basic \u2014 diluted figure tracked separately"}, "terminal_growth_rate": {"source": "Manual", "detail": "Long-run global GDP growth proxy for software industry maturity", "notes": "", "rationale": "3.0% chosen as the long-run sustainable growth rate \u2014 sits inside the 2\u20134% band typical for mature SaaS and just below long-run US nominal GDP. Anything higher implies the company outgrows the economy indefinitely, which collapses Gordon-growth defensibility under Big-4 review."}, "tax_rate_high": {"source": "Manual", "detail": "Singapore corporate tax rate 17% flat", "notes": ""}, "risk_free_rate": {"source": "Manual", "detail": "10y UST yield 2026-04-29 close", "notes": "", "rationale": "Anchored to the 10-year UST yield because the target is pricing a Nasdaq listing; equity-cost build follows US-rate convention regardless of the SG operating base. Refreshed close to the valuation date so we are not pricing off stale-rate residuals."}, "equity_risk_premium": {"source": "Damodaran", "detail": "Damodaran ERP 2024 implied", "notes": "", "rationale": "Damodaran's implied ERP is the standard reference for US public valuations and lines up with the cost-of-equity surveys used by Big-4 fairness opinions. Chosen over historical excess returns to reflect the forward-looking risk premium investors are demanding today."}, "country_risk_premium": {"source": "Damodaran", "detail": "Damodaran Country ERP 2024, SG", "notes": ""}, "dlom_pct": {"source": "Manual", "detail": "Restricted stock studies median, 2024", "notes": "Pre-IPO", "rationale": "20% DLOM reflects the median of recent restricted-stock and pre-IPO studies for software companies 6\u201318 months from a planned listing. Applied because the holdings being valued today cannot be freely traded until lockup expiry post-listing."}, "dloc_pct": {"source": "Manual", "detail": "Mergerstat control premium inverse", "notes": "", "rationale": "15% DLOC inverts the median control premium observed in Mergerstat's recent dataset. Applied because the valuation is for a minority stake; a controlling holder would not absorb the same discount."}}, "historical_fs": {"revenue": [70000, 78000, 86000, 95000, 100000], "cogs": [-42000, -46800, -51600, -57000, -60000], "gross_profit": [28000, 31200, 34400, 38000, 40000], "opex_total": [-21000, -23400, -25800, -28500, -30000], "sga": [-15000, -16800, -18500, -20400, -21500], "rnd": [-6000, -6600, -7300, -8100, -8500], "ebitda": [7000, 7800, 8600, 9500, 10000], "da": [-2100, -2340, -2580, -2850, -3000], "ebit": [4900, 5460, 6020, 6650, 7000], "interest_expense": [-800, -800, -750, -700, -700], "other_income_expense": [0, 0, 0, 0, 0], "profit_before_tax": [4100, 4660, 5270, 5950, 6300], "tax_expense": [-984, -1118, -1265, -1428, -1512], "net_income": [3116, 3542, 4005, 4522, 4788], "cash": [3000, 3500, 4500, 5500, 6500], "accounts_receivable": [10000, 11000, 12000, 13000, 14000], "inventory": [4500, 5000, 5500, 6000, 6500], "prepaid_expenses": [800, 900, 1000, 1100, 1200], "total_current_assets": [18300, 20400, 23000, 25600, 28200], "ppe": [22000, 26000, 30000, 34000, 38000], "intangibles": [3500, 3500, 3500, 3500, 3500], "other_lt_assets": [1500, 1500, 1500, 1500, 1500], "total_assets": [45300, 51400, 58000, 64600, 71200], "accounts_payable": [-7000, -7700, -8500, -9300, -10000], "short_term_debt": [-3000, -2500, -2000, -2000, -2000], "other_current_liabilities": [-2000, -2200, -2400, -2700, -3000], "total_current_liabilities": [-12000, -12400, -12900, -14000, -15000], "long_term_debt": [-12000, -11000, -9500, -9000, -8500], "other_lt_liabilities": [-1000, -1000, -1000, -1000, -1000], "total_liabilities": [-25000, -24400, -23400, -24000, -24500], "total_equity": [20300, 27000, 34600, 40600, 46700]}, "coco_multiples": [{"ev_sales_ltm": 4.2, "ev_sales_ntm": 3.5, "ev_ebitda_ltm": 18.0, "ev_ebitda_ntm": 15.0, "pe_ltm": 26.0, "pe_ntm": 22.0}, {"ev_sales_ltm": 3.8, "ev_sales_ntm": 3.2, "ev_ebitda_ltm": 16.5, "ev_ebitda_ntm": 13.5, "pe_ltm": 24.0, "pe_ntm": 20.0}, {"ev_sales_ltm": 5.5, "ev_sales_ntm": 4.6, "ev_ebitda_ltm": 22.0, "ev_ebitda_ntm": 18.0, "pe_ltm": 32.0, "pe_ntm": 26.0}, {"ev_sales_ltm": 3.1, "ev_sales_ntm": 2.7, "ev_ebitda_ltm": 14.0, "ev_ebitda_ntm": 12.0, "pe_ltm": 21.0, "pe_ntm": 18.0}], "coco_margins": [{"gross": 0.55, "ebit": 0.18, "net": 0.12}, {"gross": 0.52, "ebit": 0.16, "net": 0.1}, {"gross": 0.62, "ebit": 0.22, "net": 0.16}, {"gross": 0.48, "ebit": 0.14, "net": 0.09}], "coco_ratios": [{"roe": 0.18, "roa": 0.08, "d_to_e": 0.2, "current_ratio": 2.1}, {"roe": 0.16, "roa": 0.07, "d_to_e": 0.25, "current_ratio": 1.9}, {"roe": 0.22, "roa": 0.1, "d_to_e": 0.15, "current_ratio": 2.5}, {"roe": 0.14, "roa": 0.06, "d_to_e": 0.3, "current_ratio": 1.7}]}
