Workbook
Name company_name: 'Inputs'!$D$7
Name company_country: 'Inputs'!$D$8
Name company_industry_us: 'Inputs'!$D$9
Name company_industry_global: 'Inputs'!$D$10
Name valuation_date: 'Inputs'!$D$11
Name report_purpose: 'Inputs'!$D$12
Name accounting_standard: 'Inputs'!$D$13
Name engagement_team_partner: 'Inputs'!$D$14
Name engagement_team_manager: 'Inputs'!$D$15
Name engagement_department: 'Inputs'!$D$16
Name client_name: 'Inputs'!$D$17
Name currency: 'Inputs'!$D$20
Name unit: 'Inputs'!$D$21
Name currency_alt: 'Inputs'!$D$22
Name fx_rate_alt: 'Inputs'!$D$23
Name tax_jurisdiction: 'Inputs'!$D$26
Name tax_type: 'Inputs'!$D$27
Name tax_rate_low: 'Inputs'!$D$28
Name tax_rate_high: 'Inputs'!$D$29
Name tax_threshold: 'Inputs'!$D$30
Name tax_effective_rate: 'Inputs'!$D$31
Name projection_years: 'Inputs'!$D$34
Name revenue_growth_method: 'Inputs'!$D$35
Name revenue_y0: 'Inputs'!$D$36
Name nwc_y0: 'Inputs'!$D$37
Name gross_profit_y0: 'Inputs'!$D$38
Name opex_y0: 'Inputs'!$D$39
Name ebitda_y0: 'Inputs'!$D$40
Name ebit_y0: 'Inputs'!$D$41
Name revenue_growth_y1: 'Inputs'!$D$42
Name revenue_growth_y2: 'Inputs'!$D$43
Name revenue_growth_y3: 'Inputs'!$D$44
Name revenue_growth_y4: 'Inputs'!$D$45
Name revenue_growth_y5: 'Inputs'!$D$46
Name gross_margin_y1: 'Inputs'!$D$47
Name gross_margin_y2: 'Inputs'!$D$48
Name gross_margin_y3: 'Inputs'!$D$49
Name gross_margin_y4: 'Inputs'!$D$50
Name gross_margin_y5: 'Inputs'!$D$51
Name opex_pct_revenue_y1: 'Inputs'!$D$52
Name opex_pct_revenue_y2: 'Inputs'!$D$53
Name opex_pct_revenue_y3: 'Inputs'!$D$54
Name opex_pct_revenue_y4: 'Inputs'!$D$55
Name opex_pct_revenue_y5: 'Inputs'!$D$56
Name capex_pct_revenue_y1: 'Inputs'!$D$57
Name capex_pct_revenue_y2: 'Inputs'!$D$58
Name capex_pct_revenue_y3: 'Inputs'!$D$59
Name capex_pct_revenue_y4: 'Inputs'!$D$60
Name capex_pct_revenue_y5: 'Inputs'!$D$61
Name dep_pct_revenue_y1: 'Inputs'!$D$62
Name dep_pct_revenue_y2: 'Inputs'!$D$63
Name dep_pct_revenue_y3: 'Inputs'!$D$64
Name dep_pct_revenue_y4: 'Inputs'!$D$65
Name dep_pct_revenue_y5: 'Inputs'!$D$66
Name nwc_pct_sales_y1: 'Inputs'!$D$67
Name nwc_pct_sales_y2: 'Inputs'!$D$68
Name nwc_pct_sales_y3: 'Inputs'!$D$69
Name nwc_pct_sales_y4: 'Inputs'!$D$70
Name nwc_pct_sales_y5: 'Inputs'!$D$71
Name terminal_method: 'Inputs'!$D$74

Sheet README
A1: Valuation Workpaper — Cover & User Guide
A2: Auto-generated by the Orionmano valuation pipeline. Read this sheet first. Every figure on every downstream tab is driven by a named range on the Inputs sheet.
B4: Engagement metadata
B5: Company | C5: =company_name
B6: Country of incorporation | C6: =company_country
B7: Industry (US) | C7: =company_industry_us
B8: Industry (Global) | C8: =company_industry_global
B9: Valuation date | C9: =valuation_date
B10: Report purpose | C10: =report_purpose
B11: Accounting standard | C11: =accounting_standard
B12: Client (engaging party) | C12: =client_name
B13: Engagement partner | C13: =engagement_team_partner
B14: Engagement manager | C14: =engagement_team_manager
B15: Department | C15: =engagement_department
B17: Currency & units
B18: Reporting currency | C18: =currency
B19: Unit | C19: =unit
B20: Secondary currency | C20: =currency_alt
B21: FX rate to alt | C21: =fx_rate_alt
B22: Note | C22: All monetary values throughout this workbook are denominated in [currency] [unit] unless explicitly stated otherwise.
B24: Valuation methodologies & weights
B25: Methodology | C25: Weight | D25: Sheet | E25: Notes
B26: Discounted Cash Flow (DCF) | C26: =weight_dcf | D26: DCF / DCF (Independent) | E26: Two-scenario WACC; Gordon-growth or exit-multiple terminal.
B27: Comparable Companies (CoCo) | C27: =weight_comps | D27: Comps / CoCo Multiples | E27: Q1/Median/Q3 NTM trading multiples × target metrics.
B28: Precedent Transactions | C28: =weight_precedent | D28: Precedent | E28: Mean EV/EBITDA × Y1 EBITDA from observed M&A deals.
B29: Net Asset Value (NAV) | C29: =weight_nav | D29: — | E29: Asset-based; typically 0% for going-concern targets.
B30: Total weight | C30: =weight_dcf+weight_comps+weight_precedent+weight_nav | D30: Must equal 100%
B33: Sheet index
B34: # | C34: Sheet | D34: Purpose
B35: 1 | C35: README | D35: Instructions, version, manual-input checklist
B36: 2 | C36: Dashboard | D36: High-level outputs: EV, Net debt, Surplus, Equity, WACC, terminal g + benchmark charts
B37: 3 | C37: Inputs | D37: Single source of truth — all driver parameters
B38: 4 | C38: Historical FS | D38: 3-5 yr audited income statement + balance sheet (PBC raw)
B39: 5 | C39: Projections | D39: Year-by-year forecast lines driven by Inputs
B40: 6 | C40: DCF | D40: FCFF schedule, partial-year discount, PV, terminal value
B41: 7 | C41: DCF (Independent) | D41: Parallel scenario with independent WACC range
B42: 8 | C42: Comps | D42: Apply CoCo multiples to target metrics; implied EV/Sales, EV/EBITDA, P/E
B43: 9 | C43: Football Field | D43: Valuation range chart per methodology + weighted selected range
B44: 10 | C44: WACC | D44: Full Ke + Kd build with Per-Mgmt and Independent scenarios
B45: 11 | C45: CoCo Selection | D45: Comparable company selection with tier flags + market cap
... B54: 20 | C54: Valuation Summary | D54: Final EV -> Equity -> Per share with all weighting and adjustments
B57: Items requiring post-export manual input
B58: # | C58: Item | D58: Sheet | E58: Cell / range | F58: Notes
B59: 1 | C59: Selected football-field band (analyst override) | D59: Inputs / Football Field | E59: selected_low / selected_mid / selected_high | F59: Producer auto-fills initial estimate (±15% around weighted mid). Adjust to your judgment band before finalizing.
B60: 2 | C60: shares_outstanding_diluted | D60: Inputs | E60: shares_outstanding_diluted | F60: Required for diluted per-share output. Pull from prospectus / cap table if not auto-filled.
B61: 3 | C61: Coco/Precedent metric values flagged as null | D61: CoCo Multiples / Margins / Ratios / Precedent | E61: Cells with INPUT_FILL background | F61: Producer leaves a metric null when source data is unavailable. Fill from Capital IQ / Bloomberg if you obtain it.
B62: 4 | C62: Engagement team names | D62: Inputs | E62: engagement_team_partner / engagement_team_manager | F62: Defaults to 'TBD' if engagement letter not provided. Replace with actual partner / manager names.
B64: Reference data — refresh schedule
B65: Dataset | C65: Cadence | D65: Source | E65: URL / vendor
B66: Country ERP | C66: Annual | D66: Damodaran NYU Stern country risk premium | E66: pages.stern.nyu.edu/~adamodar/
B67: Industry Averages | C67: Annual | D67: Damodaran US industry betas / margins / multiples | E67: pages.stern.nyu.edu/~adamodar/
B68: Risk-free rate | C68: Per engagement | D68: 10y UST yield as at valuation date | E68: Bloomberg / Capital IQ
B69: ERP | C69: Per engagement | D69: Implied / historical ERP for mature markets | E69: Damodaran implied ERP
B71: Disclaimer & use restriction
B72: This workpaper has been prepared for the express purpose stated above and for the exclusive use of the engaging party. It must not be reproduced, distributed, or relied upon by any other party without prior written consent. The valuation reflects conditions and information available as at the valuation date; subsequent events are not incorporated. All inputs derive from sources cited in the audit-trail columns of the Inputs sheet — refer to those entries for source documents and assumptions. This is not a fairness opinion, audit, or attestation engagement under PCAOB / AICPA standards unless explicitly designated.

Sheet Dashboard
A1: Valuation Dashboard
A2: =company_name & " — Valuation as at " & TEXT(valuation_date,"yyyy-mm-dd") & " · " & report_purpose
B4: Headline values (Per-Management scenario)
C5: Enterprise Value | D5: Equity (after DLOM/DLOC) | E5: Per share (basic) | F5: WACC | G5: Terminal growth
C6: ='Valuation Summary'!C7 | D6: ='Valuation Summary'!C10 | E6: ='Valuation Summary'!C16 | F6: =wacc_per_mgmt | G6: =terminal_growth_rate
B8: Independent scenario | C8: ='Valuation Summary'!D7 | D8: ='Valuation Summary'!D10 | E8: ='Valuation Summary'!D16 | F8: =wacc_indep | G8: =terminal_growth_rate
B11: Methodology range — enterprise value
B12: Methodology | C12: Low | D12: Mid | E12: High | F12: Weight | G12: Weighted mid | H12: Notes
B13: DCF (across scenarios) | C13: ='Football Field'!C7 | D13: ='Football Field'!D7 | E13: ='Football Field'!E7 | F13: =weight_dcf | G13: ='Football Field'!F7 | H13: Per-Mgmt vs Independent WACC.
B14: Comparable Companies | C14: ='Football Field'!C11 | D14: ='Football Field'!D11 | E14: ='Football Field'!E11 | F14: =weight_comps | G14: ='Football Field'!F11 | H14: NTM medians × target metrics.
B15: Precedent Transactions | C15: ='Football Field'!C12 | D15: ='Football Field'!D12 | E15: ='Football Field'!E12 | F15: =weight_precedent | G15: ='Football Field'!F12 | H15: Mean EV/EBITDA × Y1 EBITDA.
B17: Weighted-average EV | G17: ='Football Field'!F16
B18: Selected band (low / mid / high) | C18: =selected_low | D18: =selected_mid | E18: =selected_high
B20: CoCo trading multiples — benchmark stats
B21: Multiple | C21: Min | D21: Q1 | E21: Median | F21: Q3 | G21: Max | H21: Mean
B22: EV / Sales NTM | C22: ='CoCo Multiples'!F42 | D22: ='CoCo Multiples'!F41 | E22: ='CoCo Multiples'!F39 | F22: ='CoCo Multiples'!F38 | G22: ='CoCo Multiples'!F37 | H22: ='CoCo Multiples'!F40
B23: EV / EBITDA NTM | C23: ='CoCo Multiples'!H42 | D23: ='CoCo Multiples'!H41 | E23: ='CoCo Multiples'!H39 | F23: ='CoCo Multiples'!H38 | G23: ='CoCo Multiples'!H37 | H23: ='CoCo Multiples'!H40
B24: P / E NTM | C24: ='CoCo Multiples'!J42 | D24: ='CoCo Multiples'!J41 | E24: ='CoCo Multiples'!J39 | F24: ='CoCo Multiples'!J38 | G24: ='CoCo Multiples'!J37 | H24: ='CoCo Multiples'!J40
B25: EV / Sales LTM | C25: ='CoCo Multiples'!E42 | D25: ='CoCo Multiples'!E41 | E25: ='CoCo Multiples'!E39 | F25: ='CoCo Multiples'!E38 | G25: ='CoCo Multiples'!E37 | H25: ='CoCo Multiples'!E40
B26: EV / EBITDA LTM | C26: ='CoCo Multiples'!G42 | D26: ='CoCo Multiples'!G41 | E26: ='CoCo Multiples'!G39 | F26: ='CoCo Multiples'!G38 | G26: ='CoCo Multiples'!G37 | H26: ='CoCo Multiples'!G40
B27: P / E LTM | C27: ='CoCo Multiples'!I42 | D27: ='CoCo Multiples'!I41 | E27: ='CoCo Multiples'!I39 | F27: ='CoCo Multiples'!I38 | G27: ='CoCo Multiples'!I37 | H27: ='CoCo Multiples'!I40
B30: Sensitivity — EV (WACC × terminal growth, Per-Mgmt)
B31: Full grid is on the Sensitivity tab. This panel shows EV at the base case (centre cell) plus ±1 step in each direction.
B32: WACC ↓ / g → | C32: g − 1 step | D32: Base g | E32: g + 1 step
B33: WACC − 1 step | C33: =INDEX('Sensitivity'!C7:M17,sens_wacc_count,sens_terminal_g_count) | D33: =INDEX('Sensitivity'!C7:M17,sens_wacc_count,sens_terminal_g_count+1) | E33: =INDEX('Sensitivity'!C7:M17,sens_wacc_count,sens_terminal_g_count+2)
B34: Base WACC | C34: =INDEX('Sensitivity'!C7:M17,sens_wacc_count+1,sens_terminal_g_count) | D34: =INDEX('Sensitivity'!C7:M17,sens_wacc_count+1,sens_terminal_g_count+1) | E34: =INDEX('Sensitivity'!C7:M17,sens_wacc_count+1,sens_terminal_g_count+2)
B35: WACC + 1 step | C35: =INDEX('Sensitivity'!C7:M17,sens_wacc_count+2,sens_terminal_g_count) | D35: =INDEX('Sensitivity'!C7:M17,sens_wacc_count+2,sens_terminal_g_count+1) | E35: =INDEX('Sensitivity'!C7:M17,sens_wacc_count+2,sens_terminal_g_count+2)
B38: Backtesting — historical revenue vs Y0 base
B39: Sanity check: Y0 base revenue (cascading into Projections) should equal the most-recent FY-1 audited revenue.
C40: FY-3 | D40: FY-2 | E40: FY-1 | F40: Y0 (Projections) | G40: Δ Y0 vs FY-1
B41: Revenue | C41: ='Historical FS'!E7 | D41: ='Historical FS'!F7 | E41: ='Historical FS'!G7 | F41: =revenue_y0 | G41: =IFERROR(revenue_y0/'Historical FS'!G7-1,"n/a")
B42: EBITDA | C42: ='Historical FS'!E13 | D42: ='Historical FS'!F13 | E42: ='Historical FS'!G13 | F42: — | G42: —
B45: Open the web dashboard (Orionmano · Companies · this entity · Valuation tab) for interactive Football Field, Sensitivity heatmap, FCFF projection, and CoCo multiple charts.

Sheet Inputs
A1: Inputs — single source of truth for all valuation parameters
A2: Every parameter below is a named range. Downstream sheets reference these by name, not by cell coordinate. The Source / Source detail / Notes columns record the audit trail.
A4: id | B4: Parameter | C4: Type | D4: Value (Per Mgmt) | E4: Value (Independent) | F4: Source | G4: Source detail | H4: Notes
A6: Section A — Engagement metadata (Core)
A7: company_name | B7: Company name | C7: text
A8: company_country | B8: Country of incorporation | C8: enum
A9: company_industry_us | B9: Industry (US classification) | C9: enum
A10: company_industry_global | B10: Industry (Global classification) | C10: enum
A11: valuation_date | B11: Valuation date | C11: date
A12: report_purpose | B12: Report purpose | C12: enum
A13: accounting_standard | B13: Accounting standard | C13: enum
A14: engagement_team_partner | B14: Engagement partner | C14: text
A15: engagement_team_manager | B15: Engagement manager | C15: text
A16: engagement_department | B16: Department | C16: text
A17: client_name | B17: Client (engaging party) | C17: text
A19: Section B — Currency & units (Core)
A20: currency | B20: Reporting currency | C20: enum
A21: unit | B21: Unit of presentation | C21: enum
A22: currency_alt | B22: Secondary display currency (optional) | C22: enum
A23: fx_rate_alt | B23: FX rate to alternate currency | C23: number
A25: Section C — Tax rule (Core)
A26: tax_jurisdiction | B26: Tax jurisdiction | C26: enum
A27: tax_type | B27: Tax structure | C27: enum | H27: flat | two_tier | progressive
A28: tax_rate_low | B28: Low-tier rate | C28: percentage
A29: tax_rate_high | B29: High-tier rate (or flat rate) | C29: percentage
A30: tax_threshold | B30: Threshold between tiers | C30: currency
A31: tax_effective_rate | B31: Effective rate (override) | C31: percentage
A33: Section D — Projection drivers (Core)
A34: projection_years | B34: Explicit forecast years | C34: number
A35: revenue_growth_method | B35: Revenue growth method | C35: enum | H35: flat | declining | staged | per_year
A36: revenue_y0 | B36: Revenue base (Y0 / LTM) | C36: currency | H36: Last reported full-year revenue; cascades into Projections
A37: nwc_y0 | B37: Net working capital (Y0) | C37: currency | H37: Audited Y0 NWC; required for Y1 ΔNWC computation
A38: gross_profit_y0 | B38: Gross profit (Y0) | C38: currency | H38: Audited Y0 gross profit; populates Projections!C12
A39: opex_y0 | B39: Operating expenses (Y0) | C39: currency | H39: Audited Y0 opex (negative); populates Projections!C14
A40: ebitda_y0 | B40: EBITDA (Y0) | C40: currency | H40: Audited Y0 EBITDA; populates Projections!C15
A41: ebit_y0 | B41: EBIT (Y0) | C41: currency | H41: Audited Y0 EBIT; populates Projections!C18
A42: revenue_growth_y1 | B42: Revenue growth (Y1) | C42: percentage
A43: revenue_growth_y2 | B43: Revenue growth (Y2) | C43: percentage
A44: revenue_growth_y3 | B44: Revenue growth (Y3) | C44: percentage
A45: revenue_growth_y4 | B45: Revenue growth (Y4) | C45: percentage
A46: revenue_growth_y5 | B46: Revenue growth (Y5) | C46: percentage
A47: gross_margin_y1 | B47: Gross margin (Y1) | C47: percentage
A48: gross_margin_y2 | B48: Gross margin (Y2) | C48: percentage
A49: gross_margin_y3 | B49: Gross margin (Y3) | C49: percentage
A50: gross_margin_y4 | B50: Gross margin (Y4) | C50: percentage
A51: gross_margin_y5 | B51: Gross margin (Y5) | C51: percentage
A52: opex_pct_revenue_y1 | B52: Opex % of revenue (Y1) | C52: percentage
A53: opex_pct_revenue_y2 | B53: Opex % of revenue (Y2) | C53: percentage
... A71: nwc_pct_sales_y5 | B71: Working capital % of sales (Y5) | C71: percentage
A73: Section E — Terminal value (Core)
A74: terminal_method | B74: Terminal value method | C74: enum | H74: gordon_growth | exit_multiple
A75: terminal_growth_rate | B75: Terminal growth rate | C75: percentage
A76: terminal_exit_multiple_type | B76: Exit multiple metric | C76: enum
A77: terminal_exit_multiple_value | B77: Exit multiple value | C77: number
A79: Section F — WACC inputs (Core)
A80: risk_free_rate | B80: Risk-free rate | C80: percentage
A81: risk_free_rate_source | B81: Risk-free rate source descriptor | C81: text
A82: equity_risk_premium | B82: Equity risk premium (ERP) | C82: percentage
A83: country_risk_premium | B83: Country risk premium | C83: percentage
A84: unlevered_beta | B84: Unlevered beta | C84: number
A85: target_debt_to_equity | B85: Target D/E ratio | C85: percentage
A86: levered_beta | B86: Levered beta (calculated) | C86: number | D86: =WACC!E10 | E86: =WACC!F10
A87: size_premium | B87: Size premium | C87: percentage
A88: specific_risk_premium | B88: Specific risk premium | C88: percentage
A89: cost_of_equity | B89: Cost of equity (calculated) | C89: percentage | D89: =WACC!E16 | E89: =WACC!F16
A90: pretax_cost_of_debt | B90: Pre-tax cost of debt | C90: percentage
A91: aftertax_cost_of_debt | B91: After-tax cost of debt (calculated) | C91: percentage | D91: =WACC!E20 | E91: =WACC!F20
A92: target_debt_weight | B92: D/V (debt weight) | C92: percentage
A93: target_equity_weight | B93: E/V (equity weight) | C93: percentage
A94: wacc | B94: WACC (calculated) | C94: percentage | D94: =WACC!E25 | E94: =WACC!F25
A96: Section I — EV -> Equity bridge (Core)
A97: surplus_assets | B97: Surplus / non-operating assets | C97: currency
A98: net_debt_override | B98: Net debt (override) | C98: currency
A99: minority_interests | B99: Minority interests | C99: currency
A100: non_operating_assets | B100: Non-operating assets | C100: currency
A101: dlom_pct | B101: DLOM rate | C101: percentage
A102: dloc_pct | B102: DLOC rate | C102: percentage
A103: equity_interest_pct | B103: Client's % equity interest | C103: percentage
A104: shares_outstanding | B104: Shares outstanding (basic) | C104: number
A105: shares_outstanding_diluted | B105: Shares outstanding (diluted) | C105: number
A106: pre_money_pct | B106: Pre-money equity % | C106: percentage
A108: Section J — Adjustment toggles (Extended)
A109: capitalize_rd | B109: Capitalize R&D? | C109: boolean
A110: rd_amortization_years | B110: R&D amortization period (years) | C110: number
A111: convert_operating_leases | B111: Convert operating leases to debt? | C111: boolean
A112: lease_discount_rate | B112: Lease discount rate | C112: percentage
A114: Section K — Football field weights (Extended)
A115: weight_dcf | B115: DCF weight | C115: percentage
A116: weight_comps | B116: Comparable companies weight | C116: percentage
A117: weight_precedent | B117: Precedent transactions weight | C117: percentage
A118: weight_nav | B118: NAV / asset-based weight | C118: percentage
A119: selected_low | B119: Selected valuation low | C119: currency
A120: selected_mid | B120: Selected valuation mid | C120: currency
A121: selected_high | B121: Selected valuation high | C121: currency
A123: Section L — Sensitivity ranges (Extended)
A124: sens_wacc_step | B124: WACC sensitivity step | C124: percentage
A125: sens_wacc_count | B125: WACC steps each side of base | C125: number
A126: sens_terminal_g_step | B126: Terminal g sensitivity step | C126: percentage
A127: sens_terminal_g_count | B127: Terminal g steps each side | C127: number
A128: sens_revenue_g_step | B128: Revenue growth sens step | C128: percentage
...

Sheet Historical FS
A1: Historical Financial Statements
A2: 3-5 years audited income statement + balance sheet. Manual entry from client PBC. Y0 base values for the Projections sheet (revenue, NWC) should be populated from this sheet.
A4: Line item | B4: Unit | C4: FY-5 | D4: FY-4 | E4: FY-3 | F4: FY-2 | G4: FY-1
A6: Income Statement
A7: Revenue | B7: (currency × unit)
A8: Cost of revenue | B8: (currency × unit)
A9: Gross profit | B9: (currency × unit)
A10: Operating expenses | B10: (currency × unit)
A11: Selling, general & admin | B11: (currency × unit)
A12: Research & development | B12: (currency × unit)
A13: EBITDA | B13: (currency × unit)
A14: Depreciation & amortization | B14: (currency × unit)
A15: EBIT (Operating income) | B15: (currency × unit)
A16: Interest expense | B16: (currency × unit)
A17: Other income / (expense) | B17: (currency × unit)
A18: Profit before tax | B18: (currency × unit)
... A20: Net income | B20: (currency × unit)
A22: Balance Sheet
A23: Current assets | B23: (currency × unit)
A24: Cash and equivalents | B24: (currency × unit)
A25: Accounts receivable | B25: (currency × unit)
A26: Inventory | B26: (currency × unit)
A27: Prepaid expenses | B27: (currency × unit)
A28: Total current assets | B28: (currency × unit)
A29: Non-current assets | B29: (currency × unit)
A30: Property, plant & equipment | B30: (currency × unit)
A31: Intangible assets | B31: (currency × unit)
A32: Other long-term assets | B32: (currency × unit)
A33: Total assets | B33: (currency × unit)
A35: Current liabilities | B35: (currency × unit)
... A44: Total equity | B44: (currency × unit)
A46: Derived metrics (calculated)
A47: Net working capital (= current assets − current liabilities) | B47: (currency × unit) | C47: =C28-C39 | D47: =D28-D39 | E47: =E28-E39 | F47: =F28-F39 | G47: =G28-G39
A48: Net debt (= short-term debt + long-term debt − cash) | B48: (currency × unit) | C48: =C37+C41-C24 | D48: =D37+D41-D24 | E48: =E37+E41-E24 | F48: =F37+F41-F24 | G48: =G37+G41-G24

Sheet Projections
A1: Projections — driven by Inputs
A2: Year-by-year forecast lines. Every assumption flows from Inputs named ranges. Edit a value on Inputs and this sheet recalculates.
A4: Line item | B4: Unit | C4: Y0 (base) | D4: Y1 | E4: Y2 | F4: Y3 | G4: Y4 | H4: Y5
A6: Revenue & growth
A8: Revenue | B8: (from Inputs) | C8: =revenue_y0 | D8: =C8*(1+revenue_growth_y1) | E8: =D8*(1+revenue_growth_y2) | F8: =E8*(1+revenue_growth_y3) | G8: =F8*(1+revenue_growth_y4) | H8: =G8*(1+revenue_growth_y5)
A9: Revenue growth | B9: % | D9: =revenue_growth_y1 | E9: =revenue_growth_y2 | F9: =revenue_growth_y3 | G9: =revenue_growth_y4 | H9: =revenue_growth_y5
A11: Profitability
A12: Gross profit | B12: (currency × unit) | C12: =IFERROR(gross_profit_y0,"") | D12: =D8*gross_margin_y1 | E12: =E8*gross_margin_y2 | F12: =F8*gross_margin_y3 | G12: =G8*gross_margin_y4 | H12: =H8*gross_margin_y5
A13: Gross margin | B13: % | C13: =IFERROR(gross_profit_y0/revenue_y0,"") | D13: =gross_margin_y1 | E13: =gross_margin_y2 | F13: =gross_margin_y3 | G13: =gross_margin_y4 | H13: =gross_margin_y5
A14: Operating expenses | B14: (currency × unit) | C14: =IFERROR(opex_y0,"") | D14: =-D8*opex_pct_revenue_y1 | E14: =-E8*opex_pct_revenue_y2 | F14: =-F8*opex_pct_revenue_y3 | G14: =-G8*opex_pct_revenue_y4 | H14: =-H8*opex_pct_revenue_y5
A15: EBITDA | B15: (currency × unit) | C15: =IFERROR(ebitda_y0,"") | D15: =D12+D14 | E15: =E12+E14 | F15: =F12+F14 | G15: =G12+G14 | H15: =H12+H14
A16: EBITDA margin | B16: % | C16: =IFERROR(ebitda_y0/revenue_y0,"") | D16: =IFERROR(D15/D8,0) | E16: =IFERROR(E15/E8,0) | F16: =IFERROR(F15/F8,0) | G16: =IFERROR(G15/G8,0) | H16: =IFERROR(H15/H8,0)
A17: Depreciation & amortization | B17: (currency × unit) | D17: =-D8*dep_pct_revenue_y1 | E17: =-E8*dep_pct_revenue_y2 | F17: =-F8*dep_pct_revenue_y3 | G17: =-G8*dep_pct_revenue_y4 | H17: =-H8*dep_pct_revenue_y5
A18: EBIT | B18: (currency × unit) | C18: =IFERROR(ebit_y0,"") | D18: =D15+D17 | E18: =E15+E17 | F18: =F15+F17 | G18: =G15+G17 | H18: =H15+H17
A19: EBIT margin | B19: % | C19: =IFERROR(ebit_y0/revenue_y0,"") | D19: =IFERROR(D18/D8,0) | E19: =IFERROR(E18/E8,0) | F19: =IFERROR(F18/F8,0) | G19: =IFERROR(G18/G8,0) | H19: =IFERROR(H18/H8,0)
A21: Tax & net income
A22: Tax | B22: (currency × unit) | D22: =IF(ISNUMBER(tax_effective_rate),-MAX(D18,0)*tax_effective_rate,IF(EXACT(tax_type,"two_tier"),IF(D18<=tax_threshold,-MAX(D18,0)*tax_rate_low,-(tax_threshold*tax_rate_low+MAX(D18-tax_threshold,0)*tax_rate_high)),-MAX(D18,0)*tax_rate_high)) | E22: =IF(ISNUMBER(tax_effective_rate),-MAX(E18,0)*tax_effective_rate,IF(EXACT(tax_type,"two_tier"),IF(E18<=tax_threshold,-MAX(E18,0)*tax_rate_low,-(tax_threshold*tax_rate_low+MAX(E18-tax_threshold,0)*tax_rate_high)),-MAX(E18,0)*tax_rate_high)) | F22: =IF(ISNUMBER(tax_effective_rate),-MAX(F18,0)*tax_effective_rate,IF(EXACT(tax_type,"two_tier"),IF(F18<=tax_threshold,-MAX(F18,0)*tax_rate_low,-(tax_threshold*tax_rate_low+MAX(F18-tax_threshold,0)*tax_rate_high)),-MAX(F18,0)*tax_rate_high)) | G22: =IF(ISNUMBER(tax_effective_rate),-MAX(G18,0)*tax_effective_rate,IF(EXACT(tax_type,"two_tier"),IF(G18<=tax_threshold,-MAX(G18,0)*tax_rate_low,-(tax_threshold*tax_rate_low+MAX(G18-tax_threshold,0)*tax_rate_high)),-MAX(G18,0)*tax_rate_high)) | H22: =IF(ISNUMBER(tax_effective_rate),-MAX(H18,0)*tax_effective_rate,IF(EXACT(tax_type,"two_tier"),IF(H18<=tax_threshold,-MAX(H18,0)*tax_rate_low,-(tax_threshold*tax_rate_low+MAX(H18-tax_threshold,0)*tax_rate_high)),-MAX(H18,0)*tax_rate_high))
A23: Net income | B23: (currency × unit) | D23: =D18+D22 | E23: =E18+E22 | F23: =F18+F22 | G23: =G18+G22 | H23: =H18+H22
A25: Capex & working capital
A26: Capex | B26: (currency × unit) | D26: =-D8*capex_pct_revenue_y1 | E26: =-E8*capex_pct_revenue_y2 | F26: =-F8*capex_pct_revenue_y3 | G26: =-G8*capex_pct_revenue_y4 | H26: =-H8*capex_pct_revenue_y5
A27: Net working capital | B27: (from Inputs) | C27: =nwc_y0 | D27: =D8*nwc_pct_sales_y1 | E27: =E8*nwc_pct_sales_y2 | F27: =F8*nwc_pct_sales_y3 | G27: =G8*nwc_pct_sales_y4 | H27: =H8*nwc_pct_sales_y5
A28: Δ Working capital | B28: (currency × unit) | D28: =-(D27-C27) | E28: =-(E27-D27) | F28: =-(F27-E27) | G28: =-(G27-F27) | H28: =-(H27-G27)
A30: FCFF construction
A31: EBIT | B31: (currency × unit) | D31: =D18 | E31: =E18 | F31: =F18 | G31: =G18 | H31: =H18
A32: Less: Tax on EBIT | B32: (currency × unit) | D32: =D22 | E32: =E22 | F32: =F22 | G32: =G22 | H32: =H22
A33: Add: Depreciation | B33: (currency × unit) | D33: =-D17 | E33: =-E17 | F33: =-F17 | G33: =-G17 | H33: =-H17
A34: Less: Capex | B34: (currency × unit) | D34: =D26 | E34: =E26 | F34: =F26 | G34: =G26 | H34: =H26
A35: Less: Δ Working capital | B35: (currency × unit) | D35: =D28 | E35: =E28 | F35: =F28 | G35: =G28 | H35: =H28
A36: Free Cash Flow to Firm (FCFF) | B36: (currency × unit) | D36: =SUM(D31:D35) | E36: =SUM(E31:E35) | F36: =SUM(F31:F35) | G36: =SUM(G31:G35) | H36: =SUM(H31:H35)

Sheet DCF
A1: DCF — Per Management scenario
A2: FCFF schedule from Projections, discounted at scenario WACC. Convention: full-period discounting (no stub-year partial); terminal value computed at end of Y5 and PV'd at the same Y5 discount factor.
A4: Item | B4: Unit | D4: Y1 | E4: Y2 | F4: Y3 | G4: Y4 | H4: Y5 | I4: Terminal
A6: Discount inputs
A7: WACC (this scenario) | B7: % | D7: =wacc_per_mgmt
A8: Terminal growth rate | B8: % | D8: =terminal_growth_rate
A10: FCFF & discount mechanics
A11: FCFF | B11: (currency × unit) | D11: =Projections!D36 | E11: =Projections!E36 | F11: =Projections!F36 | G11: =Projections!G36 | H11: =Projections!H36
A12: Discount period | B12: years | D12: 1 | E12: 2 | F12: 3 | G12: 4 | H12: 5
A13: Discount factor | B13: x | D13: =1/(1+wacc_per_mgmt)^D12 | E13: =1/(1+wacc_per_mgmt)^E12 | F13: =1/(1+wacc_per_mgmt)^F12 | G13: =1/(1+wacc_per_mgmt)^G12 | H13: =1/(1+wacc_per_mgmt)^H12
A14: PV of FCFF | B14: (currency × unit) | D14: =D11*D13 | E14: =E11*E13 | F14: =F11*F13 | G14: =G11*G13 | H14: =H11*H13
A16: Terminal value
A17: Method | I17: =terminal_method
A18: Y5 FCFF | B18: (currency × unit) | I18: =Projections!H36
A19: Terminal value — Gordon Growth | B19: (currency × unit) | I19: =IFERROR(I18*(1+terminal_growth_rate)/(wacc_per_mgmt-terminal_growth_rate),0)
A20: Terminal value — Exit Multiple | B20: (currency × unit) | I20: =IF(EXACT(terminal_exit_multiple_type,"EV/EBITDA"),Projections!H15*terminal_exit_multiple_value,IF(EXACT(terminal_exit_multiple_type,"EV/Sales"),Projections!H8*terminal_exit_multiple_value,IF(EXACT(terminal_exit_multiple_type,"P/E"),Projections!H23*terminal_exit_multiple_value,0)))
A21: Selected terminal value | B21: (currency × unit) | I21: =IF(EXACT(terminal_method,"exit_multiple"),I20,I19)
A22: PV of terminal value | B22: (currency × unit) | I22: =I21*H13
A24: Enterprise Value
A25: Sum of PV of explicit-period FCFF | I25: =SUM(D14:H14)
A26: + PV of terminal value | I26: =I22
A27: Enterprise Value | I27: =I25+I26

Sheet DCF (Independent)
A1: DCF — Independent scenario
A2: FCFF schedule from Projections, discounted at scenario WACC. Convention: full-period discounting (no stub-year partial); terminal value computed at end of Y5 and PV'd at the same Y5 discount factor.
A4: Item | B4: Unit | D4: Y1 | E4: Y2 | F4: Y3 | G4: Y4 | H4: Y5 | I4: Terminal
A6: Discount inputs
A7: WACC (this scenario) | B7: % | D7: =wacc_indep
A8: Terminal growth rate | B8: % | D8: =terminal_growth_rate
A10: FCFF & discount mechanics
A11: FCFF | B11: (currency × unit) | D11: =Projections!D36 | E11: =Projections!E36 | F11: =Projections!F36 | G11: =Projections!G36 | H11: =Projections!H36
A12: Discount period | B12: years | D12: 1 | E12: 2 | F12: 3 | G12: 4 | H12: 5
A13: Discount factor | B13: x | D13: =1/(1+wacc_indep)^D12 | E13: =1/(1+wacc_indep)^E12 | F13: =1/(1+wacc_indep)^F12 | G13: =1/(1+wacc_indep)^G12 | H13: =1/(1+wacc_indep)^H12
A14: PV of FCFF | B14: (currency × unit) | D14: =D11*D13 | E14: =E11*E13 | F14: =F11*F13 | G14: =G11*G13 | H14: =H11*H13
A16: Terminal value
A17: Method | I17: =terminal_method
A18: Y5 FCFF | B18: (currency × unit) | I18: =Projections!H36
A19: Terminal value — Gordon Growth | B19: (currency × unit) | I19: =IFERROR(I18*(1+terminal_growth_rate)/(wacc_indep-terminal_growth_rate),0)
A20: Terminal value — Exit Multiple | B20: (currency × unit) | I20: =IF(EXACT(terminal_exit_multiple_type,"EV/EBITDA"),Projections!H15*terminal_exit_multiple_value,IF(EXACT(terminal_exit_multiple_type,"EV/Sales"),Projections!H8*terminal_exit_multiple_value,IF(EXACT(terminal_exit_multiple_type,"P/E"),Projections!H23*terminal_exit_multiple_value,0)))
A21: Selected terminal value | B21: (currency × unit) | I21: =IF(EXACT(terminal_method,"exit_multiple"),I20,I19)
A22: PV of terminal value | B22: (currency × unit) | I22: =I21*H13
A24: Enterprise Value
A25: Sum of PV of explicit-period FCFF | I25: =SUM(D14:H14)
A26: + PV of terminal value | I26: =I22
A27: Enterprise Value | I27: =I25+I26

Sheet Comps
A1: Comps — comparable companies cross-check
A2: Apply CoCo NTM trading multiples to target Y1 metrics. Implied EV from EV/Sales × Revenue and EV/EBITDA × EBITDA cross-check the DCF. P/E × Net Income gives implied Equity (bridge to EV via surplus/net debt).
A4: Multiple | B4: Target metric (Y1) | C4: CoCo Q1 | D4: CoCo Median | E4: CoCo Q3 | F4: Implied (low) | G4: Implied (mid) | H4: Implied (high)
A6: NTM-based multiples (applied to Y1)
A7: EV/Sales NTM | B7: =Projections!D8 | C7: ='CoCo Multiples'!F41 | D7: ='CoCo Multiples'!F39 | E7: ='CoCo Multiples'!F38 | F7: =IFERROR(B7*C7,"n/a") | G7: =IFERROR(B7*D7,"n/a") | H7: =IFERROR(B7*E7,"n/a")
A8: EV/EBITDA NTM | B8: =Projections!D15 | C8: ='CoCo Multiples'!H41 | D8: ='CoCo Multiples'!H39 | E8: ='CoCo Multiples'!H38 | F8: =IFERROR(B8*C8,"n/a") | G8: =IFERROR(B8*D8,"n/a") | H8: =IFERROR(B8*E8,"n/a")
A9: P/E NTM (gives Equity) | B9: =Projections!D23 | C9: ='CoCo Multiples'!J41 | D9: ='CoCo Multiples'!J39 | E9: ='CoCo Multiples'!J38 | F9: =IFERROR(B9*C9,"n/a") | G9: =IFERROR(B9*D9,"n/a") | H9: =IFERROR(B9*E9,"n/a")
A11: LTM-based multiples (not wired in v1 — needs Historical FS link)
A12: TODO: when Historical FS sheet is built, wire LTM target metrics here and apply 'CoCo Multiples'!E/G/I (LTM) columns.
A14: Cross-check summary — DCF vs CoCo-implied
A15: DCF EV — Per Management | B15: ='DCF'!I27
A16: DCF EV — Independent | B16: ='DCF (Independent)'!I27
A17: CoCo-implied EV — EV/Sales NTM (Median) | B17: =G7
A18: CoCo-implied EV — EV/EBITDA NTM (Median) | B18: =G8
A19: CoCo-implied Equity — P/E NTM (Median) | B19: =G9
A20: CoCo-implied EV — P/E NTM (bridged from Equity) | B20: =G9-surplus_assets-non_operating_assets+IF(ISNUMBER(net_debt_override),net_debt_override,0)+minority_interests
A21: Mean of CoCo-implied EVs (Sales + EBITDA + P/E) | B21: =AVERAGE(B17,B18,B20)

Sheet Football Field
A1: Football Field — methodology range reconciliation
A2: Range chart input. DCF range comes from the two WACC scenarios. Comps range from CoCo Q1/Median/Q3. Precedent range from precedents_table (when populated). Apply football_field weights to compute weighted-average EV.
A4: Methodology | B4: Low | C4: Mid | D4: High | E4: Weight | F4: Weighted Mid | G4: Notes
A6: Methodology ranges (EV in currency × unit)
A7: DCF (across scenarios) | B7: =MIN('DCF'!I27,'DCF (Independent)'!I27) | C7: =AVERAGE('DCF'!I27,'DCF (Independent)'!I27) | D7: =MAX('DCF'!I27,'DCF (Independent)'!I27) | E7: =weight_dcf | F7: =C7*E7 | G7: Low = Per-Mgmt vs Indep min; High = max; Mid = average
A8: Comps — EV/Sales NTM | B8: =Comps!F7 | C8: =Comps!G7 | D8: =Comps!H7 | G8: Reference; weighted via combined Comps row below
A9: Comps — EV/EBITDA NTM | B9: =Comps!F8 | C9: =Comps!G8 | D9: =Comps!H8 | G9: Reference
A10: Comps — P/E NTM (EV after bridge) | B10: =Comps!F9-surplus_assets-non_operating_assets+IF(ISNUMBER(net_debt_override),net_debt_override,0)+minority_interests | C10: =Comps!G9-surplus_assets-non_operating_assets+IF(ISNUMBER(net_debt_override),net_debt_override,0)+minority_interests | D10: =Comps!H9-surplus_assets-non_operating_assets+IF(ISNUMBER(net_debt_override),net_debt_override,0)+minority_interests | G10: Reference; bridged from Equity
A11: Comps — combined (mean of 3 methodologies) | B11: =MIN(C8,C9,C10) | C11: =AVERAGE(C8,C9,C10) | D11: =MAX(C8,C9,C10) | E11: =weight_comps | F11: =C11*E11 | G11: Low/High across the 3 mids; Mid is mean
A12: Precedent transactions | B12: =IFERROR(MIN(IF(INDEX(precedents_table,0,1)=TRUE,INDEX(precedents_table,0,7)*Projections!D15,"")),0) | C12: =IFERROR(AVERAGEIFS(INDEX(precedents_table,0,7),INDEX(precedents_table,0,1),TRUE)*Projections!D15,0) | D12: =IFERROR(MAX(IF(INDEX(precedents_table,0,1)=TRUE,INDEX(precedents_table,0,7)*Projections!D15,"")),0) | E12: =weight_precedent | F12: =C12*E12 | G12: Mean EV/EBITDA × Y1 EBITDA across included precedents
A14: Weighted-average valuation
A15: Total weight applied | E15: =E7+E11+E12
A16: Weighted-average EV (calculated) | F16: =IFERROR((F7+F11+F12)/E15,0)
A17: Selected valuation (manual override)
A18: Selected low | B18: =selected_low
A19: Selected mid | C19: =selected_mid
A20: Selected high | D20: =selected_high

Sheet WACC
A1: WACC — discount rate build-up
A2: Two scenarios. Inputs (Rf, ERP, country premium) shared; beta / D/E / size / specific / Kd are scenario-specific. Calculated outputs (levered beta, Ke, after-tax Kd, WACC) cycle back to the Inputs sheet.
A4: Component | C4: Type | E4: Per Management | F4: Independent
A6: Cost of Equity (Ke)
A7: Effective tax rate | C7: % | E7: =IF(ISNUMBER(tax_effective_rate),tax_effective_rate,tax_rate_high) | F7: =IF(ISNUMBER(tax_effective_rate),tax_effective_rate,tax_rate_high)
A8: Unlevered beta | C8: x | E8: =unlevered_beta_per_mgmt | F8: =unlevered_beta_indep
A9: D/E ratio | C9: % | E9: =target_debt_to_equity_per_mgmt | F9: =target_debt_to_equity_indep
A10: Levered beta (calc) | C10: x | E10: =E8*(1+(1-E7)*E9) | F10: =F8*(1+(1-F7)*F9)
A11: Risk-free rate | C11: % | E11: =risk_free_rate | F11: =risk_free_rate
A12: Equity risk premium (ERP) | C12: % | E12: =equity_risk_premium | F12: =equity_risk_premium
A13: Country risk premium | C13: % | E13: =country_risk_premium | F13: =country_risk_premium
A14: Size premium | C14: % | E14: =size_premium_per_mgmt | F14: =size_premium_indep
A15: Specific risk premium | C15: % | E15: =specific_risk_premium_per_mgmt | F15: =specific_risk_premium_indep
A16: Cost of Equity (calc) | C16: % | E16: =E11+E10*E12+E13+E14+E15 | F16: =F11+F10*F12+F13+F14+F15
A18: Cost of Debt (Kd)
A19: Pre-tax cost of debt | C19: % | E19: =pretax_cost_of_debt_per_mgmt | F19: =pretax_cost_of_debt_indep
A20: After-tax cost of debt (calc) | C20: % | E20: =E19*(1-E7) | F20: =F19*(1-F7)
A22: Capital structure & WACC
A23: D/V (debt weight) | C23: % | E23: =target_debt_weight_per_mgmt | F23: =target_debt_weight_indep
A24: E/V (equity weight) | C24: % | E24: =target_equity_weight_per_mgmt | F24: =target_equity_weight_indep
A25: WACC (calc) | C25: % | E25: =E16*E24+E20*E23 | F25: =F16*F24+F20*F23

Sheet CoCo Selection
A1: CoCo Selection — comparable companies
A2: Mirror view of the comparable companies table on the Inputs sheet. Edit values on Inputs; this sheet refreshes automatically.
A4: Tier | B4: Include | C4: Company | D4: Ticker | E4: Business description | F4: Country | G4: Accounting standard | H4: Market cap (USD mm) | I4: D/E ratio | J4: Raw levered beta | K4: Effective tax rate | L4: Unlevered beta (calculated)
A6: =Inputs!A127 | B6: =Inputs!B127 | C6: =Inputs!C127 | D6: =Inputs!D127 | E6: =Inputs!E127 | F6: =Inputs!F127 | G6: =Inputs!G127 | H6: =Inputs!H127 | ... K6: =Inputs!K127 | L6: =IFERROR(Inputs!J127/(1+(1-Inputs!K127)*Inputs!I127),"")
A7: =Inputs!A128 | B7: =Inputs!B128 | C7: =Inputs!C128 | D7: =Inputs!D128 | E7: =Inputs!E128 | F7: =Inputs!F128 | G7: =Inputs!G128 | H7: =Inputs!H128 | ... K7: =Inputs!K128 | L7: =IFERROR(Inputs!J128/(1+(1-Inputs!K128)*Inputs!I128),"")
A8: =Inputs!A129 | B8: =Inputs!B129 | C8: =Inputs!C129 | D8: =Inputs!D129 | E8: =Inputs!E129 | F8: =Inputs!F129 | G8: =Inputs!G129 | H8: =Inputs!H129 | ... K8: =Inputs!K129 | L8: =IFERROR(Inputs!J129/(1+(1-Inputs!K129)*Inputs!I129),"")
A9: =Inputs!A130 | B9: =Inputs!B130 | C9: =Inputs!C130 | D9: =Inputs!D130 | E9: =Inputs!E130 | F9: =Inputs!F130 | G9: =Inputs!G130 | H9: =Inputs!H130 | ... K9: =Inputs!K130 | L9: =IFERROR(Inputs!J130/(1+(1-Inputs!K130)*Inputs!I130),"")
A10: =Inputs!A131 | B10: =Inputs!B131 | C10: =Inputs!C131 | D10: =Inputs!D131 | E10: =Inputs!E131 | F10: =Inputs!F131 | G10: =Inputs!G131 | H10: =Inputs!H131 | ... K10: =Inputs!K131 | L10: =IFERROR(Inputs!J131/(1+(1-Inputs!K131)*Inputs!I131),"")
A11: =Inputs!A132 | B11: =Inputs!B132 | C11: =Inputs!C132 | D11: =Inputs!D132 | E11: =Inputs!E132 | F11: =Inputs!F132 | G11: =Inputs!G132 | H11: =Inputs!H132 | ... K11: =Inputs!K132 | L11: =IFERROR(Inputs!J132/(1+(1-Inputs!K132)*Inputs!I132),"")
A12: =Inputs!A133 | B12: =Inputs!B133 | C12: =Inputs!C133 | D12: =Inputs!D133 | E12: =Inputs!E133 | F12: =Inputs!F133 | G12: =Inputs!G133 | H12: =Inputs!H133 | ... K12: =Inputs!K133 | L12: =IFERROR(Inputs!J133/(1+(1-Inputs!K133)*Inputs!I133),"")
A13: =Inputs!A134 | B13: =Inputs!B134 | C13: =Inputs!C134 | D13: =Inputs!D134 | E13: =Inputs!E134 | F13: =Inputs!F134 | G13: =Inputs!G134 | H13: =Inputs!H134 | ... K13: =Inputs!K134 | L13: =IFERROR(Inputs!J134/(1+(1-Inputs!K134)*Inputs!I134),"")
A14: =Inputs!A135 | B14: =Inputs!B135 | C14: =Inputs!C135 | D14: =Inputs!D135 | E14: =Inputs!E135 | F14: =Inputs!F135 | G14: =Inputs!G135 | H14: =Inputs!H135 | ... K14: =Inputs!K135 | L14: =IFERROR(Inputs!J135/(1+(1-Inputs!K135)*Inputs!I135),"")
A15: =Inputs!A136 | B15: =Inputs!B136 | C15: =Inputs!C136 | D15: =Inputs!D136 | E15: =Inputs!E136 | F15: =Inputs!F136 | G15: =Inputs!G136 | H15: =Inputs!H136 | ... K15: =Inputs!K136 | L15: =IFERROR(Inputs!J136/(1+(1-Inputs!K136)*Inputs!I136),"")
A16: =Inputs!A137 | B16: =Inputs!B137 | C16: =Inputs!C137 | D16: =Inputs!D137 | E16: =Inputs!E137 | F16: =Inputs!F137 | G16: =Inputs!G137 | H16: =Inputs!H137 | ... K16: =Inputs!K137 | L16: =IFERROR(Inputs!J137/(1+(1-Inputs!K137)*Inputs!I137),"")
A17: =Inputs!A138 | B17: =Inputs!B138 | C17: =Inputs!C138 | D17: =Inputs!D138 | E17: =Inputs!E138 | F17: =Inputs!F138 | G17: =Inputs!G138 | H17: =Inputs!H138 | ... K17: =Inputs!K138 | L17: =IFERROR(Inputs!J138/(1+(1-Inputs!K138)*Inputs!I138),"")
... A35: =Inputs!A156 | B35: =Inputs!B156 | C35: =Inputs!C156 | D35: =Inputs!D156 | E35: =Inputs!E156 | F35: =Inputs!F156 | G35: =Inputs!G156 | H35: =Inputs!H156 | ... K35: =Inputs!K156 | L35: =IFERROR(Inputs!J156/(1+(1-Inputs!K156)*Inputs!I156),"")

Sheet CoCo Multiples
A1: CoCo Multiples — trading multiples per comparable
A2: Per-CoCo metric values (Capital IQ / Bloomberg). Cols A-D mirror Inputs. Cols E onward are manual data entry. Summary stats compute below.
A4: Tier | B4: Include | C4: Company | D4: Ticker | E4: EV/Sales LTM | F4: EV/Sales NTM | G4: EV/EBITDA LTM | H4: EV/EBITDA NTM | I4: P/E LTM | J4: P/E NTM
A6: =Inputs!A127 | B6: =Inputs!B127 | C6: =Inputs!C127 | D6: =Inputs!D127
A7: =Inputs!A128 | B7: =Inputs!B128 | C7: =Inputs!C128 | D7: =Inputs!D128
A8: =Inputs!A129 | B8: =Inputs!B129 | C8: =Inputs!C129 | D8: =Inputs!D129
A9: =Inputs!A130 | B9: =Inputs!B130 | C9: =Inputs!C130 | D9: =Inputs!D130
A10: =Inputs!A131 | B10: =Inputs!B131 | C10: =Inputs!C131 | D10: =Inputs!D131
A11: =Inputs!A132 | B11: =Inputs!B132 | C11: =Inputs!C132 | D11: =Inputs!D132
A12: =Inputs!A133 | B12: =Inputs!B133 | C12: =Inputs!C133 | D12: =Inputs!D133
A13: =Inputs!A134 | B13: =Inputs!B134 | C13: =Inputs!C134 | D13: =Inputs!D134
A14: =Inputs!A135 | B14: =Inputs!B135 | C14: =Inputs!C135 | D14: =Inputs!D135
A15: =Inputs!A136 | B15: =Inputs!B136 | C15: =Inputs!C136 | D15: =Inputs!D136
A16: =Inputs!A137 | B16: =Inputs!B137 | C16: =Inputs!C137 | D16: =Inputs!D137
A17: =Inputs!A138 | B17: =Inputs!B138 | C17: =Inputs!C138 | D17: =Inputs!D138
... A35: =Inputs!A156 | B35: =Inputs!B156 | C35: =Inputs!C156 | D35: =Inputs!D156
D37: Maximum | E37: =IFERROR(MAX(E6:E35),"n/a") | F37: =IFERROR(MAX(F6:F35),"n/a") | G37: =IFERROR(MAX(G6:G35),"n/a") | H37: =IFERROR(MAX(H6:H35),"n/a") | I37: =IFERROR(MAX(I6:I35),"n/a") | J37: =IFERROR(MAX(J6:J35),"n/a")
D38: Q3 (75%) | E38: =IFERROR(QUARTILE(E6:E35,3),"n/a") | F38: =IFERROR(QUARTILE(F6:F35,3),"n/a") | G38: =IFERROR(QUARTILE(G6:G35,3),"n/a") | H38: =IFERROR(QUARTILE(H6:H35,3),"n/a") | I38: =IFERROR(QUARTILE(I6:I35,3),"n/a") | J38: =IFERROR(QUARTILE(J6:J35,3),"n/a")
D39: Median | E39: =IFERROR(MEDIAN(E6:E35),"n/a") | F39: =IFERROR(MEDIAN(F6:F35),"n/a") | G39: =IFERROR(MEDIAN(G6:G35),"n/a") | H39: =IFERROR(MEDIAN(H6:H35),"n/a") | I39: =IFERROR(MEDIAN(I6:I35),"n/a") | J39: =IFERROR(MEDIAN(J6:J35),"n/a")
D40: Mean | E40: =IFERROR(AVERAGE(E6:E35),"n/a") | F40: =IFERROR(AVERAGE(F6:F35),"n/a") | G40: =IFERROR(AVERAGE(G6:G35),"n/a") | H40: =IFERROR(AVERAGE(H6:H35),"n/a") | I40: =IFERROR(AVERAGE(I6:I35),"n/a") | J40: =IFERROR(AVERAGE(J6:J35),"n/a")
D41: Q1 (25%) | E41: =IFERROR(QUARTILE(E6:E35,1),"n/a") | F41: =IFERROR(QUARTILE(F6:F35,1),"n/a") | G41: =IFERROR(QUARTILE(G6:G35,1),"n/a") | H41: =IFERROR(QUARTILE(H6:H35,1),"n/a") | I41: =IFERROR(QUARTILE(I6:I35,1),"n/a") | J41: =IFERROR(QUARTILE(J6:J35,1),"n/a")
D42: Minimum | E42: =IFERROR(MIN(E6:E35),"n/a") | F42: =IFERROR(MIN(F6:F35),"n/a") | G42: =IFERROR(MIN(G6:G35),"n/a") | H42: =IFERROR(MIN(H6:H35),"n/a") | I42: =IFERROR(MIN(I6:I35),"n/a") | J42: =IFERROR(MIN(J6:J35),"n/a")
D44: Tier-filtered (include=TRUE)
D45: Tier 1 mean | E45: =IFERROR(AVERAGEIFS(E6:E35,$A$6:$A$35,1,$B$6:$B$35,TRUE),"n/a") | F45: =IFERROR(AVERAGEIFS(F6:F35,$A$6:$A$35,1,$B$6:$B$35,TRUE),"n/a") | G45: =IFERROR(AVERAGEIFS(G6:G35,$A$6:$A$35,1,$B$6:$B$35,TRUE),"n/a") | H45: =IFERROR(AVERAGEIFS(H6:H35,$A$6:$A$35,1,$B$6:$B$35,TRUE),"n/a") | I45: =IFERROR(AVERAGEIFS(I6:I35,$A$6:$A$35,1,$B$6:$B$35,TRUE),"n/a") | J45: =IFERROR(AVERAGEIFS(J6:J35,$A$6:$A$35,1,$B$6:$B$35,TRUE),"n/a")
D46: Tier 2 mean | E46: =IFERROR(AVERAGEIFS(E6:E35,$A$6:$A$35,2,$B$6:$B$35,TRUE),"n/a") | F46: =IFERROR(AVERAGEIFS(F6:F35,$A$6:$A$35,2,$B$6:$B$35,TRUE),"n/a") | G46: =IFERROR(AVERAGEIFS(G6:G35,$A$6:$A$35,2,$B$6:$B$35,TRUE),"n/a") | H46: =IFERROR(AVERAGEIFS(H6:H35,$A$6:$A$35,2,$B$6:$B$35,TRUE),"n/a") | I46: =IFERROR(AVERAGEIFS(I6:I35,$A$6:$A$35,2,$B$6:$B$35,TRUE),"n/a") | J46: =IFERROR(AVERAGEIFS(J6:J35,$A$6:$A$35,2,$B$6:$B$35,TRUE),"n/a")
D47: Tier 3 mean | E47: =IFERROR(AVERAGEIFS(E6:E35,$A$6:$A$35,3,$B$6:$B$35,TRUE),"n/a") | F47: =IFERROR(AVERAGEIFS(F6:F35,$A$6:$A$35,3,$B$6:$B$35,TRUE),"n/a") | G47: =IFERROR(AVERAGEIFS(G6:G35,$A$6:$A$35,3,$B$6:$B$35,TRUE),"n/a") | H47: =IFERROR(AVERAGEIFS(H6:H35,$A$6:$A$35,3,$B$6:$B$35,TRUE),"n/a") | I47: =IFERROR(AVERAGEIFS(I6:I35,$A$6:$A$35,3,$B$6:$B$35,TRUE),"n/a") | J47: =IFERROR(AVERAGEIFS(J6:J35,$A$6:$A$35,3,$B$6:$B$35,TRUE),"n/a")

Sheet CoCo Margins
A1: CoCo Margins — profitability per comparable
A2: Per-CoCo metric values (Capital IQ / Bloomberg). Cols A-D mirror Inputs. Cols E onward are manual data entry. Summary stats compute below.
A4: Tier | B4: Include | C4: Company | D4: Ticker | E4: Gross margin | F4: EBIT margin | G4: Net margin
A6: =Inputs!A127 | B6: =Inputs!B127 | C6: =Inputs!C127 | D6: =Inputs!D127
A7: =Inputs!A128 | B7: =Inputs!B128 | C7: =Inputs!C128 | D7: =Inputs!D128
A8: =Inputs!A129 | B8: =Inputs!B129 | C8: =Inputs!C129 | D8: =Inputs!D129
A9: =Inputs!A130 | B9: =Inputs!B130 | C9: =Inputs!C130 | D9: =Inputs!D130
A10: =Inputs!A131 | B10: =Inputs!B131 | C10: =Inputs!C131 | D10: =Inputs!D131
A11: =Inputs!A132 | B11: =Inputs!B132 | C11: =Inputs!C132 | D11: =Inputs!D132
A12: =Inputs!A133 | B12: =Inputs!B133 | C12: =Inputs!C133 | D12: =Inputs!D133
A13: =Inputs!A134 | B13: =Inputs!B134 | C13: =Inputs!C134 | D13: =Inputs!D134
A14: =Inputs!A135 | B14: =Inputs!B135 | C14: =Inputs!C135 | D14: =Inputs!D135
A15: =Inputs!A136 | B15: =Inputs!B136 | C15: =Inputs!C136 | D15: =Inputs!D136
A16: =Inputs!A137 | B16: =Inputs!B137 | C16: =Inputs!C137 | D16: =Inputs!D137
A17: =Inputs!A138 | B17: =Inputs!B138 | C17: =Inputs!C138 | D17: =Inputs!D138
... A35: =Inputs!A156 | B35: =Inputs!B156 | C35: =Inputs!C156 | D35: =Inputs!D156
D37: Maximum | E37: =IFERROR(MAX(E6:E35),"n/a") | F37: =IFERROR(MAX(F6:F35),"n/a") | G37: =IFERROR(MAX(G6:G35),"n/a")
D38: Q3 (75%) | E38: =IFERROR(QUARTILE(E6:E35,3),"n/a") | F38: =IFERROR(QUARTILE(F6:F35,3),"n/a") | G38: =IFERROR(QUARTILE(G6:G35,3),"n/a")
D39: Median | E39: =IFERROR(MEDIAN(E6:E35),"n/a") | F39: =IFERROR(MEDIAN(F6:F35),"n/a") | G39: =IFERROR(MEDIAN(G6:G35),"n/a")
D40: Mean | E40: =IFERROR(AVERAGE(E6:E35),"n/a") | F40: =IFERROR(AVERAGE(F6:F35),"n/a") | G40: =IFERROR(AVERAGE(G6:G35),"n/a")
D41: Q1 (25%) | E41: =IFERROR(QUARTILE(E6:E35,1),"n/a") | F41: =IFERROR(QUARTILE(F6:F35,1),"n/a") | G41: =IFERROR(QUARTILE(G6:G35,1),"n/a")
D42: Minimum | E42: =IFERROR(MIN(E6:E35),"n/a") | F42: =IFERROR(MIN(F6:F35),"n/a") | G42: =IFERROR(MIN(G6:G35),"n/a")
D44: Tier-filtered (include=TRUE)
D45: Tier 1 mean | E45: =IFERROR(AVERAGEIFS(E6:E35,$A$6:$A$35,1,$B$6:$B$35,TRUE),"n/a") | F45: =IFERROR(AVERAGEIFS(F6:F35,$A$6:$A$35,1,$B$6:$B$35,TRUE),"n/a") | G45: =IFERROR(AVERAGEIFS(G6:G35,$A$6:$A$35,1,$B$6:$B$35,TRUE),"n/a")
D46: Tier 2 mean | E46: =IFERROR(AVERAGEIFS(E6:E35,$A$6:$A$35,2,$B$6:$B$35,TRUE),"n/a") | F46: =IFERROR(AVERAGEIFS(F6:F35,$A$6:$A$35,2,$B$6:$B$35,TRUE),"n/a") | G46: =IFERROR(AVERAGEIFS(G6:G35,$A$6:$A$35,2,$B$6:$B$35,TRUE),"n/a")
D47: Tier 3 mean | E47: =IFERROR(AVERAGEIFS(E6:E35,$A$6:$A$35,3,$B$6:$B$35,TRUE),"n/a") | F47: =IFERROR(AVERAGEIFS(F6:F35,$A$6:$A$35,3,$B$6:$B$35,TRUE),"n/a") | G47: =IFERROR(AVERAGEIFS(G6:G35,$A$6:$A$35,3,$B$6:$B$35,TRUE),"n/a")

Sheet CoCo Ratios
A1: CoCo Ratios — financial ratios per comparable
A2: Per-CoCo metric values (Capital IQ / Bloomberg). Cols A-D mirror Inputs. Cols E onward are manual data entry. Summary stats compute below.
A4: Tier | B4: Include | C4: Company | D4: Ticker | E4: ROE | F4: ROA | G4: D/E | H4: Current ratio
A6: =Inputs!A127 | B6: =Inputs!B127 | C6: =Inputs!C127 | D6: =Inputs!D127
A7: =Inputs!A128 | B7: =Inputs!B128 | C7: =Inputs!C128 | D7: =Inputs!D128
A8: =Inputs!A129 | B8: =Inputs!B129 | C8: =Inputs!C129 | D8: =Inputs!D129
A9: =Inputs!A130 | B9: =Inputs!B130 | C9: =Inputs!C130 | D9: =Inputs!D130
A10: =Inputs!A131 | B10: =Inputs!B131 | C10: =Inputs!C131 | D10: =Inputs!D131
A11: =Inputs!A132 | B11: =Inputs!B132 | C11: =Inputs!C132 | D11: =Inputs!D132
A12: =Inputs!A133 | B12: =Inputs!B133 | C12: =Inputs!C133 | D12: =Inputs!D133
A13: =Inputs!A134 | B13: =Inputs!B134 | C13: =Inputs!C134 | D13: =Inputs!D134
A14: =Inputs!A135 | B14: =Inputs!B135 | C14: =Inputs!C135 | D14: =Inputs!D135
A15: =Inputs!A136 | B15: =Inputs!B136 | C15: =Inputs!C136 | D15: =Inputs!D136
A16: =Inputs!A137 | B16: =Inputs!B137 | C16: =Inputs!C137 | D16: =Inputs!D137
A17: =Inputs!A138 | B17: =Inputs!B138 | C17: =Inputs!C138 | D17: =Inputs!D138
... A35: =Inputs!A156 | B35: =Inputs!B156 | C35: =Inputs!C156 | D35: =Inputs!D156
D37: Maximum | E37: =IFERROR(MAX(E6:E35),"n/a") | F37: =IFERROR(MAX(F6:F35),"n/a") | G37: =IFERROR(MAX(G6:G35),"n/a") | H37: =IFERROR(MAX(H6:H35),"n/a")
D38: Q3 (75%) | E38: =IFERROR(QUARTILE(E6:E35,3),"n/a") | F38: =IFERROR(QUARTILE(F6:F35,3),"n/a") | G38: =IFERROR(QUARTILE(G6:G35,3),"n/a") | H38: =IFERROR(QUARTILE(H6:H35,3),"n/a")
D39: Median | E39: =IFERROR(MEDIAN(E6:E35),"n/a") | F39: =IFERROR(MEDIAN(F6:F35),"n/a") | G39: =IFERROR(MEDIAN(G6:G35),"n/a") | H39: =IFERROR(MEDIAN(H6:H35),"n/a")
D40: Mean | E40: =IFERROR(AVERAGE(E6:E35),"n/a") | F40: =IFERROR(AVERAGE(F6:F35),"n/a") | G40: =IFERROR(AVERAGE(G6:G35),"n/a") | H40: =IFERROR(AVERAGE(H6:H35),"n/a")
D41: Q1 (25%) | E41: =IFERROR(QUARTILE(E6:E35,1),"n/a") | F41: =IFERROR(QUARTILE(F6:F35,1),"n/a") | G41: =IFERROR(QUARTILE(G6:G35,1),"n/a") | H41: =IFERROR(QUARTILE(H6:H35,1),"n/a")
D42: Minimum | E42: =IFERROR(MIN(E6:E35),"n/a") | F42: =IFERROR(MIN(F6:F35),"n/a") | G42: =IFERROR(MIN(G6:G35),"n/a") | H42: =IFERROR(MIN(H6:H35),"n/a")
D44: Tier-filtered (include=TRUE)
D45: Tier 1 mean | E45: =IFERROR(AVERAGEIFS(E6:E35,$A$6:$A$35,1,$B$6:$B$35,TRUE),"n/a") | F45: =IFERROR(AVERAGEIFS(F6:F35,$A$6:$A$35,1,$B$6:$B$35,TRUE),"n/a") | G45: =IFERROR(AVERAGEIFS(G6:G35,$A$6:$A$35,1,$B$6:$B$35,TRUE),"n/a") | H45: =IFERROR(AVERAGEIFS(H6:H35,$A$6:$A$35,1,$B$6:$B$35,TRUE),"n/a")
D46: Tier 2 mean | E46: =IFERROR(AVERAGEIFS(E6:E35,$A$6:$A$35,2,$B$6:$B$35,TRUE),"n/a") | F46: =IFERROR(AVERAGEIFS(F6:F35,$A$6:$A$35,2,$B$6:$B$35,TRUE),"n/a") | G46: =IFERROR(AVERAGEIFS(G6:G35,$A$6:$A$35,2,$B$6:$B$35,TRUE),"n/a") | H46: =IFERROR(AVERAGEIFS(H6:H35,$A$6:$A$35,2,$B$6:$B$35,TRUE),"n/a")
D47: Tier 3 mean | E47: =IFERROR(AVERAGEIFS(E6:E35,$A$6:$A$35,3,$B$6:$B$35,TRUE),"n/a") | F47: =IFERROR(AVERAGEIFS(F6:F35,$A$6:$A$35,3,$B$6:$B$35,TRUE),"n/a") | G47: =IFERROR(AVERAGEIFS(G6:G35,$A$6:$A$35,3,$B$6:$B$35,TRUE),"n/a") | H47: =IFERROR(AVERAGEIFS(H6:H35,$A$6:$A$35,3,$B$6:$B$35,TRUE),"n/a")

Sheet CIQ Data Timeline
A1: CIQ Data Timeline
A2: Capital IQ data import audit trail FY-4 to FY-1
A4: TODO — formulas to be added in subsequent build pass.

Sheet Country ERP
A1: Country ERP — equity risk premium reference
A2: Reference table for country risk premium (CRP) and total ERP. Approximates Damodaran's mid-2025 published figures. **Refresh annually** from pages.stern.nyu.edu/~adamodar/ before any binding valuation. Look up your jurisdiction by ISO2 in column B, take ERP from column D and CRP from column E.
A4: Country | B4: ISO2 | C4: Moody's rating | D4: ERP | E4: Country Risk Premium | F4: Corporate Tax Rate | G4: Region
A5: United States | B5: US | C5: Aaa | D5: 0.0457 | E5: 0 | F5: 0.21 | G5: North America
A6: United Kingdom | B6: GB | C6: Aa3 | D6: 0.0507 | E6: 0.005 | F6: 0.25 | G6: Western Europe
A7: Germany | B7: DE | C7: Aaa | D7: 0.0457 | E7: 0 | F7: 0.298 | G7: Western Europe
A8: France | B8: FR | C8: Aa3 | D8: 0.0507 | E8: 0.005 | F8: 0.258 | G8: Western Europe
A9: Switzerland | B9: CH | C9: Aaa | D9: 0.0457 | E9: 0 | F9: 0.144 | G9: Western Europe
A10: Netherlands | B10: NL | C10: Aaa | D10: 0.0457 | E10: 0 | F10: 0.258 | G10: Western Europe
A11: Australia | B11: AU | C11: Aaa | D11: 0.0457 | E11: 0 | F11: 0.3 | G11: Australia & NZ
A12: New Zealand | B12: NZ | C12: Aaa | D12: 0.0457 | E12: 0 | F12: 0.28 | G12: Australia & NZ
A13: Canada | B13: CA | C13: Aaa | D13: 0.0457 | E13: 0 | F13: 0.265 | G13: North America
A14: Japan | B14: JP | C14: A1 | D14: 0.0567 | E14: 0.011 | F14: 0.305 | G14: Asia
A15: South Korea | B15: KR | C15: Aa2 | D15: 0.0489 | E15: 0.0032 | F15: 0.275 | G15: Asia
A16: Taiwan | B16: TW | C16: Aa3 | D16: 0.0507 | E16: 0.005 | F16: 0.2 | G16: Asia
... A35: Israel | B35: IL | C35: A2 | D35: 0.0596 | E35: 0.0139 | F35: 0.23 | G35: Middle East
A37: Source: Aswath Damodaran (NYU Stern) country ERP methodology. Mature-market ERP baseline ≈ 4.57%; CRP is the country-specific premium added for non-AAA jurisdictions. Numbers above are 2024-2025 approximations — REFRESH from the live source before binding work.

Sheet Industry Averages
A1: Industry Averages — Damodaran US-industry reference (mid-2025)
A2: Reference table for unlevered beta, margin, capex-intensity, and EV/EBITDA NTM by industry. Approximates Damodaran's mid-2025 published US figures. **Refresh annually** from pages.stern.nyu.edu/~adamodar/ before binding work. For Asia-Pac targets, betas tend to run ~10-15% higher than the US baseline.
A4: Industry | B4: n firms | C4: Unlevered β | D4: Gross margin | E4: EBITDA margin | F4: Operating margin | G4: Capex / Revenue | H4: D&A / Revenue | I4: EV/EBITDA NTM
A5: Advertising | B5: 58 | C5: 0.97 | D5: 0.4 | E5: 0.16 | F5: 0.1 | G5: 0.018 | H5: 0.024 | I5: 14
A6: Aerospace/Defense | B6: 71 | C6: 0.92 | D6: 0.27 | E6: 0.18 | F6: 0.12 | G6: 0.03 | H6: 0.03 | I6: 16.5
A7: Auto & Truck (manufacturers) | B7: 44 | C7: 0.95 | D7: 0.18 | E7: 0.12 | F7: 0.07 | G7: 0.045 | H7: 0.04 | I7: 9.5
A8: Bank (Money Center) | B8: 17 | C8: 0.78 | D8: 0.55 | E8: 0.4 | F8: 0.35 | G8: 0.005 | H8: 0.01 | I8: 8.5
A9: Beverage (Alcoholic) | B9: 27 | C9: 0.62 | D9: 0.48 | E9: 0.27 | F9: 0.22 | G9: 0.04 | H9: 0.03 | I9: 14
A10: Beverage (Soft) | B10: 29 | C10: 0.71 | D10: 0.55 | E10: 0.28 | F10: 0.22 | G10: 0.045 | H10: 0.03 | I10: 16
A11: Biotechnology | B11: 532 | C11: 1.18 | D11: 0.6 | E11: -0.1 | F11: -0.3 | G11: 0.02 | H11: 0.03 | I11: 12
A12: Broadcasting | B12: 21 | C12: 0.95 | D12: 0.42 | E12: 0.32 | F12: 0.22 | G12: 0.02 | H12: 0.06 | I12: 8.5
A13: Building Materials | B13: 31 | C13: 1.08 | D13: 0.3 | E13: 0.18 | F13: 0.13 | G13: 0.04 | H13: 0.04 | I13: 9
A14: Business & Consumer Services | B14: 168 | C14: 1.1 | D14: 0.45 | E14: 0.18 | F14: 0.12 | G14: 0.025 | H14: 0.035 | I14: 13
A15: Cable TV | B15: 10 | C15: 0.85 | D15: 0.55 | E15: 0.36 | F15: 0.2 | G15: 0.13 | H15: 0.14 | I15: 7
A16: Chemical (Diversified) | B16: 23 | C16: 1.04 | D16: 0.22 | E16: 0.16 | F16: 0.12 | G16: 0.04 | H16: 0.03 | I16: 9.5
... A84: Utility (Water) | B84: 15 | C84: 0.6 | D84: 0.42 | E84: 0.45 | F84: 0.3 | G84: 0.18 | H84: 0.15 | I84: 14
A86: Source: Aswath Damodaran (NYU Stern) US-industry data, mid-2025 approximation. Use unlevered β as starting point; relever to target capital structure on the WACC sheet. EV/EBITDA NTM ranges are observed market trading bands — apply with judgment.

Sheet Adjustments
A1: Adjustments — EV → Equity bridge
A2: Applies surplus assets, net debt, minority interests, then DLOM and DLOC, to derive Fair Value of the client's equity interest. Both scenarios computed side by side.
A4: Item | C4: Per Management | D4: Independent | E4: Notes
A6: EV → Equity bridge
A7: Enterprise Value (from DCF) | C7: ='DCF'!I27 | D7: ='DCF (Independent)'!I27
A8: + Surplus assets | C8: =surplus_assets | D8: =surplus_assets
A9: + Non-operating assets | C9: =non_operating_assets | D9: =non_operating_assets
A10: − Net debt | C10: =-IF(ISNUMBER(net_debt_override),net_debt_override,0) | D10: =-IF(ISNUMBER(net_debt_override),net_debt_override,0)
A11: − Minority interests | C11: =-minority_interests | D11: =-minority_interests
A12: Equity value (pre-discounts) | C12: =C7+C8+C9+C10+C11 | D12: =D7+D8+D9+D10+D11
A14: Marketability & control discounts
A15: DLOM rate | C15: =dlom_pct | D15: =dlom_pct
A16: Less: DLOM | C16: =-C12*C15 | D16: =-D12*D15
A17: Equity value after DLOM | C17: =C12+C16 | D17: =D12+D16
A18: DLOC rate | C18: =dloc_pct | D18: =dloc_pct
A19: Less: DLOC | C19: =-C17*C18 | D19: =-D17*D18
A20: Equity value after DLOM and DLOC | C20: =C17+C19 | D20: =D17+D19
A22: Client's equity interest
A23: Equity interest held by client | C23: =equity_interest_pct | D23: =equity_interest_pct
A24: Fair value of client's interest | C24: =C20*C23 | D24: =D20*D23

Sheet Sensitivity
A1: Sensitivity — WACC × Terminal growth rate
A2: Each cell recomputes EV = Σ FCFF_y / (1+WACC)^y + FCFF_y5 × (1+g) / (WACC−g) / (1+WACC)^5. Step sizes from sens_wacc_step / sens_terminal_g_step on Inputs. Base case is current wacc_per_mgmt × terminal_growth_rate.
A4: Sensitivity grid: rows = WACC; columns = Terminal growth rate
B6: WACC ↓ / g → | C6: =terminal_growth_rate+(-3)*sens_terminal_g_step | D6: =terminal_growth_rate+(-2)*sens_terminal_g_step | E6: =terminal_growth_rate+(-1)*sens_terminal_g_step | F6: =terminal_growth_rate+(0)*sens_terminal_g_step | G6: =terminal_growth_rate+(1)*sens_terminal_g_step | H6: =terminal_growth_rate+(2)*sens_terminal_g_step | I6: =terminal_growth_rate+(3)*sens_terminal_g_step
B7: =wacc_per_mgmt+(-3)*sens_wacc_step | C7: =IFERROR(Projections!D36/(1+$B$7)^1+Projections!E36/(1+$B$7)^2+Projections!F36/(1+$B$7)^3+Projections!G36/(1+$B$7)^4+Projections!H36/(1+$B$7)^5+Projections!H36*(1+C$6)/($B$7-C$6)/(1+$B$7)^5,"err") | D7: =IFERROR(Projections!D36/(1+$B$7)^1+Projections!E36/(1+$B$7)^2+Projections!F36/(1+$B$7)^3+Projections!G36/(1+$B$7)^4+Projections!H36/(1+$B$7)^5+Projections!H36*(1+D$6)/($B$7-D$6)/(1+$B$7)^5,"err") | E7: =IFERROR(Projections!D36/(1+$B$7)^1+Projections!E36/(1+$B$7)^2+Projections!F36/(1+$B$7)^3+Projections!G36/(1+$B$7)^4+Projections!H36/(1+$B$7)^5+Projections!H36*(1+E$6)/($B$7-E$6)/(1+$B$7)^5,"err") | F7: =IFERROR(Projections!D36/(1+$B$7)^1+Projections!E36/(1+$B$7)^2+Projections!F36/(1+$B$7)^3+Projections!G36/(1+$B$7)^4+Projections!H36/(1+$B$7)^5+Projections!H36*(1+F$6)/($B$7-F$6)/(1+$B$7)^5,"err") | G7: =IFERROR(Projections!D36/(1+$B$7)^1+Projections!E36/(1+$B$7)^2+Projections!F36/(1+$B$7)^3+Projections!G36/(1+$B$7)^4+Projections!H36/(1+$B$7)^5+Projections!H36*(1+G$6)/($B$7-G$6)/(1+$B$7)^5,"err") | H7: =IFERROR(Projections!D36/(1+$B$7)^1+Projections!E36/(1+$B$7)^2+Projections!F36/(1+$B$7)^3+Projections!G36/(1+$B$7)^4+Projections!H36/(1+$B$7)^5+Projections!H36*(1+H$6)/($B$7-H$6)/(1+$B$7)^5,"err") | I7: =IFERROR(Projections!D36/(1+$B$7)^1+Projections!E36/(1+$B$7)^2+Projections!F36/(1+$B$7)^3+Projections!G36/(1+$B$7)^4+Projections!H36/(1+$B$7)^5+Projections!H36*(1+I$6)/($B$7-I$6)/(1+$B$7)^5,"err")
B8: =wacc_per_mgmt+(-2)*sens_wacc_step | C8: =IFERROR(Projections!D36/(1+$B$8)^1+Projections!E36/(1+$B$8)^2+Projections!F36/(1+$B$8)^3+Projections!G36/(1+$B$8)^4+Projections!H36/(1+$B$8)^5+Projections!H36*(1+C$6)/($B$8-C$6)/(1+$B$8)^5,"err") | D8: =IFERROR(Projections!D36/(1+$B$8)^1+Projections!E36/(1+$B$8)^2+Projections!F36/(1+$B$8)^3+Projections!G36/(1+$B$8)^4+Projections!H36/(1+$B$8)^5+Projections!H36*(1+D$6)/($B$8-D$6)/(1+$B$8)^5,"err") | E8: =IFERROR(Projections!D36/(1+$B$8)^1+Projections!E36/(1+$B$8)^2+Projections!F36/(1+$B$8)^3+Projections!G36/(1+$B$8)^4+Projections!H36/(1+$B$8)^5+Projections!H36*(1+E$6)/($B$8-E$6)/(1+$B$8)^5,"err") | F8: =IFERROR(Projections!D36/(1+$B$8)^1+Projections!E36/(1+$B$8)^2+Projections!F36/(1+$B$8)^3+Projections!G36/(1+$B$8)^4+Projections!H36/(1+$B$8)^5+Projections!H36*(1+F$6)/($B$8-F$6)/(1+$B$8)^5,"err") | G8: =IFERROR(Projections!D36/(1+$B$8)^1+Projections!E36/(1+$B$8)^2+Projections!F36/(1+$B$8)^3+Projections!G36/(1+$B$8)^4+Projections!H36/(1+$B$8)^5+Projections!H36*(1+G$6)/($B$8-G$6)/(1+$B$8)^5,"err") | H8: =IFERROR(Projections!D36/(1+$B$8)^1+Projections!E36/(1+$B$8)^2+Projections!F36/(1+$B$8)^3+Projections!G36/(1+$B$8)^4+Projections!H36/(1+$B$8)^5+Projections!H36*(1+H$6)/($B$8-H$6)/(1+$B$8)^5,"err") | I8: =IFERROR(Projections!D36/(1+$B$8)^1+Projections!E36/(1+$B$8)^2+Projections!F36/(1+$B$8)^3+Projections!G36/(1+$B$8)^4+Projections!H36/(1+$B$8)^5+Projections!H36*(1+I$6)/($B$8-I$6)/(1+$B$8)^5,"err")
B9: =wacc_per_mgmt+(-1)*sens_wacc_step | C9: =IFERROR(Projections!D36/(1+$B$9)^1+Projections!E36/(1+$B$9)^2+Projections!F36/(1+$B$9)^3+Projections!G36/(1+$B$9)^4+Projections!H36/(1+$B$9)^5+Projections!H36*(1+C$6)/($B$9-C$6)/(1+$B$9)^5,"err") | D9: =IFERROR(Projections!D36/(1+$B$9)^1+Projections!E36/(1+$B$9)^2+Projections!F36/(1+$B$9)^3+Projections!G36/(1+$B$9)^4+Projections!H36/(1+$B$9)^5+Projections!H36*(1+D$6)/($B$9-D$6)/(1+$B$9)^5,"err") | E9: =IFERROR(Projections!D36/(1+$B$9)^1+Projections!E36/(1+$B$9)^2+Projections!F36/(1+$B$9)^3+Projections!G36/(1+$B$9)^4+Projections!H36/(1+$B$9)^5+Projections!H36*(1+E$6)/($B$9-E$6)/(1+$B$9)^5,"err") | F9: =IFERROR(Projections!D36/(1+$B$9)^1+Projections!E36/(1+$B$9)^2+Projections!F36/(1+$B$9)^3+Projections!G36/(1+$B$9)^4+Projections!H36/(1+$B$9)^5+Projections!H36*(1+F$6)/($B$9-F$6)/(1+$B$9)^5,"err") | G9: =IFERROR(Projections!D36/(1+$B$9)^1+Projections!E36/(1+$B$9)^2+Projections!F36/(1+$B$9)^3+Projections!G36/(1+$B$9)^4+Projections!H36/(1+$B$9)^5+Projections!H36*(1+G$6)/($B$9-G$6)/(1+$B$9)^5,"err") | H9: =IFERROR(Projections!D36/(1+$B$9)^1+Projections!E36/(1+$B$9)^2+Projections!F36/(1+$B$9)^3+Projections!G36/(1+$B$9)^4+Projections!H36/(1+$B$9)^5+Projections!H36*(1+H$6)/($B$9-H$6)/(1+$B$9)^5,"err") | I9: =IFERROR(Projections!D36/(1+$B$9)^1+Projections!E36/(1+$B$9)^2+Projections!F36/(1+$B$9)^3+Projections!G36/(1+$B$9)^4+Projections!H36/(1+$B$9)^5+Projections!H36*(1+I$6)/($B$9-I$6)/(1+$B$9)^5,"err")
B10: =wacc_per_mgmt+(0)*sens_wacc_step | C10: =IFERROR(Projections!D36/(1+$B$10)^1+Projections!E36/(1+$B$10)^2+Projections!F36/(1+$B$10)^3+Projections!G36/(1+$B$10)^4+Projections!H36/(1+$B$10)^5+Projections!H36*(1+C$6)/($B$10-C$6)/(1+$B$10)^5,"err") | D10: =IFERROR(Projections!D36/(1+$B$10)^1+Projections!E36/(1+$B$10)^2+Projections!F36/(1+$B$10)^3+Projections!G36/(1+$B$10)^4+Projections!H36/(1+$B$10)^5+Projections!H36*(1+D$6)/($B$10-D$6)/(1+$B$10)^5,"err") | E10: =IFERROR(Projections!D36/(1+$B$10)^1+Projections!E36/(1+$B$10)^2+Projections!F36/(1+$B$10)^3+Projections!G36/(1+$B$10)^4+Projections!H36/(1+$B$10)^5+Projections!H36*(1+E$6)/($B$10-E$6)/(1+$B$10)^5,"err") | F10: =IFERROR(Projections!D36/(1+$B$10)^1+Projections!E36/(1+$B$10)^2+Projections!F36/(1+$B$10)^3+Projections!G36/(1+$B$10)^4+Projections!H36/(1+$B$10)^5+Projections!H36*(1+F$6)/($B$10-F$6)/(1+$B$10)^5,"err") | G10: =IFERROR(Projections!D36/(1+$B$10)^1+Projections!E36/(1+$B$10)^2+Projections!F36/(1+$B$10)^3+Projections!G36/(1+$B$10)^4+Projections!H36/(1+$B$10)^5+Projections!H36*(1+G$6)/($B$10-G$6)/(1+$B$10)^5,"err") | H10: =IFERROR(Projections!D36/(1+$B$10)^1+Projections!E36/(1+$B$10)^2+Projections!F36/(1+$B$10)^3+Projections!G36/(1+$B$10)^4+Projections!H36/(1+$B$10)^5+Projections!H36*(1+H$6)/($B$10-H$6)/(1+$B$10)^5,"err") | I10: =IFERROR(Projections!D36/(1+$B$10)^1+Projections!E36/(1+$B$10)^2+Projections!F36/(1+$B$10)^3+Projections!G36/(1+$B$10)^4+Projections!H36/(1+$B$10)^5+Projections!H36*(1+I$6)/($B$10-I$6)/(1+$B$10)^5,"err")
B11: =wacc_per_mgmt+(1)*sens_wacc_step | C11: =IFERROR(Projections!D36/(1+$B$11)^1+Projections!E36/(1+$B$11)^2+Projections!F36/(1+$B$11)^3+Projections!G36/(1+$B$11)^4+Projections!H36/(1+$B$11)^5+Projections!H36*(1+C$6)/($B$11-C$6)/(1+$B$11)^5,"err") | D11: =IFERROR(Projections!D36/(1+$B$11)^1+Projections!E36/(1+$B$11)^2+Projections!F36/(1+$B$11)^3+Projections!G36/(1+$B$11)^4+Projections!H36/(1+$B$11)^5+Projections!H36*(1+D$6)/($B$11-D$6)/(1+$B$11)^5,"err") | E11: =IFERROR(Projections!D36/(1+$B$11)^1+Projections!E36/(1+$B$11)^2+Projections!F36/(1+$B$11)^3+Projections!G36/(1+$B$11)^4+Projections!H36/(1+$B$11)^5+Projections!H36*(1+E$6)/($B$11-E$6)/(1+$B$11)^5,"err") | F11: =IFERROR(Projections!D36/(1+$B$11)^1+Projections!E36/(1+$B$11)^2+Projections!F36/(1+$B$11)^3+Projections!G36/(1+$B$11)^4+Projections!H36/(1+$B$11)^5+Projections!H36*(1+F$6)/($B$11-F$6)/(1+$B$11)^5,"err") | G11: =IFERROR(Projections!D36/(1+$B$11)^1+Projections!E36/(1+$B$11)^2+Projections!F36/(1+$B$11)^3+Projections!G36/(1+$B$11)^4+Projections!H36/(1+$B$11)^5+Projections!H36*(1+G$6)/($B$11-G$6)/(1+$B$11)^5,"err") | H11: =IFERROR(Projections!D36/(1+$B$11)^1+Projections!E36/(1+$B$11)^2+Projections!F36/(1+$B$11)^3+Projections!G36/(1+$B$11)^4+Projections!H36/(1+$B$11)^5+Projections!H36*(1+H$6)/($B$11-H$6)/(1+$B$11)^5,"err") | I11: =IFERROR(Projections!D36/(1+$B$11)^1+Projections!E36/(1+$B$11)^2+Projections!F36/(1+$B$11)^3+Projections!G36/(1+$B$11)^4+Projections!H36/(1+$B$11)^5+Projections!H36*(1+I$6)/($B$11-I$6)/(1+$B$11)^5,"err")
B12: =wacc_per_mgmt+(2)*sens_wacc_step | C12: =IFERROR(Projections!D36/(1+$B$12)^1+Projections!E36/(1+$B$12)^2+Projections!F36/(1+$B$12)^3+Projections!G36/(1+$B$12)^4+Projections!H36/(1+$B$12)^5+Projections!H36*(1+C$6)/($B$12-C$6)/(1+$B$12)^5,"err") | D12: =IFERROR(Projections!D36/(1+$B$12)^1+Projections!E36/(1+$B$12)^2+Projections!F36/(1+$B$12)^3+Projections!G36/(1+$B$12)^4+Projections!H36/(1+$B$12)^5+Projections!H36*(1+D$6)/($B$12-D$6)/(1+$B$12)^5,"err") | E12: =IFERROR(Projections!D36/(1+$B$12)^1+Projections!E36/(1+$B$12)^2+Projections!F36/(1+$B$12)^3+Projections!G36/(1+$B$12)^4+Projections!H36/(1+$B$12)^5+Projections!H36*(1+E$6)/($B$12-E$6)/(1+$B$12)^5,"err") | F12: =IFERROR(Projections!D36/(1+$B$12)^1+Projections!E36/(1+$B$12)^2+Projections!F36/(1+$B$12)^3+Projections!G36/(1+$B$12)^4+Projections!H36/(1+$B$12)^5+Projections!H36*(1+F$6)/($B$12-F$6)/(1+$B$12)^5,"err") | G12: =IFERROR(Projections!D36/(1+$B$12)^1+Projections!E36/(1+$B$12)^2+Projections!F36/(1+$B$12)^3+Projections!G36/(1+$B$12)^4+Projections!H36/(1+$B$12)^5+Projections!H36*(1+G$6)/($B$12-G$6)/(1+$B$12)^5,"err") | H12: =IFERROR(Projections!D36/(1+$B$12)^1+Projections!E36/(1+$B$12)^2+Projections!F36/(1+$B$12)^3+Projections!G36/(1+$B$12)^4+Projections!H36/(1+$B$12)^5+Projections!H36*(1+H$6)/($B$12-H$6)/(1+$B$12)^5,"err") | I12: =IFERROR(Projections!D36/(1+$B$12)^1+Projections!E36/(1+$B$12)^2+Projections!F36/(1+$B$12)^3+Projections!G36/(1+$B$12)^4+Projections!H36/(1+$B$12)^5+Projections!H36*(1+I$6)/($B$12-I$6)/(1+$B$12)^5,"err")
B13: =wacc_per_mgmt+(3)*sens_wacc_step | C13: =IFERROR(Projections!D36/(1+$B$13)^1+Projections!E36/(1+$B$13)^2+Projections!F36/(1+$B$13)^3+Projections!G36/(1+$B$13)^4+Projections!H36/(1+$B$13)^5+Projections!H36*(1+C$6)/($B$13-C$6)/(1+$B$13)^5,"err") | D13: =IFERROR(Projections!D36/(1+$B$13)^1+Projections!E36/(1+$B$13)^2+Projections!F36/(1+$B$13)^3+Projections!G36/(1+$B$13)^4+Projections!H36/(1+$B$13)^5+Projections!H36*(1+D$6)/($B$13-D$6)/(1+$B$13)^5,"err") | E13: =IFERROR(Projections!D36/(1+$B$13)^1+Projections!E36/(1+$B$13)^2+Projections!F36/(1+$B$13)^3+Projections!G36/(1+$B$13)^4+Projections!H36/(1+$B$13)^5+Projections!H36*(1+E$6)/($B$13-E$6)/(1+$B$13)^5,"err") | F13: =IFERROR(Projections!D36/(1+$B$13)^1+Projections!E36/(1+$B$13)^2+Projections!F36/(1+$B$13)^3+Projections!G36/(1+$B$13)^4+Projections!H36/(1+$B$13)^5+Projections!H36*(1+F$6)/($B$13-F$6)/(1+$B$13)^5,"err") | G13: =IFERROR(Projections!D36/(1+$B$13)^1+Projections!E36/(1+$B$13)^2+Projections!F36/(1+$B$13)^3+Projections!G36/(1+$B$13)^4+Projections!H36/(1+$B$13)^5+Projections!H36*(1+G$6)/($B$13-G$6)/(1+$B$13)^5,"err") | H13: =IFERROR(Projections!D36/(1+$B$13)^1+Projections!E36/(1+$B$13)^2+Projections!F36/(1+$B$13)^3+Projections!G36/(1+$B$13)^4+Projections!H36/(1+$B$13)^5+Projections!H36*(1+H$6)/($B$13-H$6)/(1+$B$13)^5,"err") | I13: =IFERROR(Projections!D36/(1+$B$13)^1+Projections!E36/(1+$B$13)^2+Projections!F36/(1+$B$13)^3+Projections!G36/(1+$B$13)^4+Projections!H36/(1+$B$13)^5+Projections!H36*(1+I$6)/($B$13-I$6)/(1+$B$13)^5,"err")
A15: Highlighted cell = base case (current wacc_per_mgmt and terminal_growth_rate). EV in (currency × unit). Values do not include the EV→Equity bridge — apply surplus / debt / DLOM / DLOC manually for equity sensitivity.

Sheet Valuation Summary
A1: Valuation Summary
A2: Headline outputs across both scenarios. Per-share values convert from (currency × unit) to actual currency using the unit selected on Inputs.
A4: Metric | B4: Unit | C4: Per Management | D4: Independent | E4: Average
A6: Headline values
A7: Enterprise Value | B7: (currency × unit) | C7: =Adjustments!C7 | D7: =Adjustments!D7 | E7: =AVERAGE(C7:D7)
A8: Equity value (pre-discounts) | B8: (currency × unit) | C8: =Adjustments!C12 | D8: =Adjustments!D12 | E8: =AVERAGE(C8:D8)
A9: Equity value after DLOM | B9: (currency × unit) | C9: =Adjustments!C17 | D9: =Adjustments!D17 | E9: =AVERAGE(C9:D9)
A10: Equity value after DLOM and DLOC | B10: (currency × unit) | C10: =Adjustments!C20 | D10: =Adjustments!D20 | E10: =AVERAGE(C10:D10)
A11: Fair value of client's interest | B11: (currency × unit) | C11: =Adjustments!C24 | D11: =Adjustments!D24 | E11: =AVERAGE(C11:D11)
A13: Per-share value
A14: Unit multiplier (to actual currency) | B14: x | C14: =IF(EXACT(unit,"'000"),1000,IF(EXACT(unit,"million"),1000000,1)) | D14: =IF(EXACT(unit,"'000"),1000,IF(EXACT(unit,"million"),1000000,1))
A15: Shares outstanding (basic) | B15: shares | C15: =shares_outstanding | D15: =shares_outstanding
A16: Equity value per share (basic) | B16: actual currency | C16: =IFERROR(Adjustments!C20*C14/C15,0) | D16: =IFERROR(Adjustments!D20*D14/D15,0) | E16: =AVERAGE(C16:D16)
A17: Shares outstanding (diluted) | B17: shares | C17: =shares_outstanding_diluted | D17: =shares_outstanding_diluted
A18: Equity value per share (diluted) | B18: actual currency | C18: =IFERROR(Adjustments!C20*C14/C17,0) | D18: =IFERROR(Adjustments!D20*D14/D17,0) | E18: =AVERAGE(C18:D18)
A20: Discount rate inputs (reference)
A21: WACC | B21: % | C21: =wacc_per_mgmt | D21: =wacc_indep
A22: Terminal growth rate | B22: % | C22: =terminal_growth_rate | D22: =terminal_growth_rate

Sheet _dropdowns
A1: report_purpose | B1: accounting_standard | C1: tax_type | D1: terminal_method | E1: currency | F1: unit | G1: coco_tier | H1: revenue_growth_method
A2: BEV review | B2: IFRS | C2: flat | D2: gordon_growth | E2: USD | F2: '000 | G2: 1 | H2: flat
A3: IPO pricing | B3: US GAAP | C3: two_tier | D3: exit_multiple | E3: HKD | F3: million | G3: 2 | H3: declining
A4: Fairness opinion | B4: IFRS 9 + IFRS 13 | C4: progressive | E4: SGD | F4: actual | G4: 3 | H4: staged
A5: M&A | E5: MYR | G5: Excluded | H5: per_year
A6: Fundraising | E6: CNY
E7: JPY
E8: KRW
E9: EUR
E10: GBP
E11: AUD
